Workbook

Sheet Dash_Lojas
A1: Digite o número
B3: =VLOOKUP($A$7,Info_Loja!$A$2:$L$233,2,FALSE) -> Shopping Piracicaba | E3: =VLOOKUP($A$7,Info_Loja!$A$2:$L$233,11,FALSE) -> SP | H3: IP | I3: =VLOOKUP($A$7,'Detalhes Links Lojas'!$A$2:$AC$216,29,FALSE) -> 129.145.0.0/16 | K3: IP Loopback | L3: =VLOOKUP($A$7,'Detalhes Links Lojas'!$A$2:$AC$216,28,FALSE) -> 10.100.10.69
A6: Loja | B6: Links | H6: Telefonia Fixa | K6: N/S Fortigate | L6: =VLOOKUP($A$7,'Detalhes Links Lojas'!$A$2:$AF$216,32,FALSE) -> FGT40FTK21028599
A7: 580 | B7: Dados | C7: Link 1 | D7: Link 2 | E7: 3° Link Backup | F7: Custo Extra | H7: Linha | I7: =VLOOKUP($A$7,'Telefonia Fixa'!$A$2:$C$234,3,FALSE) -> (19) 3412-1700
B8: Operadora | C8: =VLOOKUP($A$7,'Detalhes Links Lojas'!$A$2:$AA$216,4,FALSE) -> Claro | D8: =VLOOKUP($A$7,'Detalhes Links Lojas'!$A$2:$AA$216,12,FALSE) -> Vivo | E8: =VLOOKUP($A$7,'Detalhes Links Lojas'!$A$2:$AA$216,22,FALSE) -> --- | F8: =VLOOKUP($A$7,'Detalhes Links Lojas'!$A$2:$AA$216,26,FALSE) -> --- | H8: Operadora | I8: =VLOOKUP($A$7,'Telefonia Fixa'!$A$2:$F$234,6,TRUE) -> - | K8: Custo Total | L8: =SUM(C14+I9+D20) -> 534.26
B9: Velocidade | C9: =VLOOKUP($A$7,'Detalhes Links Lojas'!$A$2:$AA$216,9,FALSE) -> 20Mb | D9: =VLOOKUP($A$7,'Detalhes Links Lojas'!$A$2:$AA$216,17,FALSE) -> 600Mb | E9: =VLOOKUP($A$7,'Detalhes Links Lojas'!$A$2:$AA$216,24,FALSE) -> 0 | H9: Valor | I9: =VLOOKUP($A$7,'Telefonia Fixa'!$A$2:$F$234,5,FALSE) -> 0
B10: Tecnologia | C10: =VLOOKUP($A$7,'Detalhes Links Lojas'!$A$2:$AA$216,10,FALSE) -> Dedicado | D10: =VLOOKUP($A$7,'Detalhes Links Lojas'!$A$2:$AA$216,18,FALSE) -> ADSL | E10: =VLOOKUP($A$7,'Detalhes Links Lojas'!$A$2:$AA$216,21,FALSE) -> --- | H10: Telefonia IP
B11: Designação | C11: =VLOOKUP($A$7,'Detalhes Links Lojas'!$A$2:$AA$216,8,FALSE) -> PAA/IP/03834 | D11: =VLOOKUP($A$7,'Detalhes Links Lojas'!$A$2:$AA$216,16,FALSE) -> PAA-817JDDTYE3-013 | E11: =VLOOKUP($A$7,'Detalhes Links Lojas'!$A$2:$AA$216,23,FALSE) -> ---
B12: Vigência | C12: =VLOOKUP($A$7,'Detalhes Links Lojas'!$A$2:$AA$216,7,FALSE) -> 47078 | D12: =VLOOKUP($A$7,'Detalhes Links Lojas'!$A$2:$AA$216,15,FALSE) -> 46674 | H12: Linha | I12: =VLOOKUP($A$7,'Telefonia Ip - Lojas'!$A$2:$H$232,6,FALSE) -> 11 2109-3007
B13: Valor | C13: =VLOOKUP($A$7,'Detalhes Links Lojas'!$A$2:$AA$216,11,FALSE) -> 439.27 | D13: =VLOOKUP($A$7,'Detalhes Links Lojas'!$A$2:$AA$216,19,FALSE) -> 94.99 | E13: =VLOOKUP($A$7,'Detalhes Links Lojas'!$A$2:$AA$216,25,FALSE) -> 0 | F13: =VLOOKUP($A$7,'Detalhes Links Lojas'!$A$2:$AA$216,27,FALSE) -> 0 | H13: Qtd ramais | I13: =VLOOKUP($A$7,'Telefonia Ip - Lojas'!$A$2:$H$232,5,FALSE) -> 1
B14: Total | C14: =SUM(C13+D13+E13+F13) -> 534.26
B17: Telefonia Móvel | F17: Aps | K17: Switches
B18: Número | C18: Operadora | D18: Valor | F18: Tecnologia | G18: Marca/Modelo | H18: Qtde | K18: Modelo | L18: IP | M18: Qtde
B19: =VLOOKUP($A$7,'Telefonia Móvel'!$A$2:$H$236,7,FALSE) -> - | C19: =VLOOKUP($A$7,'Telefonia Móvel'!$A$4:$H$236,2,FALSE) -> - | D19: =VLOOKUP($A$7,'Telefonia Móvel'!$A$2:$H$236,8,FALSE) -> 0 | F19: =VLOOKUP(A7,'[1]Antenas Lojas'!$A$3:$H$235,7,FALSE) -> IAP | G19: =VLOOKUP(A7,'[1]Antenas Lojas'!$A$3:$H$235,8,FALSE) -> Aruba - 205 Aruba - 205 Aruba - 205 Aruba - 205 Aruba - 205 Aruba - 205 | H19: =VLOOKUP(A7,'[1]Antenas Lojas'!$A$3:$H$235,6,FALSE) -> 6 | K19: =VLOOKUP(A7,'[1]Switches Lojas'!$A$3:$D$239,2,FALSE) -> HPE OfficeConnect Switch 1920S HPE OfficeConnect Switch 1920S | L19: =VLOOKUP(A7,'[1]Switches Lojas'!$A$3:$D$239,3,FALSE) -> 129.145.0.8 129.145.0.9 | M19: =VLOOKUP(A7,'[1]Switches Lojas'!$A$3:$D$239,4,FALSE) -> 2
C20: Valor | D20: =VLOOKUP(A7,'Telefonia Móvel'!A2:P236,16,FALSE) -> 0

Sheet Info_Loja
A1: IDLoja | B1: Nome Filial | C1: Telefone Marisa | D1: Tipo | E1: Logradouro | F1: Núm. | G1: Complemento | H1: CEP | I1: Bairro | J1: Cidade | K1: UF | L1: Região Geográfica
A2: 22 | B2: Azenha | C2: (51) 3275-8980 | D2: Rua | E2: Rua da Azenha | F2: 795 | H2: 90160-002 | I2: Azenha | J2: Porto Alegre | K2: RS | L2: Sul
A3: 43 | B3: São Caetano do Sul | C3: (11) 4228-7820 | D3: Rua | E3: R. Manoel Coelho | F3: 316 | G3: 318, 32 E328 | H3: 09510-100 | I3: Centro | J3: São Caetano do Sul | K3: SP | L3: Sudeste
A4: 80 | B4: Campina Grande | C4: (83) 3182-4800 | D4: Rua | E4: R. Maciel Pinheiro | F4: 185 | H4: 58400-100 | I4: Centro | J4: Campina Grande | K4: PB | L4: Nordeste
A5: 87 | B5: Teresina (Centro) | C5: (86) 3302-6104 | D5: Rua | E5: R. Senador Teodoro Pacheco | F5: 1074 | H5: 64001-060 | I5: Centro | J5: Teresina | K5: PI | L5: Nordeste
A6: 120 | B6: São Luiz | C6: (98) 3878-6950 | D6: Rua | E6: R. Grande Oswaldo Cruz | F6: 523 | H6: 65020-250 | I6: Centro | J6: São Luís | K6: MA | L6: Nordeste
A7: 125 | B7: Aracajú | C7: (11) 2109-3045 | D7: Rua | E7: R. João Pessoa | F7: 45 | H7: 49010-130 | I7: Centro | J7: Aracaju | K7: SE | L7: Nordeste
A8: 130 | B8: Florianópolis | C8: (48) 3878-2150 | D8: Rua | E8: Praça XV de Novembro | F8: 111 | H8: 88010-400 | I8: Centro | J8: Florianópolis | K8: SC | L8: Sul
A9: 133 | B9: Shopping Interlagos | C9: (11) 2138-8159 | D9: Shopping | E9: Av. Interlagos | F9: 2255 | H9: 04661-200 | I9: Campo Grande | J9: São Paulo | K9: SP | L9: Sudeste
A10: 135 | B10: Shopping Mueller Joinville | C10: (47) 3803-6550 | D10: Shopping | E10: R. Visconde de Taunay | F10: 234 | H10: 89201-430 | I10: Centro | J10: Joinville | K10: SC | L10: Sul
A11: 136 | B11: Shopping Metrópole | C11: (11) 2138-8534 | D11: Shopping | E11: Pça. Samuel Sabatini | F11: 200 | H11: 09750-902 | I11: Centro | J11: São Bernardo do Campo | K11: SP | L11: Sudeste
A12: 140 | B12: River Shopping | C12: (87) 3201-3984 | D12: Shopping | E12: Av. Mons. Ângelo Sampaio | F12: 100 | G12: lj. 87/88 | H12: 56304-160 | I12: Centro | J12: Petrolina | K12: PE | L12: Nordeste
A13: 142 | B13: Norte Shopping | C13: (21) 2187-7600 | D13: Shopping | E13: Av. Dom Hélder Câmara | F13: 5332 | G13: Salões Comerciais 357/ 358 / 359 / 377/A - Piso S - Norte Shopping | H13: 20771-004 | I13: Cachambi | J13: Rio de Janeiro | K13: RJ | L13: Sudeste
A14: 150 | B14: Pátio Brasil Shopping | C14: (61) 3521-9906 | D14: Shopping | E14: Setor Comercial Sul | F14: Q. 07 | G14: Bloco A, Piso Térreo T3- Loja 1t | H14: 70310-500 | I14: Asa Sul | J14: Brasília | K14: DF | L14: Centro-Oeste
A15: 160 | B15: Riverside Shopping | C15: (86) 3301-2530 | D15: Shopping | E15: Av. Ininga | F15: 1201 | G15: LJ H15/23 E J39/47 | H15: 64046-010 | I15: Jockey Club | J15: Teresina | K15: PI | L15: Nordeste
A16: 165 | B16: Grand Plaza Shopping | C16: (11) 2109-3194 | D16: Shopping | E16: Av. Industrial | F16: 600 | G16: lj. 124 - Bairro Jardim | H16: 09080-500 | I16: Jardim | J16: Santo André | K16: SP | L16: Sudeste
A17: 176 | B17: Internacional Shopping | C17: (11) 2109-6112 | D17: Shopping | E17: Rod. Presidente Dutra KM 397/650 | F17: s/n | G17: Km 397/65 | H17: 07042-050 | I17: Lj B 18 Piso Terreo | J17: Guarulhos | K17: SP | L17: Sudeste
A18: 178 | B18: Buriti Shopping | C18: (62) 3625-7180 | D18: Shopping | E18: Av. Rio Verde | F18: 1 | G18: Qd. 12 / 14 - Loja 153 | H18: 74840-150 | I18: Vila São Tomas | J18: Goiânia | K18: GO | L18: Centro-Oeste
A19: 180 | B19: Litoral Plaza Shopping | C19: (13) 3476-1283 | D19: Shopping | E19: Av. Ayrton Senna | F19: 1511 | G19: Lojas 28, 29, 3 e 31, Xixová | H19: 11726-500 | I19: Sitio do Campo | J19: Praia Grande | K19: SP | L19: Sudeste
A20: 196 | B20: Manaíra Shopping | C20: (83) 3533-4351 | D20: Shopping | E20: R. Manoel Arruda Cavalcante | F20: 805 | G20: Av Gov. Flavio Ribeiro Coutinho - 2º Piso | H20: 58038-680 | I20: Manaira | J20: João Pessoa | K20: PB | L20: Nordeste
A21: 508 | B21: Alameda Shopping | C21: (61) 2102-1314 | D21: Shopping | E21: Estr. Shopping Center Csb | F21: 2 | G21: Lotes 1/2/3/4 - Loja T13, T15 e T15A | H21: 72015-901 | I21: Centro | J21: Brasília | K21: DF | L21: Centro-Oeste
A22: 510 | B22: Shopping Aricanduva | C22: (11) 2109-3178 | D22: Shopping | E22: Av. Aricanduva | F22: 5555 | G22: Âncora 5-Shop. C. Leste | H22: 03527-900 | I22: Jardim Colorado | J22: São Paulo | K22: SP | L22: Sudeste
A23: 512 | B23: Cuiabá | C23: (65) 3928-3249 | D23: Rua | E23: R. Treze de Junho | F23: 265 | H23: 78005-410 | I23: Centro | J23: Cuiabá | K23: MT | L23: Centro-Oeste
A24: 514 | B24: Macapá | C24: (96) 2101-8850 | D24: Rua | E24: R. Cândido Mendes | F24: 1280 | H24: 68900-100 | I24: Centro | J24: Macapá | K24: AP | L24: Norte
A25: 515 | B25: Santo Amaro | C25: (11) 2109-6466 | D25: Rua | E25: Av. Adolfo Pinheiro | F25: 62 | H25: 04734-000 | I25: Santo Amaro | J25: São Paulo | K25: SP | L25: Sudeste
A26: 517 | B26: Rio Branco | C26: (68) 3303-8980 | D26: Rua | E26: Av. Getúlio Vargas | F26: 258 | H26: 69900-060 | I26: Centro | J26: Rio Branco | K26: AC | L26: Norte
A27: 518 | B27: Diadema | C27: (11) 2109-3171 | D27: Rua | E27: Av. Pres. Kennedy | F27: 99 | G27: Av. São José, 26 | H27: 09913-000 | I27: Centro | J27: Diadema | K27: SP | L27: Sudeste
A28: 519 | B28: Porto Velho | C28: (69) 2182-4380 | D28: Rua | E28: Av. Sete de Setembro | F28: 941 | G28: e 941-A | H28: 76801-073 | I28: Centro | J28: Porto Velho | K28: RO | L28: Norte
A29: 520 | B29: Mauá Plaza Shopping | C29: (11) 2109-6054 | D29: Shopping | E29: Av. Antonia Rosa Fioravanti | F29: 3000 | G29: 327 e 338 | H29: 09390-120 | I29: Centro | J29: Mauá | K29: SP | L29: Sudeste
A30: 525 | B30: Sh Rio Mar Aracajú | C30: (79) 3711-2770 | D30: Shopping | E30: R. Delmiro Gouveia | F30: 0 | G30: S/N - Loja Ancora "A" | H30: 49035-900 | I30: Coroa do Meio | J30: Aracaju | K30: SE | L30: Nordeste
A31: 526 | B31: Canoas Shopping | C31: (51) 2102-7280 | D31: Shopping | E31: Av. Guilherme Schell | F31: 6750 | H31: 92310-001 | I31: Centro | J31: Canoas | K31: RS | L31: Sul
A32: 527 | B32: North Shopping Fortaleza | C32: (85) 3392-3684 | D32: Shopping | E32: Av. Bezerra de Menezes | F32: 2450 | G32: lj. 8 1º Piso | H32: 60325-902 | I32: Centro | J32: Fortaleza | K32: CE | L32: Nordeste
A33: 529 | B33: São Leopoldo | C33: (11) 2138-8537 | D33: Rua | E33: R. Independência | F33: 906 | H33: 93010-003 | I33: Centro | J33: São Leopoldo | K33: RS | L33: Sul
A34: 531 | B34: Via Shopping Barreiro | C34: (31) 3211-7350 | D34: Shopping | E34: Av. Afonso Vaz Melo | F34: 640 | G34: Ljs. 235 e 243 | H34: 30640-070 | I34: Barreiro | J34: Belo Horizonte | K34: MG | L34: Sudeste
A35: 534 | B35: Maxi Shopping Jundiaí | C35: (11) 4583-6683 | D35: Shopping | E35: Av. Antonio Frederico Ozanam | F35: 6000 | G35: SUC 14 - 1º PISO | H35: 13215-900 | I35: Vila Rio Branco | J35: Jundiaí | K35: SP | L35: Sudeste
A36: 535 | B36: São José dos Pinhais | C36: (41) 3311-7630 | D36: Rua | E36: R. Quinze de Novembro | F36: 1795 | H36: 83005-000 | I36: Centro | J36: São José dos Pinhais | K36: PR | L36: Sul
A37: 536 | B37: BH Centro | C37: (31) 3242-8500 | D37: Rua | E37: R. Carijós | F37: 645 | H37: 30120-060 | I37: Centro | J37: Belo Horizonte | K37: MG | L37: Sudeste
A38: 543 | B38: Campo Grande | C38: (21) 3622-8730 | D38: Rua | E38: R. Cel. Agostinho | F38: 146 | H38: 23050-360 | I38: Campo Grande | J38: Rio de Janeiro | K38: RJ | L38: Sudeste | M38: encerrada
A39: 544 | B39: Shopping Penha | C39: (11) 2109-6021 | D39: Shopping | E39: R. Dr. João Ribeiro | F39: 304 | G39: SUC 1711/1712 | H39: 03634-900 | I39: Penha de Franca | J39: São Paulo | K39: SP | L39: Sudeste
A40: 546 | B40: São Bernardo | C40: (11) 2109-3172 | D40: Rua | E40: R. Mal. Deodoro | F40: 900 | H40: 09710-001 | I40: Centro | J40: São Bernardo do Campo | K40: SP | L40: Sudeste
A41: 547 | B41: Gonzaga | C41: (13) 3208-6481 | D41: Rua | E41: Av. Mal. Floriano Peixoto | F41: 59 | H41: 11060-301 | I41: Centro | J41: Santos | K41: SP | L41: Sudeste
A42: 548 | B42: Curitiba | C42: (11) 2138-8530 | D42: Rua | E42: R. Xv de Novembro | F42: 225 | G42: nº 257 - 1º, 2º e 3º andar. | H42: 80020-310 | I42: Centro | J42: Curitiba | K42: PR | L42: Sul
A43: 549 | B43: Novo Shopping Center Ribeirão Preto | C43: (16) 3965-8510 | D43: Shopping | E43: Av. Pres. Kennedy | F43: 1500 | H43: 14096-970 | I43: Ribeirania | J43: Ribeirão Preto | K43: SP | L43: Sudeste
A44: 550 | B44: Guarulhos | C44: (11) 2109-6017 | D44: Rua | E44: R. D. Pedro II | F44: 27 | G44: 31 e 35 | H44: 07010-003 | I44: Centro | J44: Guarulhos | K44: SP | L44: Sudeste
A45: 553 | B45: Midway Mall | C45: (84) 3344-7235 | D45: Shopping | E45: Av. Bernardo Vieira | F45: 3775 | G45: 3775 - piso L2 - EUC´s 253 e 253A - Tirol | H45: 59015-900 | I45: Tirol | J45: Natal | K45: RN | L45: Nordeste
A46: 558 | B46: Manaus | C46: (92) 3303-9430 | D46: Rua | E46: Av. Eduardo Ribeiro | F46: 390 | G46: e 46 | H46: 69005-160 | I46: Centro | J46: Manaus | K46: AM | L46: Norte
A47: 559 | B47: Osasco Plaza Shopping | C47: (11) 2109-3173 | D47: Shopping | E47: R. Ten. Avelar Pires de Azevedo | F47: 81 | G47: lj. 11, 12, 19 e 191 PS Térreo e 31 PS Superior | H47: 06016-060 | I47: Centro | J47: Osasco | K47: SP | L47: Sudeste
A48: 560 | B48: Castanheira Shopping Center | C48: (91) 3344-5080 | D48: Shopping | E48: Rod. Br. 316 | F48: 0 | G48: Km 1 s/n.º EUC 117 / 119 / 122 / 124 e Expanção | H48: 66645-900 | I48: Atalaia | J48: Belém | K48: PA | L48: Norte
A49: 563 | B49: Santana | C49: (11) 2138-8506 | D49: Rua | E49: R. Leite de Moraes | F49: 112 | G49: E 12 | H49: 02034-020 | I49: Santana | J49: São Paulo | K49: SP | L49: Sudeste
A50: 564 | B50: São Miguel Paulista | C50: (11) 2138-8517 | D50: Rua | E50: R. Serra Dourada | F50: 102 | G50: E 11 | H50: 08010-000 | I50: Sao Miguel Paulista | J50: São Paulo | K50: SP | L50: Sudeste
A51: 565 | B51: Shopping Guararapes | C51: (81) 3201-7250 | D51: Shopping | E51: Av. Gen. Barreto de Menezes | F51: 800 | G51: SUC's nº 99/1/11/12 A-B-C - Piedade | H51: 54410-100 | I51: Alto Guararapes | J51: Jaboatão dos Guararapes | K51: PE | L51: Nordeste
A52: 566 | B52: Maceió Shopping | C52: (82) 3214-6550 | D52: Shopping | E52: Av. Gustavo Paiva | F52: 2990 | G52: Espaço Comercial Âncora H-2.º Piso | H52: 57032-901 | I52: Mangabeiras | J52: Maceió | K52: AL | L52: Nordeste
A53: 568 | B53: Fortaleza | C53: (85) 3521-4950 | D53: Rua | E53: R. Maj. Facundo | F53: 532 | H53: 60025-100 | I53: Centro | J53: Fortaleza | K53: CE | L53: Nordeste
A54: 571 | B54: Shopping Do Vale | C54: (51) 3533-6680 | D54: Shopping | E54: Av. Flores da Cunha | F54: 4001 | G54: lj.279/28/281 | H54: 94950-000 | I54: Centro | J54: Cachoeirinha | K54: RS | L54: Sul
A55: 573 | B55: Santo André | C55: (11) 2138-8510 | D55: Rua | E55: R. Cel. Oliveira Lima | F55: 395 | H55: 09010-000 | I55: Centro | J55: Santo André | K55: SP | L55: Sudeste
A56: 575 | B56: Alcântara | C56: (21) 3575-7401 | D56: Rua | E56: R. Dr. Alfredo Backer | F56: 689 | H56: 24452-001 | I56: Alcantrara | J56: São Gonçalo | K56: RJ | L56: Sudeste
A57: 576 | B57: Parque Dom Pedro Shopping | C57: (19) 3709-9080 | D57: Shopping | E57: Av. Guilherme Campos | F57: 500 | G57: EUC nº âncora A-2 | H57: 13087-901 | I57: Jardim Sta Genebra | J57: Campinas | K57: SP | L57: Sudeste
A58: 577 | B58: Mogi Shopping | C58: (11) 4728-3172 | D58: Shopping | E58: Av. Ver. Narciso Yague Guimaraes | F58: 1001 | G58: Area Comerc A17 | H58: 08780-910 | I58: Jd Armenia | J58: Mogi das Cruzes | K58: SP | L58: Sudeste
A59: 578 | B59: Farol Shopping | C59: (48) 3301-3150 | D59: Shopping | E59: Av. Marcolino Martins Cabral | F59: 2525 | G59: SUC Nº ÂNCORA A 4 | H59: 88705-003 | I59: Aeroporto | J59: Tubarão | K59: SC | L59: Sul
A60: 579 | B60: Shopping Campo Limpo | C60: (11) 2138-8508 | D60: Shopping | E60: R. Estrada do Campo Limpo | F60: 459 | G60: EUC A4/A5 e 354-OS-C.C/A4-Itap.A5/EUC 354 | H60: 05777-001 | I60: Santo Amaro | J60: São Paulo | K60: SP | L60: Sudeste
A61: 580 | B61: Shopping Piracicaba | C61: (19) 3412-1700 | D61: Shopping | E61: Av. Limeira | F61: 722 | H61: 13414-018 | I61: Centro | J61: Piracicaba | K61: SP | L61: Sudeste
A62: 582 | B62: Porto Alegre (Centro) | C62: (51) 3396-5820 | D62: Rua | E62: R. Voluntários da Pátria | F62: 167 | H62: 90030-002 | I62: Centro | J62: Porto Alegre | K62: RS | L62: Sul
A63: 583 | B63: Shopping Delrey | C63: (31) 3048-4080 | D63: Shopping | E63: Av. Pres. Carlos Luz | F63: 3001 | G63: SALÕES COMERCIAIS 314 / 316 / 336 e R2 - 3º PISO | H63: 31310-250 | I63: Engenho Nogueira | J63: Belo Horizonte | K63: MG | L63: Sudeste
A64: 586 | B64: Sh Metrô Boulevard Tatuapé | C64: (11) 2109-3174 | D64: Shopping | E64: R. Gonçalves Crespo | F64: 78 | G64: Loja 23B/24b/ 21B - 1pav. (PS metro) e Loja 31 / 33 - 2pavimento | H64: 03066-030 | I64: Tatuape | J64: São Paulo | K64: SP | L64: Sudeste
A65: 589 | B65: Maceió | C65: (82) 3312-1880 | D65: Rua | E65: R. do Comércio | F65: 352 | H65: 57020-000 | I65: Centro | J65: Maceió | K65: AL | L65: Nordeste
A66: 590 | B66: Big Shopping | C66: (31) 3358-3500 | D66: Shopping | E66: Av. João C. de Oliveira | F66: 1275 | G66: lj. 293 | H66: 32310-220 | I66: Centro | J66: Contagem | K66: MG | L66: Sudeste
A67: 594 | B67: Floripa Shopping | C67: (48) 3231-3100 | D67: Shopping | E67: Rod. Virgilio Várzea | F67: 587 | G67: Àrea 2- Bairro Saco Grande II | H67: 88032-000 | I67: Saco Grande | J67: Florianópolis | K67: SC | L67: Sul
A68: 597 | B68: Nova Iguaçu | C68: (21) 3575-5060 | D68: Rua | E68: Av. Nilo Peçanha | F68: 163 | H68: 26210-011 | I68: Centro | J68: Nova Iguaçu | K68: RJ | L68: Sudeste
A69: 598 | B69: Shopping Avenida Center | C69: (67) 2108-3380 | D69: Shopping | E69: Av. Marcelino Pires | F69: 3600 | G69: Ljs. A1, A2 e A3 | H69: 79830-903 | I69: Cabaceira Alegre | J69: Dourados | K69: MS | L69: Centro-Oeste
A70: 599 | B70: Ponta Grossa | C70: (42) 3302-2150 | D70: Rua | E70: R. Coronel Cláudio | F70: 175 | G70: Loja 4 | H70: 84010-120 | I70: Centro | J70: Ponta Grossa | K70: PR | L70: Sul
A71: 600 | B71: Salvador Shopping | C71: (71) 3617-4830 | D71: Shopping | E71: Av. Tancredo Neves | F71: 2915 | G71: Salão Comercial 162- Setor Comercial 114- Piso 1 | H71: 41820-021 | I71: Caminho das Arvores | J71: Salvador | K71: BA | L71: Nordeste
A72: 601 | B72: Shopping Recife | C72: (11) 2109-3191 | D72: Shopping | E72: R. Padre Carapuceiro | F72: 777 | G72: Espaços Comerciais PC 157/158 - Piso Padre Carapuceiro | H72: 51020-900 | I72: Boa Viagem | J72: Recife | K72: PE | L72: Nordeste
A73: 604 | B73: Vitória da Conquista | C73: (77) 3201-7180 | D73: Rua | E73: R. Monsenhor Olímpio | F73: 106 | H73: 45015-300 | I73: Centro | J73: Vitória da Conquista | K73: BA | L73: Nordeste
A74: 605 | B74: Shopping Avenida Center | C74: (44) 3355-4550 | D74: Shopping | E74: Av. São Paulo | F74: 458 | G74: Loja B-13 Piso Superior e Loja I- 115- Shopping Av. Center | H74: 87013-929 | I74: Zona Armagem | J74: Maringá | K74: PR | L74: Sul
A75: 606 | B75: Shopping Vale do Aço | C75: (31) 3094-2100 | D75: Shopping | E75: Av. Pedro Linhares | F75: 3900 | G75: LJS 1/2/3/82- Shopping Vale do Aço | H75: 35160-290 | I75: Horto | J75: Ipatinga | K75: MG | L75: Sudeste
A76: 607 | B76: Pátio Limeira Shopping | C76: (19) 3404-4180 | D76: Shopping | E76: R. Carlos Gomes | F76: 1321 | G76: Lj 12/13/13A;14 -CENTRAL PLAZA | H76: 13480-013 | I76: Centro | J76: Limeira | K76: SP | L76: Sudeste
A77: 608 | B77: Taubaté Shopping | C77: (12) 2125-2350 | D77: Shopping | E77: Av. Charles Schnneider | F77: 1700 | G77: ancora A8 Taubaté Shopping Center Taubaté | H77: 12040-900 | I77: Parque Senhor do Bonfim | J77: Taubaté | K77: SP | L77: Sudeste
A78: 610 | B78: Partage Shopping Campina Grande | C78: (83) 2102-2254 | D78: Shopping | E78: Av. Pref. Severino Bezerra Cabral | F78: 1190 | G78: Sala Comercial 242 PS 1 | H78: 58407-475 | I78: Jose Pinheiro | J78: Campina Grande | K78: PB | L78: Nordeste
A79: 613 | B79: Itaim Paulista | C79: (11) 2109-3170 | D79: Rua | E79: Av. Marechal Tito | F79: 4265 | H79: 08115-100 | I79: Itaim Paulista | J79: São Paulo | K79: SP | L79: Sudeste
A80: 617 | B80: Goiânia | C80: (62) 3878-3200 | D80: Rua | E80: Av. Vinte e Quatro de Outubro | F80: 347 | G80: Sala Comercial 242 PS 1 | H80: 74505-011 | I80: Aeroviário | J80: Goiânia | K80: GO | L80: Centro-Oeste
A81: 618 | B81: Shopping Jequitiba | C81: (11) 2109-6291 | D81: Shopping | E81: Av. Aziz Maron | F81: 0 | G81: S/N - Loja 25,26 e 27 - Piso Térreo | H81: 45605-415 | I81: Goes Calmon | J81: Itabuna | K81: BA | L81: Nordeste
A82: 619 | B82: Shopping Bonsucesso | C82: (11) 2109-6486 | D82: Shopping | E82: Estr. Juscelino Kubitschek de Oliveira | F82: 5308 | G82: Loja D - Shopping Bonsucesso | H82: 07252-000 | I82: Loja D Shop Bonsucesso | J82: Guarulhos | K82: SP | L82: Sudeste
A83: 622 | B83: Shopping Metrô Tucuruvi | C83: (11) 2109-3014 | D83: Shopping | E83: Av. Dr. Antônio Maria Laet | F83: 566 | G83: Salão Comercial n.º L 27/T- Piso Térreo- Shopping Metrô Tucuruvi | H83: 02240-000 | I83: Tucuruvi | J83: São Paulo | K83: SP | L83: Sudeste
A84: 623 | B84: Caruaru Shopping | C84: (81) 2103-2350 | D84: Shopping | E84: Av. Adjar da Silva Casé | F84: 800 | G84: ECL 5- Âncora Shopping Center Caruaru | H84: 55024-901 | I84: Indianopolis | J84: Caruaru | K84: PE | L84: Nordeste
A85: 624 | B85: Shopping Vale Sul | C85: (12) 3878-7810 | D85: Shopping | E85: Av. Andrômeda | F85: 227 | G85: SUC 16- Vale Sul Shopping | H85: 12230-000 | I85: Jardim Satelite | J85: São José dos Campos | K85: SP | L85: Sudeste
A86: 625 | B86: Campo Grande | C86: (67) 3303-3352 | D86: Rua | E86: R. D. Aquino | F86: 1355 | H86: 79002-185 | I86: Centro | J86: Campo Grande | K86: MS | L86: Centro-Oeste
A87: 626 | B87: Shopping Metrô Itaquera | C87: (11) 2138-8511 | D87: Shopping | E87: Estrada da Pedreira S/N | F87: 0 | G87: Gleba I - Lj 122 - Térre - Shop Metro Itaquera | H87: 08220-385 | I87: Itaquera | J87: São Paulo | K87: SP | L87: Sudeste
A88: 627 | B88: Partage Norte Shopping Natal | C88: (84) 3311-3052 | D88: Shopping | E88: Av. Dr. João Medeiros Filho | F88: 2395 | G88: Espaço Comercial n.º 236/243- Piso L2- Shopping Natal Norte-Bairro Potengi | H88: 59110-200 | I88: Potengi | J88: Natal | K88: RN | L88: Nordeste
A89: 629 | B89: Plaza Avenida Shopping | C89: (17) 2138-2150 | D89: Shopping | E89: Av. Jose Munia | F89: 4775 | G89: Luc A 11 Piso 1 - Shopping Plaza Avenida | H89: 15085-350 | I89: Jardim Redentor | J89: São José do Rio Preto | K89: SP | L89: Sudeste
A90: 631 | B90: Shopping União de Osasco | C90: (11) 2138-8502 | D90: Shopping | E90: Av. dos Autonomistas | F90: 1400 | H90: 06020-010 | I90: Vila Yara | J90: Osasco | K90: SP | L90: Sudeste
A91: 632 | B91: Shopping Jardim das Américas | C91: (41) 3358-2980 | D91: Shopping | E91: Av. Nossa Senhora de Lourdes | F91: 63 | G91: Lojas n.º 4B/41-B/42-B | H91: 81530-020 | I91: Jardim das Americas | J91: Curitiba | K91: PR | L91: Sul
A92: 633 | B92: Bourbon Shopping | C92: (51) 3302-5301 | D92: Shopping | E92: Av. Assis Brasil | F92: 164 | H92: 91010-000 | I92: Passo D Areia | J92: Porto Alegre | K92: RS | L92: Sul
A93: 635 | B93: Minas Shopping | C93: (31) 3878-1550 | D93: Shopping | E93: Av. Cristiano Machado | F93: 4000 | G93: Espaço Comercial NRS 6- Localizada no 2.º Piso Minas Shopping-União | H93: 31910-900 | I93: Uniao | J93: Belo Horizonte | K93: MG | L93: Sudeste
A94: 636 | B94: Marília Shppping | C94: (14) 3311-5354 | D94: Shopping | E94: R. Tucunarés | F94: 500 | G94: LUC A5 - Âncora 2 - Aquarius Shopping Center - Bairro Jardim Maria Marta | H94: 17507-280 | I94: Jardim Maria Marta | J94: Marília | K94: SP | L94: Sudeste
A95: 639 | B95: Cubatão | C95: (13) 2138-2700 | D95: Rua | E95: Av. Nove de Abril | F95: 1994 | H95: 11510-001 | I95: Centro | J95: Cubatão | K95: SP | L95: Sudeste
A96: 640 | B96: Silva Bueno | C96: (11) 2109-6025 | D96: Rua | E96: R. Silva Bueno | F96: 2404 | H96: 04208-002 | I96: Ipiranga | J96: São Paulo | K96: SP | L96: Sudeste
A97: 641 | B97: Ferraz de Vasconcelos | C97: (11) 3238-3700 | D97: Rua | E97: Av. Quinze de Novembro | F97: 88 | G97: E 94 | H97: 08500-405 | I97: Vila Romanopolis | J97: Ferraz de Vasconcelos | K97: SP | L97: Sudeste
A98: 642 | B98: Buriti Shopping Guara | C98: (12) 2131-3613 | D98: Shopping | E98: Av. Juscelino Kubitschek de Oliveira | F98: 351 | G98: LUC 29 - Buriti Shopping | H98: 12505-300 | I98: Campo do Galvao | J98: Guaratinguetá | K98: SP | L98: Sudeste
A99: 643 | B99: Shopping Tambiá | C99: (83) 3515-5250 | D99: Shopping | E99: Av. Dep. Odon Bezerra | F99: 184 | G99: Lojas A-11/A-12/A-12/A-13/A-116/A-117/2.º Pavimento-Piso Acácia- Shop.Tambiá | H99: 58020-050 | I99: Tambia | J99: João Pessoa | K99: PB | L99: Nordeste
A100: 645 | B100: Jacareí | C100: (12) 2128-2050 | D100: Rua | E100: R. Dr. Lucio Malta | F100: 478 | H100: 12327-001 | I100: Centro | J100: Jacareí | K100: SP | L100: Sudeste
...

Sheet Telefonia Fixa
A1: Loja | B1: Nome Filial | C1: Telefone Marisa | D1: Telefone Fixo | E1: Valor Cobrado | F1: Operadora
A2: 22 | B2: Azenha | C2: (51) 3275-8980 | D2: - | F2: -
A3: 43 | B3: São Caetano do Sul | C3: (11) 4228-7820 | D3: - | F3: -
A4: 80 | B4: Campina Grande | C4: (83) 3182-4800 | D4: - | F4: -
A5: 87 | B5: Teresina (Centro) | C5: (86) 3302-6104 | D5: - | F5: -
A6: 120 | B6: São Luiz | C6: (98) 3878-6950 | D6: - | F6: -
A7: 125 | B7: Aracajú | C7: (11) 2109-3045 | D7: - | F7: -
A8: 130 | B8: Florianópolis | C8: (48) 3878-2150 | D8: - | F8: -
A9: 133 | B9: Shopping Interlagos | C9: (11) 2138-8159 | D9: - | F9: -
A10: 135 | B10: Shopping Mueller Joinville | C10: (47) 3803-6550 | D10: - | F10: -
A11: 136 | B11: Shopping Metrópole | C11: (11) 2138-8534 | D11: - | F11: -
A12: 140 | B12: River Shopping | C12: (87) 3201-3984 | D12: - | F12: -
A13: 142 | B13: Norte Shopping | C13: (21) 2187-7600 | D13: - | F13: -
... A18: 178 | B18: Buriti Shopping | C18: (62) 3625-7180 | D18: - | F18: -
A19: 180 | B19: Litoral Plaza Shopping | C19: (13) 3476-1283 | D19: (13)3476-1288 | E19: 23.475709 | F19: TELEFONICA
A20: 196 | B20: Manaíra Shopping | C20: (83) 3533-4351 | D20: - | F20: -
A21: 508 | B21: Alameda Shopping | C21: (61) 2102-1314 | D21: - | F21: -
A22: 510 | B22: Shopping Aricanduva | C22: (11) 2109-3178 | D22: - | F22: -
A23: 512 | B23: Cuiabá | C23: (65) 3928-3249 | D23: - | F23: -
A24: 514 | B24: Macapá | C24: (96) 2101-8850 | D24: - | F24: -
A25: 515 | B25: Santo Amaro | C25: (11) 2109-6466 | D25: - | F25: -
A26: 517 | B26: Rio Branco | C26: (68) 3303-8980 | D26: - | F26: -
A27: 518 | B27: Diadema | C27: (11) 2109-3171 | D27: - | F27: -
A28: 519 | B28: Porto Velho | C28: (69) 2182-4380 | D28: - | F28: -
A29: 520 | B29: Mauá Plaza Shopping | C29: (11) 2109-6054 | D29: - | F29: -
A30: 525 | B30: Sh Rio Mar Aracajú | C30: (79) 3711-2770 | D30: - | F30: -
A31: 526 | B31: Canoas Shopping | C31: (51) 2102-7280 | D31: - | F31: -
A32: 527 | B32: North Shopping Fortaleza | C32: (85) 3392-3684 | D32: (85)3392-3680 | E32: 28.76 | F32: EMBRATEL
A33: 529 | B33: São Leopoldo | C33: (11) 2138-8537 | D33: - | F33: -
A34: 531 | B34: Via Shopping Barreiro | C34: (31) 3211-7350 | D34: - | F34: -
A35: 534 | B35: Maxi Shopping Jundiaí | C35: (11) 4583-6683 | D35: - | F35: -
A36: 535 | B36: São José dos Pinhais | C36: (41) 3311-7630 | D36: - | F36: -
A37: 536 | B37: BH Centro | C37: (31) 3242-8500 | D37: - | F37: -
A38: 543 | B38: Campo Grande | C38: (21) 3622-8730 | D38: - | F38: -
A39: 544 | B39: Shopping Penha | C39: (11) 2109-6021 | D39: - | F39: -
A40: 546 | B40: São Bernardo | C40: (11) 2109-3172 | D40: - | F40: -
A41: 547 | B41: Gonzaga | C41: (13) 3208-6481 | D41: 1332086499 | E41: 86.55 | F41: EMBRATEL
A42: 548 | B42: Curitiba | C42: (11) 2138-8530 | D42: - | F42: -
A43: 549 | B43: Novo Shopping Center Ribeirão Preto | C43: (16) 3965-8510 | D43: - | F43: -
A44: 550 | B44: Guarulhos | C44: (11) 2109-6017 | D44: - | F44: -
A45: 553 | B45: Midway Mall | C45: (84) 3344-7235 | D45: - | F45: -
A46: 558 | B46: Manaus | C46: (92) 3303-9430 | D46: - | F46: -
A47: 559 | B47: Osasco Plaza Shopping | C47: (11) 2109-3173 | D47: - | F47: -
A48: 560 | B48: Castanheira Shopping Center | C48: (91) 3344-5080 | D48: 9133445080 | E48: 28.72 | F48: EMBRATEL
A49: 563 | B49: Santana | C49: (11) 2138-8506 | D49: - | F49: -
A50: 564 | B50: São Miguel Paulista | C50: (11) 2138-8517 | D50: - | F50: -
A51: 565 | B51: Shopping Guararapes | C51: (81) 3201-7250 | D51: - | F51: -
A52: 566 | B52: Maceió Shopping | C52: (82) 3214-6550 | D52: - | F52: -
A53: 568 | B53: Fortaleza | C53: (85) 3521-4950 | D53: - | F53: -
A54: 571 | B54: Shopping Do Vale | C54: (51) 3533-6680 | D54: - | F54: -
A55: 573 | B55: Santo André | C55: (11) 2138-8510 | D55: - | F55: -
A56: 575 | B56: Alcântara | C56: (21) 3575-7401 | D56: - | F56: -
A57: 576 | B57: Parque Dom Pedro Shopping | C57: (19) 3709-9080 | D57: - | F57: -
A58: 577 | B58: Mogi Shopping | C58: (11) 4728-3172 | D58: - | F58: -
A59: 578 | B59: Farol Shopping | C59: (48) 3301-3150 | D59: - | F59: -
A60: 579 | B60: Shopping Campo Limpo | C60: (11) 2138-8508 | D60: - | F60: -
... A66: 590 | B66: Big Shopping | C66: (31) 3358-3500 | D66: - | F66: -
A67: 594 | B67: Floripa Shopping | C67: (48) 3231-3100 | D67: 4832313100 | E67: 137.99 | F67: EMBRATEL
A68: 594 | B68: Floripa Shopping | C68: (48) 3231-3100 | D68: 4832313100 | E68: 334.69 | F68: OI TELEMAR
A69: 597 | B69: Nova Iguaçu | C69: (21) 3575-5060 | D69: - | F69: -
A70: 598 | B70: Shopping Avenida Center | C70: (67) 2108-3380 | D70: - | F70: -
A71: 599 | B71: Ponta Grossa | C71: (42) 3302-2150 | D71: - | F71: -
A72: 600 | B72: Salvador Shopping | C72: (71) 3617-4830 | D72: - | F72: -
A73: 601 | B73: Shopping Recife | C73: (11) 2109-3191 | D73: - | F73: -
A74: 604 | B74: Vitória da Conquista | C74: (77) 3201-7180 | D74: - | F74: -
A75: 605 | B75: Shopping Avenida Center | C75: (44) 3355-4550 | D75: - | F75: -
A76: 606 | B76: Shopping Vale do Aço | C76: (31) 3094-2100 | D76: - | F76: -
A77: 607 | B77: Pátio Limeira Shopping | C77: (19) 3404-4180 | D77: - | F77: -
A78: 608 | B78: Taubaté Shopping | C78: (12) 2125-2350 | D78: - | F78: -
A79: 610 | B79: Partage Shopping Campina Grande | C79: (83) 2102-2254 | D79: - | F79: -
A80: 613 | B80: Itaim Paulista | C80: (11) 2109-3170 | D80: - | F80: -
... A83: 619 | B83: Shopping Bonsucesso | C83: (11) 2109-6486 | D83: - | F83: -
A84: 622 | B84: Shopping Metrô Tucuruvi | C84: (11) 2109-3014 | D84: 9055_Fixa | E84: 247.45 | F84: YIPI
A85: 623 | B85: Caruaru Shopping | C85: (81) 2103-2350 | D85: - | F85: -
A86: 624 | B86: Shopping Vale Sul | C86: (12) 3878-7810 | D86: 1238787800 | E86: 22.32 | F86: EMBRATEL
A87: 625 | B87: Campo Grande | C87: (67) 3303-3352 | D87: - | F87: -
A88: 626 | B88: Shopping Metrô Itaquera | C88: (11) 2138-8511 | D88: - | F88: -
A89: 627 | B89: Partage Norte Shopping Natal | C89: (84) 3311-3052 | D89: - | F89: -
A90: 629 | B90: Plaza Avenida Shopping | C90: (17) 2138-2150 | D90: - | F90: -
A91: 631 | B91: Shopping União de Osasco | C91: (11) 2138-8502 | D91: - | F91: -
A92: 632 | B92: Shopping Jardim das Américas | C92: (41) 3358-2980 | D92: - | F92: -
A93: 633 | B93: Bourbon Shopping | C93: (51) 3302-5301 | D93: - | F93: -
A94: 635 | B94: Minas Shopping | C94: (31) 3878-1550 | D94: - | F94: -
A95: 636 | B95: Marília Shppping | C95: (14) 3311-5354 | D95: 1433115350 | E95: 5.46 | F95: EMBRATEL
A96: 639 | B96: Cubatão | C96: (13) 2138-2700 | E96: 0.35 | F96: EMBRATEL
A97: 640 | B97: Silva Bueno | C97: (11) 2109-6025 | D97: - | F97: -
A98: 641 | B98: Ferraz de Vasconcelos | C98: (11) 3238-3700 | D98: 1132383700 | E98: 9.1 | F98: EMBRATEL
A99: 642 | B99: Buriti Shopping Guara | C99: (12) 2131-3613 | D99: 1221313600 | E99: 14.17 | F99: EMBRATEL
A100: 643 | B100: Shopping Tambiá | C100: (83) 3515-5250 | D100: - | F100: -
A101: 645 | B101: Jacareí | C101: (12) 2128-2050 | D101: - | F101: -
A102: 646 | B102: Shopping da Bahia | C102: (71) 3525-2063 | D102: - | F102: -
A103: 647 | B103: Vicente de Carvalho | C103: (13) 3878-5800 | D103: 1338785800 | E103: 1.91 | F103: EMBRATEL
A104: 648 | B104: Shopping Taboão | C104: (11) 2109-3015 | D104: - | F104: -
A105: 649 | B105: Palladium Shopping | C105: (41) 3888-5900 | D105: - | F105: -
A106: 650 | B106: Boulevard Shopping Belém | C106: (91) 3205-4100 | D106: 9132054100 | E106: 68.62 | F106: EMBRATEL
A107: 651 | B107: Shopping Conjunto Nacional | C107: (61) 2107-6659 | D107: - | F107: -
A108: 652 | B108: Montes Claros Shopping | C108: (38) 2101-8400 | D108: - | F108: -
A109: 653 | B109: Shopping Via Sul | C109: (85) 3402-5614 | D109: 8534025600 | E109: 13.3 | F109: EMBRATEL
A110: 654 | B110: Shopping Plaza Macaé | C110: (22) 3311-1600 | D110: - | F110: -
A111: 656 | B111: Andorinha Hiper Center | C111: (11) 2109-3192 | D111: - | F111: -
...

Sheet Telefonia Ip - Lojas
A1: Loja | B1: Filial | C1: Estado | D1: Hunt Group | E1: Qtde aps ativos | F1: Req/Num loja | G1: Data Instalação | H1: Ramais Criados | I1: OBS
A2: 22 | B2: Azenha | C2: RS | D2: 111 | E2: 1 | F2: 11 2109-3151 | G2: 45327 | H2: 60221
A3: 43 | B3: São Caetano do Sul | C3: SP | D3: 112 | E3: 1 | F3: 11 2109-3152 | G3: 45327 | H3: 60431
A4: 80 | B4: Campina Grande | C4: PB | D4: 113 | E4: 1 | F4: 11 2109-3153 | G4: 45394 | H4: 60801
A5: 87 | B5: Teresina (Centro) | C5: pi | D5: 114 | E5: 1 | F5: 11 2109-3154 | G5: 45359 | H5: 60871
A6: 120 | B6: São Luiz | C6: MA | D6: 115 | E6: 1 | F6: 11 2109-3155 | G6: 45327 | H6: 61201
A7: 125 | B7: Aracajú | C7: SE | D7: 22 | E7: 4 | F7: 11 2109-3045 | G7: 45084 | H7: 61251 a 61254
A8: 130 | B8: Florianópolis | C8: sc | D8: 116 | E8: 1 | F8: 11 2109-3156 | G8: 45489 | H8: 61301
A9: 133 | B9: Shop. Interlagos | C9: SP | D9: 72 | E9: 3 | F9: 11 2138-8159 | G9: 45043 | H9: 61331 a 61334
A10: 135 | B10: Shop. Mueller Joinville | C10: sc | D10: 117 | E10: 1 | F10: 11 2109-3157 | G10: 45363 | H10: 61351
A11: 136 | B11: Shop. Metrópole | C11: SP | D11: 94 | E11: 4 | F11: 11 2138-8534 | G11: 45056 | H11: 61361 a 61364
A12: 140 | B12: River Shopping | C12: pe | D12: 118 | E12: 1 | F12: 11 2109-3158 | G12: 45362 | H12: 61401
A13: 142 | B13: Norte Shopping | C13: RJ | D13: 119 | E13: 1 | F13: 11 2109-3159 | G13: 45328 | H13: 61421
A14: 150 | B14: Pátio Brasil Shop. | C14: DF | D14: 121 | E14: 1 | F14: 11 2109-3161 | G14: 45328 | H14: 61501 | I14: DDR desativado em 06/06/2025
A15: 160 | B15: Riverside Walk Shop. | C15: PI | D15: 122 | E15: 1 | F15: 11 2109-3162 | G15: 45328 | H15: 61601
A16: 165 | B16: Grand Plaza Shop. | C16: SP | D16: 73 | E16: 3 | F16: 11 2109-3194 | G16: 45043 | H16: 61651 a 61654
A17: 176 | B17: Internacional Shop. Guarulhos | C17: SP | D17: 23 | E17: 4 | F17: 11 2109-6112 | G17: 45043 | H17: 61761 a 61764
A18: 178 | B18: Buriti Shop. | C18: GO | D18: 124 | E18: 1 | F18: 11 2109-3164 | G18: 45328 | H18: 61781
A19: 180 | B19: Litoral Plaza Shop. | C19: SP | D19: 125 | E19: 1 | F19: 11 2109-3165 | G19: 45362 | H19: 61801
A20: 196 | B20: Manaíra Shop. | C20: PB | D20: 41 | E20: 3 | F20: 11 2138-8564 | G20: 45254 | H20: 61961 a 61963
A21: 508 | B21: Alameda Shop. | C21: DF | D21: 126 | E21: 1 | F21: 11 2109-3166 | G21: 45489 | H21: 65081
A22: 510 | B22: Shop. Aricanduva | C22: SP | D22: 63 | E22: 5 | F22: 11 2109-3178 | G22: 45057 | H22: 65101 a 65105
A23: 512 | B23: Cuiabá | C23: MT | D23: 127 | E23: 1 | F23: 11 2109-3167 | G23: 45488 | H23: 65121
A24: 514 | B24: Macapá | C24: AP | D24: 128 | E24: 1 | F24: 11 2109-3168 | G24: 45329 | H24: 65141 | I24: DDR desativado em 02/06/2025
A25: 515 | B25: Santo Amaro | C25: SP | D25: 55 | E25: 4 | F25: 11 2109-6466 | G25: 45043 | H25: 65151 a 65154
A26: 517 | B26: Rio Branco | C26: ac | D26: 129 | E26: 1 | F26: 11 2109-3169 | G26: 45365 | H26: 65171
A27: 518 | B27: Diadema | C27: SP | D27: 69 | E27: 6 | F27: 11 2109-3171 | G27: 45058 | H27: 65181 a 65186
A28: 519 | B28: Porto Velho | C28: ro | D28: 130 | E28: 1 | F28: 11 2109-3175 | G28: 45817 | H28: 65191 a 65192
A29: 520 | B29: Mauá Plaza Shop. | C29: SP | D29: 40 | E29: 4 | F29: 11 2109-6054 | G29: 45125 | H29: 65201 a 65204
A30: 525 | B30: RioMar Aracajú | C30: se | D30: 131 | E30: 1 | F30: 11 2109-3180 | G30: 45337 | H30: 65251
A31: 526 | B31: Canoas Shop. | C31: rs | D31: 132 | E31: 1 | F31: 11 2109-3182 | G31: 45362 | H31: 65261
A32: 527 | B32: North Shop. Fortaleza | C32: ce | D32: 133 | E32: 1 | F32: 11 2109-3183 | G32: 45364 | H32: 65271
A33: 529 | B33: São Leopoldo | C33: RS | D33: 38 | E33: 4 | F33: 11 2138-8537 | G33: 45170 | H33: 65291 a 65294
A34: 531 | B34: Via Shop. | C34: MG | D34: 134 | E34: 1 | F34: 11 2109-3184 | G34: 45364 | H34: 65311
A35: 534 | B35: Maxi Shop. Jundiaí | C35: SP | D35: 135 | E35: 3 | F35: 11 2109-3185 | G35: 45819 | H35: 65341 a 65343
A36: 535 | B36: São José dos Pinhais | C36: PR | D36: 136 | E36: 1 | F36: 11 2109-3186 | G36: 45359 | H36: 65351
A37: 536 | B37: BH Centro | C37: MG | D37: 137 | E37: 1 | F37: 11 2109-3187 | G37: 45391 | H37: 65361
A38: 544 | B38: Shop. Penha | C38: SP | D38: 39 | E38: 4 | F38: 11 2109-6021 | G38: 45043 | H38: 65441 a 65444
A39: 546 | B39: São Bernardo do Campo | C39: SP | D39: 68 | E39: 4 | F39: 11 2109-3172 | G39: 45061 | H39: 65461 a 65466
A40: 547 | B40: Gonzaga | C40: SP | D40: 139 | E40: 1 | F40: 11 2109-3189 | G40: 45329 | H40: 65471
A41: 548 | B41: Curitiba | C41: PR | D41: 99 | E41: 7 | F41: 11 2138 8530 | G41: 45250 | H41: 65481 a 65487
A42: 549 | B42: Novo Shop. Center Ribeirão Preto | C42: SP | D42: 140 | E42: 1 | F42: 11 2109-3190 | G42: 45329 | H42: 65491
A43: 550 | B43: Guarulhos | C43: SP | D43: 35 | E43: 4 | F43: 11 2109-6017 | G43: 45043 | H43: 65501 a 65504
A44: 553 | B44: Midway Mall | C44: rn | D44: 141 | E44: 2 | F44: 11 2109-3193 | G44: 45842 | H44: 65531 a 65532
A45: 558 | B45: Manaus | C45: am | D45: 142 | E45: 1 | F45: 11 2109-3195 | G45: 45359 | H45: 65581
A46: 559 | B46: Osasco Plaza Shop. | C46: SP | D46: 67 | E46: 4 | F46: 11 2109-3173 | G46: 45099 | H46: 65591 a 65594
A47: 560 | B47: Castanheira Shop. Center | C47: pa | D47: 143 | E47: 1 | F47: 11 2109-3196 | G47: 45364 | H47: 65601
A48: 563 | B48: Santana | C48: SP | D48: 78 | E48: 4 | F48: 11 2138-8506 | G48: 45043 | H48: 65631 a 65634
A49: 564 | B49: São Miguel Pta | C49: SP | D49: 86 | E49: 4 | F49: 11 2138-8517 | G49: 45043 | H49: 65641 a 65644
A50: 565 | B50: Shop. Guararapes | C50: pe | D50: 81 | E50: 1 | F50: 11 2109-3197 | G50: 45364 | H50: 65651
A51: 566 | B51: Maceió Shop. | C51: al | D51: 145 | E51: 1 | F51: 11 2109-3198 | G51: 45364 | H51: 65661
A52: 568 | B52: Fortaleza | C52: ce | D52: 146 | E52: 1 | F52: 11 2109-3199 | G52: 45366 | H52: 65681
A53: 571 | B53: Shop. do Vale | C53: rs | D53: 147 | E53: 1 | F53: 11 2109-3002 | G53: 45475 | H53: 65711
A54: 573 | B54: Santo André | C54: SP | D54: 81 | E54: 3 | F54: 11 2138 8510 | G54: 45036 | H54: 65731 a 65733
A55: 575 | B55: Alcântara | C55: rj | D55: 148 | E55: 3 | F55: 11 2109-3003 | G55: 45483 | H55: 65751 a 65753
A56: 576 | B56: Parque Dom Pedro Shop. | C56: sp | D56: 149 | E56: 1 | F56: 11 2109-3004 | G56: 45366 | H56: 65761
A57: 577 | B57: Mogi Shop. | C57: sp | D57: 150 | E57: 3 | F57: 11 2109-3005 | G57: 45819 | H57: 65771 a 65773
A58: 578 | B58: Farol Shop. | C58: sc | D58: 151 | E58: 1 | F58: 11 2109-3006 | G58: 45341 | H58: 65781
A59: 579 | B59: Shop. Campo Limpo | C59: SP | D59: 80 | E59: 4 | F59: 11 2138-8508 | G59: 45043 | H59: 65791 a 65794
A60: 580 | B60: Shop. Piracicaba | C60: sp | D60: 152 | E60: 1 | F60: 11 2109-3007 | G60: 45329 | H60: 65801
A61: 582 | B61: Porto Alegre (Centro) | C61: rs | D61: 153 | E61: 1 | F61: 11 2109-3008 | G61: 45488 | H61: 65821
A62: 583 | B62: Shop. Del Rey | C62: mg | D62: 154 | E62: 1 | F62: 11 2109-3009 | G62: 45366 | H62: 65831
A63: 586 | B63: Shop. Metrô Tatuapé | C63: SP | D63: 66 | E63: 4 | F63: 11 2109-3174 | G63: 45057 | H63: 65861 a 65866
A64: 589 | B64: Maceió | C64: al | D64: 155 | E64: 1 | F64: 11 2109-3010 | G64: 45378 | H64: 65891
A65: 590 | B65: Big Shop. | C65: mg | D65: 156 | E65: 1 | F65: 11 2109-3011 | G65: 45377 | H65: 65901
A66: 594 | B66: Floripa Shop. | C66: sc | D66: 157 | E66: 3 | F66: 11 2109-3012 | G66: 45341 | H66: 65941
A67: 597 | B67: Nova Iguaçu | C67: rj | D67: 158 | E67: 1 | F67: 11 2109-3013 | G67: 45330 | H67: 65971
A68: 598 | B68: Shop. Avenida Center | C68: MS | D68: 159 | E68: 2 | F68: 11 2109-3001 | G68: 45328 | H68: 65981 a 65982
A69: 599 | B69: Ponta Grossa | C69: pr | D69: 161 | E69: 1 | F69: 11 2109-3018 | G69: 45378 | H69: 65991
A70: 600 | B70: Salvador Shop. | C70: ba | D70: 162 | E70: 1 | F70: 11 2109-3019 | G70: 45377 | H70: 66001
A71: 601 | B71: Shop. Recife | C71: PE | D71: 76 | E71: 4 | F71: 11 2109-3191 | G71: 45180 | H71: 66011 a 66015
A72: 604 | B72: Vitória da Conquista | C72: ba | D72: 163 | E72: 1 | F72: 11 2109-3022 | G72: 45337 | H72: 66041
A73: 605 | B73: Shop. Avenida Center | C73: pr | D73: 164 | E73: 1 | F73: 11 2109-3023 | G73: 45378 | H73: 66051
A74: 606 | B74: Shop. do Vale do Aço | C74: mg | D74: 165 | E74: 1 | F74: 11 2109-3025 | G74: 45378 | H74: 66061
A75: 607 | B75: Pátio Limeira Shop. | C75: sp | D75: 166 | E75: 1 | F75: 11 2109-3028 | G75: 45379 | H75: 66071
A76: 608 | B76: Taubaté Shop. | C76: sp | D76: 167 | E76: 1 | F76: 11 2109-3033 | G76: 45384 | H76: 66081
A77: 610 | B77: Partage Shop. Campina Grande | C77: pb | D77: 168 | E77: 1 | F77: 11 2109-3034 | G77: 45384 | H77: 66101
A78: 613 | B78: Itaim Paulista | C78: SP | D78: 70 | E78: 4 | F78: 11 2109-3170 | G78: 45056 | H78: 66131 a 66134
A79: 617 | B79: Goiânia | C79: go | D79: 169 | E79: 1 | F79: 11 2109-3036 | G79: 45462 | H79: 66171
A80: 618 | B80: Shop. Jequitiba | C80: BA | D80: 79 | E80: 4 | F80: 11 2109-6291 | G80: 45166 | H80: 66181 a 66184
A81: 619 | B81: Shop Bonsucesso | C81: SP | D81: 43 | E81: 4 | F81: 11 2109-6486 | G81: 45043 | H81: 66191 a 66194
A82: 622 | B82: Shop. Metrô Tucuruvi | C82: SP | D82: 19 | E82: 3 | F82: 11 2109-3014 | G82: 45043 | H82: 66221 a 66224
A83: 623 | B83: North Shop. Caruaru | C83: pe | D83: 170 | E83: 3 | F83: 11 2109-3038 | G83: 45819 | H83: 66231 a 66233
A84: 624 | B84: Vale Sul Shop. | C84: sp | D84: 171 | E84: 1 | F84: 11 2109-3039 | G84: 45384 | H84: 66241
A85: 625 | B85: Campo Grande | C85: ms | D85: 172 | E85: 2 | F85: 11 2109-3040 | G85: 45359 | H85: 66251 a 66252
A86: 626 | B86: Shop. Metrô Itaquera | C86: SP | D86: 82 | E86: 6 | F86: 11 2138-8511 | G86: 45043 | H86: 66261 a 66266
A87: 627 | B87: Partage Norte Shop. Natal | C87: rn | D87: 173 | E87: 1 | F87: 11 2109-3041 | G87: 45490 | H87: 66271
A88: 629 | B88: Plaza Avenida Shop. | C88: sp | D88: 174 | E88: 1 | F88: 11 2109-3042 | G88: 45338 | H88: 66291
A89: 631 | B89: Shop. União de Osasco | C89: SP | D89: 75 | E89: 3 | F89: 11 2138-8502 | G89: 45043 | H89: 66311 a 66314
A90: 632 | B90: Shop. Jardim das Américas | C90: pr | D90: 175 | E90: 1 | F90: 11 2109-3043 | G90: 45481 | H90: 66321
A91: 633 | B91: Bourbon Shop. | C91: rs | D91: 176 | E91: 1 | F91: 11 2109-3044 | G91: 45489 | H91: 66331
A92: 635 | B92: Minas Shop. | C92: mg | D92: 177 | E92: 1 | F92: 11 2109-3046 | G92: 45341 | H92: 66351
A93: 636 | B93: Marília Shop. | C93: sp | D93: 178 | E93: 1 | F93: 11 2109-3047 | G93: 45384 | H93: 66361
A94: 639 | B94: Cubatão | C94: sp | D94: 179 | E94: 1 | F94: 11 2109-3048 | G94: 45338 | H94: 66391
A95: 640 | B95: Silva Bueno | C95: SP | D95: 42 | E95: 4 | F95: 11 2109-6025 | G95: 45043 | H95: 66401 a 66404
A96: 641 | B96: Ferraz de Vasconcelos | C96: sp | D96: 180 | E96: 1 | F96: 11 2109-3095 | G96: 45474 | H96: 66411
A97: 642 | B97: Buriti Shop. Guará | C97: sp | D97: 181 | E97: 1 | F97: 11 2109-3096 | G97: 45394 | H97: 66421
A98: 643 | B98: Shop Tambiá | C98: pb | D98: 182 | E98: 2 | F98: 11 2109-3098 | G98: 45818 | H98: 66431 a 66432
A99: 645 | B99: Jacare¡ | C99: sp | D99: 183 | E99: 2 | F99: 11 2109-3099 | G99: 45809 | H99: 66451 a 66452
A100: 646 | B100: Iguatemi Salvador | C100: ba | D100: 184 | E100: 1 | F100: 11 2109-3100 | G100: 45394 | H100: 66461
...

Sheet EC-Tivit-CDs
A1: Site | B1: CR | C1: Operadora 1 | D1: Tipo | E1: Velocidade | F1: Data de Ativação | G1: Vigencia | H1: Valor | I1: Designação | J1: Operadora 2 | K1: Tipo | L1: Velocidade | M1: Data de Ativação | N1: Vigencia | O1: Valor | P1: Designação | Q1: Operadora 3 | R1: Tipo | S1: Velocidade | T1: Data de Ativação | U1: Vigencia | V1: Valor | W1: Designação | X1: Operadora 4 | Y1: Tipo | Z1: Velocidade | AA1: Data de Ativação | AB1: Vigencia | AC1: Valor | AD1: Designação | AE1: Operadora 5 | AF1: Tipo | AG1: Velocidade | AH1: Data de Ativação | AI1: Vigencia | AJ1: Valor | AK1: Designação | AL1: Operadora 6 | AM1: Tipo | AN1: Velocidade | AO1: Data de Ativação | AP1: Vigencia | AQ1: Valor | AR1: Designação | AT1: IP Loopback | AU1: IP Local
A2: EC | B2: 41100 | C2: Embratel | D2: Dedicado | E2: 500Mb | F2: 44903 | G2: 45999 | H2: 3181.21 | I2: SPO/IP/40295 | J2: Vivo | K2: Dedicado | L2: 1 GB | M2: 45595 | N2: 46690 | O2: 3434.64 | P2: 110003392209490 | Q2: Algar | R2: L2L (EC-Tivit) | S2: 1 GB | T2: 44750 | U2: 45846 | V2: 2345.89 | W2: 8880105
A3: Tivit | C3: Embratel | D3: Dedicado | E3: 1Gb | F3: 44901 | G3: 45997 | H3: 5657.1 | I3: SPO/IP/70714 | J3: Vivo | K3: Dedicado | L3: 1 GB | M3: 45132 | N3: 46228 | O3: 3763.7 | P3: 830000171641295 | Q3: Algar | R3: L2L (Tivit-EC) | S3: 1 GB | T3: 44750 | U3: 45846 | V3: 2345.89 | W3: 8880104 | X3: EBT (Sitef) | Y3: MPLS | Z3: 20MB | AC3: 4993.06 | AD3: SPO/IP/55340 | AE3: Algar | AF3: L2L(Tivit-CD) | AG3: 50 MB | AH3: 44651 | AI3: Vencido | AJ3: 1034.56 | AK3: 8788650 | AL3: Vivo (Sitef) | AM3: MPLS | AN3: 4Mb | AO3: 45070 | AP3: Vencido | AQ3: 3998.82 | AR3: 110005641094794
A4: CD Itaqua | B4: CD820 | C4: Vivo | D4: Dedicado | E4: 200Mb | F4: 45338 | G4: 46434 | H4: 1760.03 | I4: 113004643101796 | J4: WCS | K4: Dedicado | L4: 100 MB | M4: 45609 | N4: 46704 | O4: 430 | P4: CD 820 - Itaquaquecetuba - SP | Q4: Algar | R4: L2L (CD-Tivit) | S4: 50 MB | T4: 44651 | U4: Vencido | V4: 1034.56 | W4: 8788652 | AU4: 10.8.120.0/22
A5: CD Blumenau | B5: CD811 | C5: Algar | D5: Dedicado | E5: 20 MB | F5: 44596 | G5: Vencido | H5: 980.92 | I5: 8756818/8756819 | J5: Embratel | K5: Dedicado | L5: 20 MB | M5: 44714 | N5: Vencido | O5: 484.62 | P5: BNU/IP/01514 | AU5: 10.8.100.0/22
A6: CD Goiânia | B6: CD807 | C6: Algar | D6: Dedicado | E6: 10MB | F6: 44617 | G6: Vencido | H6: 450.13 | I6: 8754445/8754447 | J6: Vivo | K6: Dedicado | L6: 10 MB | M6: 44470 | N6: Vencido | O6: 584.64 | P6: 621980152126996 | AU6: 10.8.108.0/22
A7: CD Navegantes | B7: CD818 | C7: Algar | D7: Dedicado | E7: 20 MB | F7: 44589 | G7: Vencido | H7: 566.52 | I7: 8754444/8754446 | J7: Mega | K7: Dedicado | L7: 20 MB | M7: 44735 | N7: Vencido | O7: 897.79 | P7: TIT000872 | AU7: 10.8.107.0/22
B8: SITEF | C8: Vivo-P2 EQN-ALA | D8: MPLS | E8: 2MB | F8: 43738 | G8: Vencido | H8: 832.3 | I8: 110714191224793 | J8: Embratel | K8: MPLS | L8: 2Mb | O8: 1343.81 | P8: BRE/IP/25280
C9: Vivo-P1 EQN-MIG | D9: MPLS | E9: 2MB | F9: 43738 | G9: Vencido | H9: 832.3 | I9: 110003106383097 | J9: Embratel | K9: MPLS | L9: 2Mb | O9: 1909.68 | P9: SPO/IP/55325
B15: EC | C15: =SUM(H2+O2+V2) -> 8961.74
B16: TIVIT | C16: =SUM(H3+O3+V3+AJ3) -> 12801.25
B17: CD Itaqua | C17: =SUM(H4+O4+V4) -> 3224.59
B18: CD Blumenau | C18: =SUM(H5+O5+V5) -> 1465.54
B19: CD Goiânia | C19: =SUM(H6+O6+V6) -> 1034.77
B20: CD Navegantes | C20: =SUM(H7+O7+V7) -> 1464.31
B21: SITEF | C21: =SUM(AC3+AQ3+H8+H9+O8+O9) -> 13909.97
B22: Custo Total | C22: =SUM(C15:C21) -> 42862.17

Sheet Telefonia Móvel
A1: CR | B1: Operadora | C1: Plano | D1: Conta | E1: Localidade | F1: Telefonia | G1: Numero | H1: Valor | P1: Total
A2: 22 | B2: - | C2: - | D2: - | F2: MÓVEL | G2: - | H2: 0 | P2: =SUM(I2:O2) -> 0
A3: 43 | B3: - | C3: - | D3: - | F3: MÓVEL | G3: - | H3: 0 | P3: =SUM(I3:O3) -> 0
A4: 80 | B4: VIVO | C4: PLANO INTERNET BOX PJ | D4: 2027121479 | E4: 080 - CAMPINA GRANDE | F4: MÓVEL | G4: 11995086262 | H4: 104.05 | I4: 104.05 | P4: =SUM(I4:O4) -> 104.05
A5: 87 | B5: VIVO | C5: SMART EMPRESAS 2GB D | D5: 381199225 | E5: 087 - TERESINA | F5: MÓVEL | G5: 11971053948 11950616361 11995061269 | H5: R$ 18,99 R$ 18,99 R$ 18,99 | I5: 18.99 | J5: 18.99 | K5: 18.99 | P5: =SUM(I5:O5) -> 56.97
A6: 120 | B6: VIVO | C6: SMART EMPRESAS 0.5GB D | D6: 381199225 | E6: 120 - SÃO LUIZ | F6: MÓVEL | G6: 11944706003 11944439242 | H6: R$ 30,50 R$ 18,99 | I6: 30.5 | J6: 18.99 | P6: =SUM(I6:O6) -> 49.49
A7: 140 | B7: VIVO | C7: SMART EMPRESAS 2GB D | D7: 381199225 | E7: 140 - RIVER SHOP | F7: MÓVEL | G7: 16996333608 19996458099 21995002687 79998442585 | H7: R$ 18,99 R$ 18,99 R$ 18,99 R$ 30,50 | I7: 18.99 | J7: 18.99 | K7: 18.99 | L7: 30.5 | P7: =SUM(I7:O7) -> 87.47
A8: 142 | B8: CLARO | C8: PLANO TOTAL SHARE 2.0 | D8: 832140239 | E8: 142 - NORTE SHOP | F8: MÓVEL | G8: 11992175076 11992350946 11992979384 11993155324 | H8: R$ 62,23 R$ 50,59 R$ 50,59 R$ 50,59 | I8: 62.23 | J8: 50.59 | K8: 50.59 | L8: 50.59 | P8: =SUM(I8:O8) -> 214
A9: 125 | B9: - | C9: - | D9: - | F9: MÓVEL | G9: - | H9: 0 | P9: =SUM(I9:O9) -> 0
A10: 130 | B10: - | C10: - | D10: - | F10: MÓVEL | G10: - | H10: 0 | P10: =SUM(I10:O10) -> 0
A11: 133 | B11: - | C11: - | D11: - | F11: MÓVEL | G11: - | H11: 0 | P11: =SUM(I11:O11) -> 0
A12: 135 | B12: - | C12: - | D12: - | F12: MÓVEL | G12: - | H12: 0 | P12: =SUM(I12:O12) -> 0
A13: 136 | B13: - | C13: - | D13: - | F13: MÓVEL | G13: - | H13: 0 | P13: =SUM(I13:O13) -> 0
A14: 150 | B14: VIVO | C14: SMART EMPRESAS 2GB D | D14: 381199225 | E14: 150 - PATIO BRASIL SHOP | F14: MÓVEL | G14: 51980635226 21967265582 | H14: R$ 18,99 R$ 18,99 | I14: 18.99 | J14: 18.99 | P14: =SUM(I14:O14) -> 37.98
A15: 160 | B15: VIVO | C15: SMART EMPRESAS 2GB D | D15: 381199225 | E15: 160 - RIVERSIDE WALK SHOP | F15: MÓVEL | G15: 11944594725 11944705147 | H15: R$ 18,99 R$ 18,99 | I15: 18.99 | J15: 18.99 | P15: =SUM(I15:O15) -> 37.98
A16: 178 | B16: VIVO | C16: SMART EMPRESAS 2GB D | D16: 381199225 | E16: 178 - BURUTI SHOP | F16: MÓVEL | G16: 11943930362 11996831429 | H16: R$ 18,99 R$ 18,99 | I16: 18.99 | J16: 18.99 | P16: =SUM(I16:O16) -> 37.98
A17: 508 | B17: VIVO | C17: SMART EMPRESAS 2GB D | D17: 381199225 | E17: 508 - ALAMEDA SHOP | F17: MÓVEL | G17: 11971405188 11996287684 | H17: R$ 18,99 R$ 18,99 | I17: 18.99 | J17: 18.99 | P17: =SUM(I17:O17) -> 37.98
A18: 165 | B18: - | C18: - | D18: - | E18: 165 - | F18: MÓVEL | G18: - | H18: 0 | P18: =SUM(I18:O18) -> 0
A19: 176 | B19: - | C19: - | D19: - | E19: 176 - SHOP ITERNACIONAL | F19: MÓVEL | G19: - | H19: 0 | P19: =SUM(I19:O19) -> 0
A20: 512 | B20: VIVO | C20: SMART EMPRESAS 2GB D | D20: 381199225 | E20: 512 - CUIABÁ | F20: MÓVEL | G20: 65996326335 | H20: 18.99 | I20: 18.99 | P20: =SUM(I20:O20) -> 18.99
A21: 180 | B21: - | C21: - | D21: - | F21: MÓVEL | G21: - | H21: 0 | P21: =SUM(I21:O21) -> 0
A22: 196 | B22: - | C22: - | D22: - | F22: MÓVEL | G22: - | H22: 0 | P22: =SUM(I22:O22) -> 0
A23: 514 | B23: VIVO | C23: SMART EMPRESAS 2GB D | D23: 381199225 | E23: 514 - MACAPÁ | F23: MÓVEL | G23: 11930280682 11999131734 | H23: R$ 18,99 R$ 31,99 | I23: 18.99 | J23: 31.99 | P23: =SUM(I23:O23) -> 50.98
A24: 510 | B24: - | C24: - | D24: - | E24: 510 - SHOP ARICANDUVA | F24: MÓVEL | G24: - | H24: 0 | P24: =SUM(I24:O24) -> 0
A25: 517 | B25: VIVO | C25: SMART EMPRESAS 2GB D | D25: 381199225 | E25: 517 - RIO BRANCO | F25: MÓVEL | G25: 19999319448 31996463551 51980476592 51996463769 | H25: R$ 18,99 R$ 18,99 R$ 18,99 R$ 18,99 | I25: 18.99 | J25: 18.99 | K25: 18.99 | L25: 18.99 | P25: =SUM(I25:O25) -> 75.96
A26: 519 | B26: CLARO | C26: PLANO TOTAL SHARE 2.0 | D26: 167840395 | E26: 519 - PORTO VELHO | F26: MÓVEL | G26: 69992372309 69993189066 69993261979 69993409924 | H26: R$ 40,47 R$ 40,47 R$ 40,47 R$ 40,47 | I26: 40.47 | J26: 40.47 | K26: 40.47 | L26: 40.47 | P26: =SUM(I26:O26) -> 161.88
A27: 515 | B27: - | C27: - | D27: - | E27: 515 - SANTO AMARO | F27: MÓVEL | G27: - | H27: 0 | P27: =SUM(I27:O27) -> 0
A28: 529 | B28: CLARO | C28: PLANO TOTAL SHARE 2.0 | D28: 167858424 | E28: 529 - SÃO LEOPONDO | F28: MÓVEL | G28: 51991708568 51991711470 51991722682 11988237933 | H28: R$ 32,19 R$ 32,19 R$ 32,19 R$ 157,79 | I28: 32.19 | J28: 32.19 | K28: 32.19 | L28: 157.79 | P28: =SUM(I28:O28) -> 254.36
A29: 518 | B29: - | C29: - | D29: - | F29: MÓVEL | G29: - | H29: 0 | P29: =SUM(I29:O29) -> 0
A30: 531 | B30: CLARO | C30: PLANO TOTAL SHARE 2.0 | D30: 105638675 | E30: 531 - VIA SHOP | F30: MÓVEL | G30: 31992430060 | H30: 52.28 | I30: 52.28 | P30: =SUM(I30:O30) -> 52.28
A31: 520 | B31: - | C31: - | D31: - | F31: MÓVEL | G31: - | H31: 0 | P31: =SUM(I31:O31) -> 0
A32: 525 | B32: - | C32: - | D32: - | F32: MÓVEL | G32: - | H32: 0 | P32: =SUM(I32:O32) -> 0
A33: 526 | B33: - | C33: - | D33: - | F33: MÓVEL | G33: - | H33: 0 | P33: =SUM(I33:O33) -> 0
A34: 527 | B34: - | C34: - | D34: - | F34: MÓVEL | G34: - | H34: 0 | P34: =SUM(I34:O34) -> 0
A35: 536 | B35: CLARO CLARO CLARO VIVO | C35: PLANO TOTAL SHARE 2.0 PLANO TOTAL SHARE 2.0 PLANO TOTAL SHARE 2.0 SMART EMPRESAS 2GB D | D35: 832140239 832140239 832140239 381199225 | E35: 536 - BH CENTRO | F35: MÓVEL | G35: 11961798677 11991366958 11993141259 31998576863 | H35: R$ 50,59 R$ 50,59 R$ 50,59 R$ 18,99 | I35: 50.59 | J35: 50.59 | K35: 50.59 | L35: 18.99 | P35: =SUM(I35:O35) -> 170.76
A36: 543 | B36: VIVO | C36: SMART EMPRESAS 2GB D | D36: 381199225 | E36: 543 - CAMPO GRANDE | F36: MÓVEL | G36: 21967265450 | H36: 18.99 | I36: 18.99 | P36: =SUM(I36:O36) -> 18.99
A37: 534 | B37: - | C37: - | D37: - | F37: MÓVEL | G37: - | H37: 0 | P37: =SUM(I37:O37) -> 0
A38: 535 | B38: - | C38: - | D38: - | F38: MÓVEL | G38: - | H38: 0 | P38: =SUM(I38:O38) -> 0
A39: 544 | B39: CLARO | C39: PLANO TOTAL SHARE 2.0 | D39: 832140239 | E39: 544 - SHOP PENHA | F39: MÓVEL | G39: 11913072083 | H39: 49.48 | I39: 49.48 | P39: =SUM(I39:O39) -> 49.48
A40: 546 | B40: VIVO | C40: SMART EMPRESAS 2GB D | D40: 381199225 | E40: 546 - SBC | F40: MÓVEL | G40: 11963974721 | H40: 18.99 | I40: 18.99 | P40: =SUM(I40:O40) -> 18.99
A41: 558 | B41: CLARO | C41: PLANO TOTAL SHARE 2.0 | D41: 167736275 | E41: 558 - MANAUS | F41: MÓVEL | G41: 92984007464 92984009650 | H41: R$ 39,78 R$ 39,78 | I41: 39.78 | J41: 39.78 | P41: =SUM(I41:O41) -> 79.56
A42: 559 | B42: - | C42: - | D42: - | E42: 559 -OSASCO PLAZA SHOP | F42: MÓVEL | G42: --- | H42: --- | P42: =SUM(I42:O42) -> 0
A43: 547 | B43: - | C43: - | D43: - | F43: MÓVEL | G43: - | H43: 0 | P43: =SUM(I43:O43) -> 0
A44: 548 | B44: - | C44: - | D44: - | F44: MÓVEL | G44: - | H44: 0 | P44: =SUM(I44:O44) -> 0
A45: 549 | B45: - | C45: - | D45: - | F45: MÓVEL | G45: - | H45: 0 | P45: =SUM(I45:O45) -> 0
A46: 550 | B46: - | C46: - | D46: - | F46: MÓVEL | G46: - | H46: 0 | P46: =SUM(I46:O46) -> 0
A47: 553 | B47: - | C47: - | D47: - | F47: MÓVEL | G47: - | H47: 0 | P47: =SUM(I47:O47) -> 0
A48: 560 | B48: VIVO | C48: SMART EMPRESAS 2GB D | D48: 2027121479 | E48: 560 - CASTENHEIRA SHOP CENTER | F48: MÓVEL | G48: 61996958653 19996492702 61999177867 83981661924 99991551322 | H48: R$ 19,25 R$ 30,50 R$ 18,99 R$ 18,99 R$ 18,99 | I48: 19.25 | J48: 30.5 | K48: 18.99 | L48: 18.99 | M48: 18.99 | P48: =SUM(I48:O48) -> 106.72
A49: 563 | B49: - | C49: PLANO TOTAL SHARE 2.0 | D49: 832140239 | E49: 563 - SANTANA | F49: MÓVEL | G49: - | H49: -
A50: 565 | B50: CLARO | C50: PLANO TOTAL SHARE 2.0 | D50: 167889704 | E50: 565 - SHOP GUARARAPES | F50: MÓVEL | G50: 81973452779 81973452844 81973452887 81973452989 | H50: R$ 40,10 R$ 40,10 R$ 40,10 R$ 40,10 | I50: 40.1 | J50: 40.1 | K50: 40.1 | L50: 40.1 | P50: =SUM(I50:O50) -> 160.4
A51: 571 | B51: VIVO | C51: SMART EMPRESAS 2GB D | D51: 381199225 | E51: 571- SHOP DO VALE | F51: MÓVEL | G51: 11972639969 11974404774 | H51: R$ 18,99 R$ 18,99 | I51: 18.99 | J51: 18.99 | P51: =SUM(I51:O51) -> 37.98
A52: 564 | B52: - | C52: - | D52: - | F52: MÓVEL | G52: - | H52: 0 | P52: =SUM(I52:O52) -> 0
A53: 575 | B53: CLARO | C53: PLANO TOTAL SHARE 2.0 | D53: 167796232 | E53: 575 - ALCANTARA | F53: MÓVEL | G53: 21973009913 21973024047 21973097638 21973126628 | H53: R$ 27,30 R$ 27,30 R$ 27,30 R$ 27,30 | I53: 27.3 | J53: 27.3 | K53: 27.3 | L53: 27.3 | P53: =SUM(I53:O53) -> 109.2
A54: 566 | B54: - | C54: - | D54: - | F54: MÓVEL | G54: - | H54: 0 | P54: =SUM(I54:O54) -> 0
A55: 568 | B55: - | C55: - | D55: - | F55: MÓVEL | G55: - | H55: 0 | P55: =SUM(I55:O55) -> 0
A56: 578 | B56: CLARO | C56: PLANO TOTAL SHARE 2.0 | D56: 167858424 | E56: 578 - FAROL SHOP | F56: MÓVEL | G56: 53991153874 53991156301 | H56: R$ 19,44 R$ 19,44 | I56: 19.44 | J56: 19.44 | P56: =SUM(I56:O56) -> 38.88
A57: 573 | B57: - | C57: - | D57: - | F57: MÓVEL | G57: - | H57: 0 | P57: =SUM(I57:O57) -> 0
A58: 583 | B58: VIVO | C58: SMART EMPRESAS 2GB D | D58: 381199225 | E58: 583 - SHOP DEL REY | F58: MÓVEL | G58: 11968602629 11996469220 11997959698 | H58: R$ 18,99 R$ 18,99 R$ 18,99 | I58: 18.99 | J58: 18.99 | K58: 18.99 | P58: =SUM(I58:O58) -> 56.97
A59: 576 | B59: - | C59: - | D59: - | F59: MÓVEL | G59: - | H59: 0 | P59: =SUM(I59:O59) -> 0
A60: 577 | B60: - | C60: - | D60: - | F60: MÓVEL | G60: - | H60: 0 | P60: =SUM(I60:O60) -> 0
A61: 589 | B61: VIVO | C61: SMART EMPRESAS 2GB D | D61: 381199225 | E61: 589 - MACEIÓ | F61: MÓVEL | G61: 75997068800 | H61: 18.99 | I61: 18.99 | P61: =SUM(I61:O61) -> 18.99
A62: 579 | B62: - | C62: - | D62: - | F62: MÓVEL | G62: - | H62: 0 | P62: =SUM(I62:O62) -> 0
A63: 580 | B63: - | C63: - | D63: - | F63: MÓVEL | G63: - | H63: 0 | P63: =SUM(I63:O63) -> 0
A64: 582 | B64: - | C64: - | D64: - | F64: MÓVEL | G64: - | H64: 0 | P64: =SUM(I64:O64) -> 0
A65: 590 | B65: VIVO | C65: SMART EMPRESAS 2GB D | D65: 381199225 | E65: 590 - BIG SHOP | F65: MÓVEL | G65: 75997069124 | H65: 18.99 | I65: 18.99 | P65: =SUM(I65:O65) -> 18.99
A66: 586 | B66: - | C66: - | D66: - | F66: MÓVEL | G66: - | H66: 0 | P66: =SUM(I66:O66) -> 0
A67: 594 | B67: CLARO | C67: PLANO TOTAL SHARE 2.0 | D67: 167799322 | E67: 594 - FLORIPA SHOP | F67: MÓVEL | G67: 48988241456 48988246761 48988247888 48988248552 | H67: R$ 39,78 R$ 39,78 R$ 39,78 R$ 39,78 | I67: 39.78 | J67: 39.78 | K67: 39.78 | L67: 39.78 | P67: =SUM(I67:O67) -> 159.12
A68: 598 | B68: CLARO | C68: PLANO TOTAL SHARE 2.0 | D68: 167834423 | E68: 598 - SHOP AVENIDA CENTER | F68: MÓVEL | G68: 67991206138 61999662958 62996837351 | H68: R$ 38,12 R$ 30,50 R$ 18,99 | I68: 38.12 | J68: 30.5 | K68: 18.99 | P68: =SUM(I68:O68) -> 87.61
A69: 600 | B69: CLARO | C69: PLANO TOTAL SHARE 2.0 | D69: 167861798 | E69: 600 - SALVADOR SHOP | F69: MÓVEL | G69: 71983069343 71983071908 71983074306 | H69: R$ 10,01 R$ 10,01 R$ 10,01 | I69: 10.01 | J69: 10.01 | K69: 10.01 | P69: =SUM(I69:O69) -> 30.03
A70: 597 | B70: - | C70: - | D70: - | F70: MÓVEL | G70: - | H70: 0 | P70: =SUM(I70:O70) -> 0
A71: 601 | B71: VIVO | C71: SMART EMPRESAS 2GB D | D71: 381199225 | E71: 601 - Shop. Recife | F71: MÓVEL | G71: 81981908266 | H71: 18.99 | I71: 18.99 | P71: =SUM(I71:O71) -> 18.99
A72: 599 | B72: - | C72: - | D72: - | F72: MÓVEL | G72: - | H72: 0 | P72: =SUM(I72:O72) -> 0
A73: 604 | B73: VIVO | C73: SMART EMPRESAS 2GB D | D73: 381199225 | E73: 604 - VITORIA DA CONQUISTA | F73: MÓVEL | G73: 71999321473 | H73: 18.99 | I73: 18.99 | P73: =SUM(I73:O73) -> 18.99
A74: 605 | B74: VIVO | C74: SMART EMPRESAS 2GB D | D74: 381199225 | E74: 605 - SHOP AVENIDA CENTER | F74: MÓVEL | G74: 47992402072 47991083677 47991320744 | H74: R$ 18,99 R$ 18,99 R$ 18,99 | I74: 18.99 | J74: 18.99 | K74: 18.99 | P74: =SUM(I74:O74) -> 56.97
A75: 607 | B75: CLARO | C75: PLANO TOTAL SHARE 2.0 | D75: 797293511 | E75: 607 - PÁTIO LIMERIRA SHOP | F75: MÓVEL | G75: 11988936521 | H75: 143.79 | I75: 143.79 | P75: =SUM(I75:O75) -> 143.79
A76: 617 | B76: VIVO | C76: SMART EMPRESAS 2GB D | D76: 381199225 | E76: 617 - GOIANIA | F76: MÓVEL | G76: 11944634137 62996807284 | H76: R$ 18,99 R$ 18,99 | I76: 18.99 | J76: 18.99 | P76: =SUM(I76:O76) -> 37.98
A77: 606 | B77: - | C77: - | D77: - | F77: MÓVEL | G77: - | H77: 0 | P77: =SUM(I77:O77) -> 0
A78: 618 | B78: VIVO | C78: SMART EMPRESAS 2GB D | D78: 381199225 | E78: 618 - SHOP JEQUITIBÁ | F78: MÓVEL | G78: 82981644453 | H78: 18.99 | I78: 18.99 | P78: =SUM(I78:O78) -> 18.99
A79: 608 | B79: - | C79: - | D79: - | F79: MÓVEL | G79: - | H79: 0 | P79: =SUM(I79:O79) -> 0
A80: 610 | B80: - | C80: - | D80: - | F80: MÓVEL | G80: - | H80: 0 | P80: =SUM(I80:O80) -> 0
A81: 613 | B81: - | C81: - | D81: - | F81: MÓVEL | G81: - | H81: 0 | P81: =SUM(I81:O81) -> 0
A82: 625 | B82: CLARO CLARO CLARO CLARO CLARO CLARO VIVO | C82: PLANO TOTAL SHARE 2.0 PLANO TOTAL SHARE 2.0 PLANO TOTAL SHARE 2.0 PLANO TOTAL SHARE 2.0 PLANO TOTAL SHARE 2.0 PLANO TOTAL SHARE 2.0 SMART EMPRESAS 2GB D | D82: 167836949 | E82: 625 - CAMPO GRANDE | F82: MÓVEL | G82: 67991206191 67991216739 67991260018 67991262036 67991203389 11913614392 67996915048 | H82: R$ 38,49 R$ 38,49 R$ 38,49 R$ 38,49 R$ 38,49 R$ 143,79 R$ 18,99 | I82: 38.49 | J82: 38.49 | K82: 38.49 | L82: 38.49 | M82: 38.49 | N82: 143.79 | O82: 18.99 | P82: =SUM(I82:O82) -> 355.23
A83: 627 | B83: VIVO | C83: PLANO INTERNET BOX PJ | D83: 2027121479 | E83: 627 - Partage Norte Shop. Natal | F83: MÓVEL | G83: 11942025033 | H83: 104.05 | I83: 104.05 | P83: =SUM(I83:O83) -> 104.05
A84: 619 | B84: - | C84: - | D84: - | F84: MÓVEL | G84: - | H84: 0 | P84: =SUM(I84:O84) -> 0
A85: 622 | B85: - | C85: - | D85: - | F85: MÓVEL | G85: - | H85: 0 | P85: =SUM(I85:O85) -> 0
A86: 623 | B86: - | C86: - | D86: - | F86: MÓVEL | G86: - | H86: 0 | P86: =SUM(I86:O86) -> 0
A87: 624 | B87: - | C87: - | D87: - | F87: MÓVEL | G87: - | H87: 0 | P87: =SUM(I87:O87) -> 0
A88: 629 | B88: VIVO | C88: SMART EMPRESAS 2GB D | D88: 381199225 | E88: 629 - PLAZA AVENIDA SHOP | F88: MÓVEL | G88: 48991021138 | H88: 18.99 | I88: 18.99 | P88: =SUM(I88:O88) -> 18.99
A89: 626 | B89: - | C89: - | D89: - | F89: MÓVEL | G89: - | H89: 0 | P89: =SUM(I89:O89) -> 0
A90: 635 | B90: VIVO | C90: SMART EMPRESAS 0.5GB D | D90: 381199225 | E90: 635 - MINAS SHOP | F90: MÓVEL | G90: 11943904647 11943837705 11944706195 | H90: R$ 30,50 R$ 30,50 R$ 18,99 | I90: 30.5 | J90: 30.5 | K90: 18.99 | P90: =SUM(I90:O90) -> 79.99
A91: 639 | B91: VIVO | C91: SMART EMPRESAS 2GB D | D91: 2027121479 | E91: 639 - Cubatão | F91: MÓVEL | G91: 11930382197 11933670940 | H91: R$ 19,45 R$ 18,99 | I91: 19.45 | J91: 18.99 | P91: =SUM(I91:O91) -> 18.99
A92: 631 | B92: - | C92: - | D92: - | F92: MÓVEL | G92: - | H92: 0 | P92: =SUM(I92:O92) -> 0
A93: 632 | B93: - | C93: - | D93: - | F93: MÓVEL | G93: - | H93: 0 | P93: =SUM(I93:O93) -> 0
A94: 633 | B94: - | C94: - | D94: - | F94: MÓVEL | G94: - | H94: 0 | P94: =SUM(I94:O94) -> 0
A95: 650 | B95: VIVO | C95: PLANO INTERNET BOX PJ | D95: 2027121479 | E95: 650 - BOULEVARD SHOP BELEM | F95: MÓVEL | G95: 11942876965 | H95: 104.05 | I95: 104.05 | P95: =SUM(I95:O95) -> 104.05
A96: 636 | B96: - | C96: - | D96: - | F96: MÓVEL | G96: - | H96: 0 | P96: =SUM(I96:O96) -> 0
A97: 651 | B97: VIVO | C97: SMART EMPRESAS 2GB D | D97: 381199225 | E97: 651 - SHOP CONJUNTO NACIONAL | F97: MÓVEL | G97: 73999287137 | H97: 18.99 | I97: 18.99 | P97: =SUM(I97:O97) -> 18.99
A98: 640 | B98: - | C98: - | D98: - | F98: MÓVEL | G98: - | H98: 0 | P98: =SUM(I98:O98) -> 0
A99: 641 | B99: - | C99: - | D99: - | F99: MÓVEL | G99: - | H99: 0 | P99: =SUM(I99:O99) -> 0
A100: 642 | B100: - | C100: - | D100: - | F100: MÓVEL | G100: - | H100: 0 | P100: =SUM(I100:O100) -> 0
...

Sheet Dash_Custo
A2: Custo por Operadora - Lojas | F2: Custo por Operadora - EC-CDs-Datacenter
A3: Operadora | B3: Qtde de Links | C3: Valor Total | D3: Média | F3: Operadora | G3: Qtde de Links | H3: Valor Total | I3: Média
A4: Embratel | B4: =COUNTIF('Detalhes Links Lojas'!D$2:D$216,"Embratel") + COUNTIF('Detalhes Links Lojas'!L$2:L$216,"Embratel") -> 4 | C4: =SUMIF('Detalhes Links Lojas'!D$2:D$216,"Embratel",'Detalhes Links Lojas'!K$2:K$216) + SUMIF('Detalhes Links Lojas'!L$2:L$216,"Embratel",'Detalhes Links Lojas'!S$2:S$216) -> 1862.71 | D4: =IFERROR(C4/B4,0) -> 465.6775 | F4: Claro | G4: =COUNTIF('Detalhes EC-EQX-CDs'!D$2:D$7,"Claro") + COUNTIF('Detalhes EC-EQX-CDs'!K$2:K$7,"Claro") + COUNTIF('Detalhes EC-EQX-CDs'!Z$2:Z$7,"Claro") -> 2 | H4: =SUMIF('Detalhes EC-EQX-CDs'!D$2:D$7,"Claro",'Detalhes EC-EQX-CDs'!J$2:J$7) + SUMIF('Detalhes EC-EQX-CDs'!K$2:K$7,"Claro",'Detalhes EC-EQX-CDs'!Q$2:Q$7) + SUMIF('Detalhes EC-EQX-CDs'!Z$2:Z$7,"Claro",'Detalhes EC-EQX-CDs'!AF$2:AF$7) -> 3876.3 | I4: =IFERROR(H4/G4,0) -> 1938.15
A5: Claro | B5: =COUNTIF('Detalhes Links Lojas'!D$2:D$216,"Claro") + COUNTIF('Detalhes Links Lojas'!L$2:L$216,"Claro") -> 175 | C5: =SUMIF('Detalhes Links Lojas'!D2:D216,"Claro",'Detalhes Links Lojas'!K2:K216) + SUMIF('Detalhes Links Lojas'!L2:L216,"Claro",'Detalhes Links Lojas'!S2:S216) -> 71848.24 | D5: =IFERROR(C5/B5,0) -> 410.56137 | F5: Vivo | G5: =COUNTIF('Detalhes EC-EQX-CDs'!D$2:D$7,"Vivo") + COUNTIF('Detalhes EC-EQX-CDs'!K$2:K$7,"Vivo") + COUNTIF('Detalhes EC-EQX-CDs'!Z$2:Z$7,"Vivo") -> 4 | H5: =SUMIF('Detalhes EC-EQX-CDs'!D$2:D$7,"Vivo",'Detalhes EC-EQX-CDs'!J$2:J$7) + SUMIF('Detalhes EC-EQX-CDs'!K$2:K$7,"Vivo",'Detalhes EC-EQX-CDs'!Q$2:Q$7) + SUMIF('Detalhes EC-EQX-CDs'!Z$2:Z$7,"Vivo",'Detalhes EC-EQX-CDs'!AF$2:AF$7) -> 9800.19 | I5: =IFERROR(H5/G5,0) -> 2450.0475
A6: Vivo | B6: =COUNTIF('Detalhes Links Lojas'!D$2:D$216,"Vivo") + COUNTIF('Detalhes Links Lojas'!L$2:L$216,"Vivo") -> 76 | C6: =SUMIF('Detalhes Links Lojas'!D2:D216,"Vivo",'Detalhes Links Lojas'!K2:K216) + SUMIF('Detalhes Links Lojas'!L2:L216,"Vivo",'Detalhes Links Lojas'!S2:S216) -> 22187.44 | D6: =IFERROR(C6/B6,0) -> 291.94 | F6: Fibrion | G6: =COUNTIF('Detalhes EC-EQX-CDs'!D$2:D$7,"Fibrion") + COUNTIF('Detalhes EC-EQX-CDs'!K$2:K$7,"Fibrion") + COUNTIF('Detalhes EC-EQX-CDs'!Z$2:Z$7,"Fibrion") -> 1 | H6: =SUMIF('Detalhes EC-EQX-CDs'!D$2:D$7,"Fibrion",'Detalhes EC-EQX-CDs'!J$2:J$7) + SUMIF('Detalhes EC-EQX-CDs'!K$2:K$7,"Fibrion",'Detalhes EC-EQX-CDs'!Q$2:Q$7) + SUMIF('Detalhes EC-EQX-CDs'!Z$2:Z$7,"Fibrion",'Detalhes EC-EQX-CDs'!AF$2:AF$7) -> 430 | I6: =IFERROR(H6/G6,0) -> 430
A7: Fibrion | B7: =COUNTIF('Detalhes Links Lojas'!D$2:D$216,"Fibrion") + COUNTIF('Detalhes Links Lojas'!L$2:L$216,"Fibrion") -> 28 | C7: =SUMIF('Detalhes Links Lojas'!D2:D216,"Fibrion",'Detalhes Links Lojas'!K2:K216) + SUMIF('Detalhes Links Lojas'!L2:L216,"Fibrion",'Detalhes Links Lojas'!S2:S216) -> 14240.72 | D7: =IFERROR(C7/B7,0) -> 508.59714 | F7: Mundivox | G7: =COUNTIF('Detalhes EC-EQX-CDs'!D$2:D$7,"Mundivox") + COUNTIF('Detalhes EC-EQX-CDs'!K$2:K$7,"Mundivox") + COUNTIF('Detalhes EC-EQX-CDs'!Z$2:Z$7,"Mundivox") -> 1 | H7: =SUMIF('Detalhes EC-EQX-CDs'!D$2:D$7,"Mundivox",'Detalhes EC-EQX-CDs'!J$2:J$7) + SUMIF('Detalhes EC-EQX-CDs'!K$2:K$7,"Mundivox",'Detalhes EC-EQX-CDs'!Q$2:Q$7) + SUMIF('Detalhes EC-EQX-CDs'!Z$2:Z$7,"Mundivox",'Detalhes EC-EQX-CDs'!AF$2:AF$7) -> 2750 | I7: =IFERROR(H7/G7,0) -> 2750
A8: Vero | B8: =COUNTIF('Detalhes Links Lojas'!D$2:D$216,"Vero") + COUNTIF('Detalhes Links Lojas'!L$2:L$216,"Vero") -> 66 | C8: =SUMIF('Detalhes Links Lojas'!D2:D216,"Vero",'Detalhes Links Lojas'!K2:K216) + SUMIF('Detalhes Links Lojas'!L2:L216,"Vero",'Detalhes Links Lojas'!S2:S216) -> 19667.81 | D8: =IFERROR(C8/B8,0) -> 297.99712 | F8: Algar | G8: =COUNTIF('Detalhes EC-EQX-CDs'!D$2:D$7,"Algar") + COUNTIF('Detalhes EC-EQX-CDs'!K$2:K$7,"Algar") + COUNTIF('Detalhes EC-EQX-CDs'!Z$2:Z$7,"Algar") -> 3 | H8: =SUMIF('Detalhes EC-EQX-CDs'!D$2:D$7,"Algar",'Detalhes EC-EQX-CDs'!J$2:J$7) + SUMIF('Detalhes EC-EQX-CDs'!K$2:K$7,"Algar",'Detalhes EC-EQX-CDs'!Q$2:Q$7) + SUMIF('Detalhes EC-EQX-CDs'!Z$2:Z$7,"Algar",'Detalhes EC-EQX-CDs'!AF$2:AF$7) -> 2085.81 | I8: =IFERROR(H8/G8,0) -> 695.27
A9: Mundivox | B9: =COUNTIF('Detalhes Links Lojas'!D$2:D$216,"Mundivox") + COUNTIF('Detalhes Links Lojas'!L$2:L$216,"Mundivox") -> 24 | C9: =SUMIF('Detalhes Links Lojas'!D2:D216,"Mundivox",'Detalhes Links Lojas'!K2:K216) + SUMIF('Detalhes Links Lojas'!L2:L216,"Mundivox",'Detalhes Links Lojas'!S2:S216) -> 9291.91 | D9: =IFERROR(C9/B9,0) -> 387.16292 | F9: Megatelecom | G9: =COUNTIF('Detalhes EC-EQX-CDs'!D$2:D$7,"Megatelecom") + COUNTIF('Detalhes EC-EQX-CDs'!K$2:K$7,"Megatelecom") + COUNTIF('Detalhes EC-EQX-CDs'!Z$2:Z$7,"Megatelecom") -> 1 | H9: =SUMIF('Detalhes EC-EQX-CDs'!D$2:D$7,"Megatelecom",'Detalhes EC-EQX-CDs'!J$2:J$7) + SUMIF('Detalhes EC-EQX-CDs'!K$2:K$7,"Megatelecom",'Detalhes EC-EQX-CDs'!Q$2:Q$7) + SUMIF('Detalhes EC-EQX-CDs'!Z$2:Z$7,"Megatelecom",'Detalhes EC-EQX-CDs'!AF$2:AF$7) -> 997.79 | I9: =IFERROR(H9/G9,0) -> 997.79
A10: Oi | B10: =COUNTIF('Detalhes Links Lojas'!D$2:D$216,"Oi") + COUNTIF('Detalhes Links Lojas'!L$2:L$216,"Oi") -> 3 | C10: =SUMIF('Detalhes Links Lojas'!D$2:D$216,"Oi",'Detalhes Links Lojas'!K$2:K$216) + SUMIF('Detalhes Links Lojas'!L$2:L$216,"Oi",'Detalhes Links Lojas'!S$2:S$216) -> 2114.52 | D10: =IFERROR(C10/B10,0) -> 704.84 | F10: Total | G10: =SUM(G4:G9) -> 12 | H10: =SUM(H4:H9) -> 19940.09
A11: Algar | B11: =COUNTIF('Detalhes Links Lojas'!D$2:D$216,"Algar") + COUNTIF('Detalhes Links Lojas'!L$2:L$216,"Algar") -> 21 | C11: =SUMIF('Detalhes Links Lojas'!D$2:D$216,"Algar",'Detalhes Links Lojas'!K$2:K$216) + SUMIF('Detalhes Links Lojas'!L$2:L$216,"Algar",'Detalhes Links Lojas'!S$2:S$216) -> 9089.79 | D11: =IFERROR(C11/B11,0) -> 432.84714
A12: SEA Telecom | B12: =COUNTIF('Detalhes Links Lojas'!D$2:D$216,"SEA Telecom") + COUNTIF('Detalhes Links Lojas'!L$2:L$216,"SEA Telecom") -> 1 | C12: =SUMIF('Detalhes Links Lojas'!D$2:D$216,"SEA Telecom",'Detalhes Links Lojas'!K$2:K$216) + SUMIF('Detalhes Links Lojas'!L$2:L$216,"SEA Telecom",'Detalhes Links Lojas'!S$2:S$216) -> 189 | D12: =IFERROR(C12/B12,0) -> 189 | F12: Qtde de lojas | H12: =SUM('Por Loja'!D2:D216) -> 215
A13: SP18 | B13: =COUNTIF('Detalhes Links Lojas'!D$2:D$216,"SP18") + COUNTIF('Detalhes Links Lojas'!L$2:L$216,"SP18") -> 2 | C13: =SUMIF('Detalhes Links Lojas'!D$2:D$216,"SP18",'Detalhes Links Lojas'!K$2:K$216) + SUMIF('Detalhes Links Lojas'!L$2:L$216,"SP18",'Detalhes Links Lojas'!S$2:S$216) -> 1214.28 | D13: =IFERROR(C13/B13,0) -> 607.14
A14: Tesa | B14: =COUNTIF('Detalhes Links Lojas'!D$2:D$216,"Tesa") + COUNTIF('Detalhes Links Lojas'!L$2:L$216,"Tesa") -> 2 | C14: =SUMIF('Detalhes Links Lojas'!D$2:D$216,"Tesa",'Detalhes Links Lojas'!K$2:K$216) + SUMIF('Detalhes Links Lojas'!L$2:L$216,"Tesa",'Detalhes Links Lojas'!S$2:S$216) -> 1409.23 | D14: =IFERROR(C14/B14,0) -> 704.615
A15: Wipi | B15: =COUNTIF('Detalhes Links Lojas'!D$2:D$216,"Wipi") + COUNTIF('Detalhes Links Lojas'!L$2:L$216,"Wipi") -> 1 | C15: =SUMIF('Detalhes Links Lojas'!D$2:D$216,"Wipi",'Detalhes Links Lojas'!K$2:K$216) + SUMIF('Detalhes Links Lojas'!L$2:L$216,"Wipi",'Detalhes Links Lojas'!S$2:S$216) -> 710 | D15: =IFERROR(C15/B15,0) -> 710 | F15: Qtde de links | H15: =SUM(B21+G10) -> 441
A16: Megatelecom | B16: =COUNTIF('Detalhes Links Lojas'!D$2:D$216,"Megatelecom") + COUNTIF('Detalhes Links Lojas'!L$2:L$216,"Megatelecom") -> 0 | C16: =SUMIF('Detalhes Links Lojas'!D$2:D$216,"Megatelecom",'Detalhes Links Lojas'!K$2:K$216) + SUMIF('Detalhes Links Lojas'!L$2:L$216,"Megatelecom",'Detalhes Links Lojas'!S$2:S$216) -> 0 | D16: =IFERROR(C16/B16,0) -> 0
A17: WFT / AST | B17: =COUNTIF('Detalhes Links Lojas'!D$2:D$216,"WFT/AST") + COUNTIF('Detalhes Links Lojas'!L$2:L$216,"WFT/AST") -> 1 | C17: =SUMIF('Detalhes Links Lojas'!D$2:D$216,"WFT/AST",'Detalhes Links Lojas'!K$2:K$216) + SUMIF('Detalhes Links Lojas'!L$2:L$216,"WFT/AST",'Detalhes Links Lojas'!S$2:S$216) -> 200 | D17: =IFERROR(C17/B17,0) -> 200
A18: Vtal | B18: =COUNTIF('Detalhes Links Lojas'!D$2:D$216,"Vtal") + COUNTIF('Detalhes Links Lojas'!L$2:L$216,"Vtal") -> 21 | C18: =SUMIF('Detalhes Links Lojas'!D$2:D$216,"Vtal",'Detalhes Links Lojas'!K$2:K$216) + SUMIF('Detalhes Links Lojas'!L$2:L$216,"Vtal",'Detalhes Links Lojas'!S$2:S$216) -> 6694.63 | D18: =IFERROR(C18/B18,0) -> 318.7919 | F18: Custo total | H18: =SUM(C21+H10) -> 181880.27
A19: Irapido | B19: =COUNTIF('Detalhes Links Lojas'!D$2:D$216,"Irapido") + COUNTIF('Detalhes Links Lojas'!L$2:L$216,"Irapido") -> 3 | C19: =SUMIF('Detalhes Links Lojas'!D$2:D$216,"Irapido",'Detalhes Links Lojas'!K$2:K$216) + SUMIF('Detalhes Links Lojas'!L$2:L$216,"Irapido",'Detalhes Links Lojas'!S$2:S$216) -> 900 | D19: =IFERROR(C19/B19,0) -> 300
A20: ITS Brasil | B20: =COUNTIF('Detalhes Links Lojas'!D$2:D$216,"ITS Brasil") + COUNTIF('Detalhes Links Lojas'!L$2:L$216,"ITS Brasil") -> 1 | C20: =SUMIF('Detalhes Links Lojas'!D$2:D$216,"ITS Brasil",'Detalhes Links Lojas'!K$2:K$216) + SUMIF('Detalhes Links Lojas'!L$2:L$216,"ITS Brasil",'Detalhes Links Lojas'!S$2:S$216) -> 319.9 | D20: =IFERROR(C20/B20,0) -> 319.9
A21: Total | B21: =SUM(B4:B20) -> 429 | C21: =SUM(C4:C20) -> 161940.18

Sheet Dash-EC-EQX-CDs 
A1: SITE | B1: EC | C1: EQUINIX | D1: CD ITAQUA | E1: CD BLUMENAU | F1: CD GOIÂNIA | G1: CD NAVEGANTES
A2: CR | B2: EC | C2: EQX | D2: CD-820 | E2: CD-811 | F2: CD-807 | G2: CD-818
A3: OPERADORA 1 | B3: Claro | C3: Vivo | D3: =VLOOKUP($D$2,'Detalhes EC-EQX-CDs'!$A$2:$AF$7,4,FALSE) -> Vivo | E3: =VLOOKUP($E$2,'Detalhes EC-EQX-CDs'!$A$2:$AF$7,4,FALSE) -> Algar | F3: =VLOOKUP($F$2,'Detalhes EC-EQX-CDs'!$A$2:$AF$7,4,FALSE) -> Algar | G3: =VLOOKUP($G$2,'Detalhes EC-EQX-CDs'!$A$2:$AF$7,4,FALSE) -> Algar | I3: SITE | J3: QTDE LINKS | K3: VALOR
A4: TIPO | B4: Dedicado | C4: Dedicado | D4: =VLOOKUP($D$2,'Detalhes EC-EQX-CDs'!$A$2:$AF$7,9,FALSE) -> Dedicado | E4: =VLOOKUP($E$2,'Detalhes EC-EQX-CDs'!$A$2:$AF$7,9,FALSE) -> Dedicado | F4: =VLOOKUP($F$2,'Detalhes EC-EQX-CDs'!$A$2:$AF$7,9,FALSE) -> Dedicado | G4: =VLOOKUP($G$2,'Detalhes EC-EQX-CDs'!$A$2:$AF$7,9,FALSE) -> Dedicado | I4: EC | J4: 3 | K4: =SUM(B8+B15+B22) -> 9064.3
A5: VELOCIDADE | B5: 1Gbps | C5: 1 GB | D5: =VLOOKUP($D$2,'Detalhes EC-EQX-CDs'!$A$2:$AF$7,8,FALSE) -> 200Mb | E5: =VLOOKUP($E$2,'Detalhes EC-EQX-CDs'!$A$2:$AF$7,8,FALSE) -> 20Mb | F5: =VLOOKUP($F$2,'Detalhes EC-EQX-CDs'!$A$2:$AF$7,8,FALSE) -> 10Mb | G5: =VLOOKUP($G$2,'Detalhes EC-EQX-CDs'!$A$2:$AF$7,8,FALSE) -> 20Mb | I5: CD Itaqua | J5: 2 | K5: =SUM(D8+D15) -> 2340.03
A6: DATA DE ATIVAÇÃO | B6: 46112 | C6: 45568 | D6: =VLOOKUP($D$2,'Detalhes EC-EQX-CDs'!$A$2:$AF$7,5,FALSE) -> 45338 | E6: =VLOOKUP($E$2,'Detalhes EC-EQX-CDs'!$A$2:$AF$7,5,FALSE) -> 44596 | F6: =VLOOKUP($F$2,'Detalhes EC-EQX-CDs'!$A$2:$AF$7,5,FALSE) -> 44617 | G6: =VLOOKUP($G$2,'Detalhes EC-EQX-CDs'!$A$2:$AF$7,5,FALSE) -> 44589 | I6: CD Blumenau | J6: 2 | K6: =SUM(E8+E15) -> 1986.5
A7: VIGÊNCIA | B7: 47208 | C7: 46663 | D7: =VLOOKUP($D$2,'Detalhes EC-EQX-CDs'!$A$2:$AF$7,6,FALSE) -> 46434 | E7: =VLOOKUP($E$2,'Detalhes EC-EQX-CDs'!$A$2:$AF$7,6,FALSE) -> Vencido | F7: =VLOOKUP($F$2,'Detalhes EC-EQX-CDs'!$A$2:$AF$7,6,FALSE) -> Vencido | G7: =VLOOKUP($G$2,'Detalhes EC-EQX-CDs'!$A$2:$AF$7,6,FALSE) -> Vencido | I7: CD Goiânia | J7: 2 | K7: =SUM(F8+F15) -> 850.62
A8: VALOR | B8: 2914.3 | C8: 4110.16 | D8: =VLOOKUP($D$2,'Detalhes EC-EQX-CDs'!$A$2:$AF$7,10,FALSE) -> 1910.03 | E8: =VLOOKUP($E$2,'Detalhes EC-EQX-CDs'!$A$2:$AF$7,10,FALSE) -> 1024.5 | F8: =VLOOKUP($F$2,'Detalhes EC-EQX-CDs'!$A$2:$AF$7,10,FALSE) -> 470.62 | G8: =VLOOKUP($G$2,'Detalhes EC-EQX-CDs'!$A$2:$AF$7,10,FALSE) -> 590.69 | I8: CD Navegantes | J8: 2 | K8: =SUM(G8+G15) -> 1588.48
A9: DESIGNAÇÃO | B9: SPO/IP/40295 | C9: 110005641701194 | D9: =VLOOKUP($D$2,'Detalhes EC-EQX-CDs'!$A$2:$AF$7,7,FALSE) -> 113004643101796 | E9: =VLOOKUP($E$2,'Detalhes EC-EQX-CDs'!$A$2:$AF$7,7,FALSE) -> 8756818/8756819 | F9: =VLOOKUP($F$2,'Detalhes EC-EQX-CDs'!$A$2:$AF$7,7,FALSE) -> 8754445/8754447 | G9: =VLOOKUP($G$2,'Detalhes EC-EQX-CDs'!$A$2:$AF$7,7,FALSE) -> 8754444/8754446 | I9: Equinix | J9: 1 | K9: =SUM(C8+C15+C22+C29) -> 4110.16
A10: OPERADORA 2 | B10: Mundivox | D10: =VLOOKUP($D$2,'Detalhes EC-EQX-CDs'!$A$2:$AF$7,11,FALSE) -> Fibrion | E10: Claro | F10: Vivo | G10: MegaTelecom | I10: Custo Total | J10: =SUM(J4:J9) -> 12 | K10: =SUM(K4:K9) -> 19940.09
A11: TIPO | B11: Dedicado | D11: =VLOOKUP($D$2,'Detalhes EC-EQX-CDs'!$A$2:$AF$7,16,FALSE) -> Dedicado | E11: =VLOOKUP($E$2,'Detalhes EC-EQX-CDs'!$A$2:$AF$7,16,FALSE) -> Dedicado | F11: =VLOOKUP($F$2,'Detalhes EC-EQX-CDs'!$A$2:$AF$7,16,FALSE) -> Dedicado | G11: =VLOOKUP($G$2,'Detalhes EC-EQX-CDs'!$A$2:$AF$7,16,FALSE) -> Dedicado
A12: VELOCIDADE | B12: 1Gbps | D12: =VLOOKUP($D$2,'Detalhes EC-EQX-CDs'!$A$2:$AF$7,15,FALSE) -> 100Mb | E12: =VLOOKUP($E$2,'Detalhes EC-EQX-CDs'!$A$2:$AF$7,15,FALSE) -> 50Mb | F12: =VLOOKUP($F$2,'Detalhes EC-EQX-CDs'!$A$2:$AF$7,15,FALSE) -> 20Mb | G12: =VLOOKUP($G$2,'Detalhes EC-EQX-CDs'!$A$2:$AF$7,15,FALSE) -> 20Mb
A13: DATA DE ATIVAÇÃO | B13: 46010 | D13: =VLOOKUP($D$2,'Detalhes EC-EQX-CDs'!$A$2:$AF$7,12,FALSE) -> 45609 | E13: =VLOOKUP($E$2,'Detalhes EC-EQX-CDs'!$A$2:$AF$7,12,FALSE) -> 46218 | F13: =VLOOKUP($F$2,'Detalhes EC-EQX-CDs'!$A$2:$AF$7,12,FALSE) -> 46176 | G13: =VLOOKUP($G$2,'Detalhes EC-EQX-CDs'!$A$2:$AF$7,12,FALSE) -> 44735 | I13: OPERADORA | J13: QTDE LINKS | K13: CUSTO
A14: VIGÊNCIA | B14: 47106 | D14: =VLOOKUP($D$2,'Detalhes EC-EQX-CDs'!$A$2:$AF$7,13,FALSE) -> 46704 | E14: =VLOOKUP($E$2,'Detalhes EC-EQX-CDs'!$A$2:$AF$7,13,FALSE) -> 47314 | F14: =VLOOKUP($F$2,'Detalhes EC-EQX-CDs'!$A$2:$AF$7,13,FALSE) -> 47272 | G14: =VLOOKUP($G$2,'Detalhes EC-EQX-CDs'!$A$2:$AF$7,13,FALSE) -> Vencido | I14: Vivo | J14: 4 | K14: =SUM(B22+C8+D8+F15) -> 9800.19
A15: VALOR | B15: 2750 | D15: =VLOOKUP($D$2,'Detalhes EC-EQX-CDs'!$A$2:$AF$7,17,FALSE) -> 430 | E15: =VLOOKUP($E$2,'Detalhes EC-EQX-CDs'!$A$2:$AF$7,17,FALSE) -> 962 | F15: =VLOOKUP($F$2,'Detalhes EC-EQX-CDs'!$A$2:$AF$7,17,FALSE) -> 380 | G15: =VLOOKUP($G$2,'Detalhes EC-EQX-CDs'!$A$2:$AF$7,17,FALSE) -> 997.79 | I15: Claro | J15: 2 | K15: =SUM(B8+E15) -> 3876.3
A16: DESIGNAÇÃO | B16: 11020625 | D16: =VLOOKUP($D$2,'Detalhes EC-EQX-CDs'!$A$2:$AF$7,14,FALSE) -> ZZ45726039001 | E16: =VLOOKUP($E$2,'Detalhes EC-EQX-CDs'!$A$2:$AF$7,14,FALSE) -> BNU/IP/01514 | F16: =VLOOKUP($F$2,'Detalhes EC-EQX-CDs'!$A$2:$AF$7,14,FALSE) -> 621980221280394 | G16: =VLOOKUP($G$2,'Detalhes EC-EQX-CDs'!$A$2:$AF$7,14,FALSE) -> TIT000872 | I16: Algar | J16: 3 | K16: =SUM(E8+F8+G8) -> 2085.81
A17: OPERADORA 3 | B17: Vivo | I17: WCS | J17: 1 | K17: =SUM(D15) -> 430
A18: TIPO | B18: Dedicado | I18: Mega Telecom | J18: 1 | K18: =SUM(G15) -> 997.79
A19: VELOCIDADE | B19: 1 GB | I19: Mundivox | J19: 1 | K19: =SUM(B15) -> 2750
A20: DATA DE ATIVAÇÃO | B20: 46024 | I20: Total | J20: =SUM(J14:J19) -> 12 | K20: =SUM(K14:K19) -> 19940.09
A21: VIGÊNCIA | B21: 47120
A22: VALOR | B22: 3400
A23: DESIGNAÇÃO | B23: 110003825281299

Sheet Espelho EC-CDs-2025
A1: SITE | B1: EC | C1: TIVIT | D1: EQUINIX | E1: CD ITAQUA | F1: CD BLUMENAU | G1: CD GOIÂNIA | H1: CD NAVEGANTES | I1: SITEF
A2: CR | B2: 41100 | C2: TIVIT | E2: CD-820 | F2: CD-811 | G2: CD-807 | H2: CD-818 | I2: SITEF 2 | J2: SITEF 1
A3: OPERADORA 1 | B3: Embratel | C3: Embratel | E3: Vivo | F3: Algar | G3: Algar | H3: Algar | I3: Vivo | J3: Vivo | L3: SITE | M3: QTDE LINKS | N3: VALOR
A4: TIPO | B4: Dedicado | C4: Dedicado | E4: Dedicado | F4: Dedicado | G4: Dedicado | H4: Dedicado | I4: MPLS -P2 EQN-ALA | J4: MPLS -P1 EQN-MIG | L4: EC | M4: 4 | N4: =SUM(B8+B15+B22+B29) -> 12033.18
A5: VELOCIDADE | B5: 500Mb | C5: 1Gb | E5: 200Mb | F5: 20Mb | G5: 10Mb | H5: 20Mb | I5: 2Mb | J5: 2Mb | L5: TIVIT | M5: 4 | N5: =SUM(C8+C15+C22+C36) -> 13272.39
A6: DATA DE ATIVAÇÃO | B6: 44903 | C6: 44901 | E6: 45338 | F6: 44596 | G6: 44617 | H6: 44589 | I6: 43738 | J6: 43738 | L6: CD Itaqua | M6: 3 | N6: =SUM(E8+E15+E22) -> 3374.59
A7: VIGÊNCIA | B7: 45999 | C7: Cancelado | E7: 46434 | F7: Vencido | G7: Vencido | H7: Vencido | I7: Cancelado | J7: Cancelado | L7: CD Blumenau | M7: 2 | N7: =SUM(F8+F15) -> 1464.36
A8: VALOR | B8: 3198.68 | C8: 5657.1 | E8: 1910.03 | F8: 952.94 | G8: 440.78 | H8: 562.27 | I8: 832.3 | J8: 832.3 | L8: CD Goiânia | M8: 2 | N8: =SUM(G8+G15) -> 1025.42
A9: DESIGNAÇÃO | B9: SPO/IP/40295 | C9: SPO/IP/70714 | E9: 113004643101796 | F9: 8756818/8756819 | G9: 8754445/8754447 | H9: 8754444/8754446 | I9: 110714191224793 | J9: 110003106383097 | L9: CD Navegantes | M9: 2 | N9: =SUM(H8+H15) -> 1560.06
A10: OPERADORA 2 | B10: Vivo | C10: Vivo | E10: WCS | F10: Embratel | G10: Vivo | H10: MegaTelecom | I10: Embratel | J10: Embratel | L10: SITEF | M10: 6 | N10: =SUM(I8+J8+I15+J15+C29+C43) -> 13984.59
A11: TIPO | B11: Dedicado | C11: Dedicado | E11: Dedicado | F11: Dedicado | G11: Dedicado | H11: Dedicado | I11: MPLS | J11: MPLS | L11: Equinix | M11: 1 | N11: =SUM(D8+D15+D22+D29) -> 3025.46
A12: VELOCIDADE | B12: 1 GB | C12: 1 GB | E12: 100 MB | F12: 20 MB | G12: 10 MB | H12: 20 MB | I12: 2Mb | J12: 2Mb | L12: Custo Total | M12: =SUM(M4:M10) -> 23 | N12: =SUM(N4:N11) -> 49740.05
A13: DATA DE ATIVAÇÃO | B13: 45595 | C13: 45132 | E13: 45609 | F13: 44714 | G13: 44470 | H13: 44735 | I13: 43346 | J13: 43361
A14: VIGÊNCIA | B14: 46690 | C14: 46228 | E14: 46704 | F14: Vencido | G14: Vencido | H14: Vencido | I14: Cancelado | J14: Cancelado
A15: VALOR | B15: 3613.93 | C15: 4110.16 | E15: 430 | F15: 511.42 | G15: 584.64 | H15: 997.79 | I15: 1343.81 | J15: 1909.68 | L15: OPERADORA | M15: QTDE LINKS | N15: CUSTO
A16: DESIGNAÇÃO | B16: 110003392209490 | C16: 110005641701194 | E16: CD 820 - Itaquaquecetuba - SP | F16: BNU/IP/01514 | G16: 621980152126996 | H16: TIT000872 | I16: BRE/IP/25280 | J16: SPO/IP/55325 | L16: Vivo | M16: 8 | N16: =SUM(E8+I8+J8+B15+G15+C43+C15+D29) -> 18982.26
A17: OPERADORA 3 | B17: Algar | C17: Algar | E17: Algar | L17: Embratel | M17: 6 | N17: =SUM(C29+J15+I15+F15+C8+B8) -> 17613.75
A18: TIPO | B18: L2L (EC-Tivit) | C18: L2L (Tivit-EC) | E18: L2L (CD-Tivit) | L18: Algar | M18: 7 | N18: =SUM(C36+E22+C22+B22+F8+G8+H8) -> 8966.25
A19: VELOCIDADE | B19: 1 GB | C19: 1 GB | E19: 50Mb | L19: WCS | M19: 1 | N19: =SUM(E15) -> 430
A20: DATA DE ATIVAÇÃO | B20: 44750 | C20: 44750 | E20: 44651 | H20: Cancelamentos | L20: Mega Telecom | M20: 1 | N20: =SUM(H15) -> 997.79
A21: VIGÊNCIA | B21: Cancelado | C21: Cancelado | E21: Cancelado | L21: Mundivox | M21: 1 | N21: =SUM(B29) -> 2750
A22: VALOR | B22: 2470.57 | C22: 2470.57 | E22: 1034.56 | H22: Operadora | I22: Tipo | J22: Data solicitação | L22: Total | M22: =SUM(M16:M20) -> 23 | N22: =SUM(N16:N21) -> 49740.05
A23: DESIGNAÇÃO | B23: 8880105 | C23: 8880104 | E23: 8788650 | H23: Embratel | I23: Dedicado - Tivit | J23: 46037 | K23: sem cob em mar/26
A24: OPERADORA 4 | B24: Mundivox | C24: Embratel | D24: Vivo | H24: Vivo | I24: Dedicado - EC antigo | J24: 46035 | K24: sem cob em mar/26
A25: TIPO | B25: Dedicado | C25: MPLS - (Sitef) | D25: L2L (EC-Equinix) | H25: Vivo | I25: L2L (EC-Equinix) | J25: 46015 | K25: sem cobr em fev/26
A26: VELOCIDADE | B26: 1Gbps | C26: 20MB | D26: 1 Gb | H26: Algar | I26: Lan2lan (CD-Tivit) | J26: 45985 | K26: sem cob em mar/26
A27: DATA DE ATIVAÇÃO | B27: 46010 | C27: 43383 | D27: 45782 | H27: Algar | I27: Lan2lan (EC-Tivit) | J27: 45975 | K27: sem cob em mar/26
A28: VIGÊNCIA | B28: 47106 | C28: Cancelado | D28: 46878 | H28: Vivo | I28: MPLS -P2 EQN-ALA | J28: 45951 | K28: sem cob jan/26
A29: VALOR | B29: 2750 | C29: 4993.06 | D29: 3025.46 | H29: Vivo | I29: MPLS -P2 EQN-MIG | J29: 45951 | K29: sem cob jan/26
A30: DESIGNAÇÃO | B30: 11020625 | C30: SPO/IP/55340 | D30: 110003392058297 | H30: Vivo | I30: MPLS - (sitef) | J30: 45951 | K30: sem cobrança dez/25
A31: OPERADORA 5 | C31: Algar | H31: Embratel | I31: MPLS -P2 EQN-ALA | J31: 45951 | K31: sem cobr em fev/26
A32: TIPO | C32: L2L(Tivit-CD) | H32: Embratel | I32: MPLS -P2 EQN-MIG | J32: 45951 | K32: sem cobr em fev/26
A33: VELOCIDADE | C33: 50Mb | H33: Embratel | I33: MPLS - (sitef) | J33: 45951 | K33: sem cobr em fev/26
A34: DATA DE ATIVAÇÃO | C34: 44651
A35: VIGÊNCIA | C35: Cancelado
A36: VALOR | C36: 1034.56
A37: DESIGNAÇÃO | C37: 8788652
A38: OPERADORA 6 | C38: Vivo
A39: TIPO | C39: MPLS - (Sitef)
A40: VELOCIDADE | C40: 4Mb
A41: DATA DE ATIVAÇÃO | C41: 45070
A42: VIGÊNCIA | C42: Cancelado
A43: VALOR | C43: 4073.44
A44: DESIGNAÇÃO | C44: 110005641094794

Sheet PPOE Lojas
A1: PPOE LOJAS
A2: Loja | B2: Operadora | C2: Ip | D2: Mascara | E2: Gateway | F2: Data da alteração | G2: Velocidade | H2: Obs | I2: User | J2: Passoword
A3: 651 | B3: SPIN18 | C3: 45172162196 | D3: 255255255255 | E3: 10.65.14.1 | F3: 45848 | G3: 10Mb ded | H3: link já estava ativo/ alterou para PPOE o acesso | I3: spin18_marisa | J3: HBQPGEDL
A4: 868 | B4: VERO | C4: 100.64.98.138 | D4: 255255255255 | E4: 186225116129 | F4: 45838 | G4: 300Mb ADSL | H4: link já estava ativo/ alterou para PPOE o acesso | I4: A077474100037@sp.spo | J4: 8qpqmypdipmv
A5: 888 | B5: VERO | C5: 100.64.105.112 | D5: 255255255255 | E5: 186225116129 | F5: 45838 | G5: 300Mb ADSL | H5: link já estava ativo/ alterou para PPOE o acesso | I5: A077474100031@rs.pae | J5: h0m8pphrroel

Sheet Por Loja
A1: Loja | B1: Operadora 1 | C1: Operadora 2 | D1: Qtde
A2: 22 | B2: =VLOOKUP(A2,'Detalhes Links Lojas'!A2:D216,4) -> Claro | C2: =VLOOKUP(A2,'Detalhes Links Lojas'!A2:L216,12) -> Vero | D2: 1
A3: 43 | B3: =VLOOKUP(A3,'Detalhes Links Lojas'!A3:D217,4) -> Mundivox | C3: =VLOOKUP(A3,'Detalhes Links Lojas'!A3:L217,12) -> Vero | D3: 1
A4: 80 | B4: =VLOOKUP(A4,'Detalhes Links Lojas'!A4:D218,4) -> Claro | C4: =VLOOKUP(A4,'Detalhes Links Lojas'!A4:L218,12) -> Vivo | D4: 1
A5: 87 | B5: =VLOOKUP(A5,'Detalhes Links Lojas'!A5:D219,4) -> Claro | C5: =VLOOKUP(A5,'Detalhes Links Lojas'!A5:L219,12) -> Vivo | D5: 1
A6: 120 | B6: =VLOOKUP(A6,'Detalhes Links Lojas'!A6:D220,4) -> Vtal | C6: =VLOOKUP(A6,'Detalhes Links Lojas'!A6:L220,12) -> Fibrion | D6: 1
A7: 125 | B7: =VLOOKUP(A7,'Detalhes Links Lojas'!A7:D221,4) -> Claro | C7: =VLOOKUP(A7,'Detalhes Links Lojas'!A7:L221,12) -> Vivo | D7: 1
A8: 130 | B8: =VLOOKUP(A8,'Detalhes Links Lojas'!A8:D222,4) -> Claro | C8: =VLOOKUP(A8,'Detalhes Links Lojas'!A8:L222,12) -> Vivo | D8: 1
A9: 133 | B9: =VLOOKUP(A9,'Detalhes Links Lojas'!A9:D223,4) -> Claro | C9: =VLOOKUP(A9,'Detalhes Links Lojas'!A9:L223,12) -> SP18 | D9: 1
A10: 135 | B10: =VLOOKUP(A10,'Detalhes Links Lojas'!A10:D223,4) -> Algar | C10: =VLOOKUP(A10,'Detalhes Links Lojas'!A10:L223,12) -> Claro | D10: 1
A11: 136 | B11: =VLOOKUP(A11,'Detalhes Links Lojas'!A11:D223,4) -> Mundivox | C11: =VLOOKUP(A11,'Detalhes Links Lojas'!A11:L223,12) -> Vero | D11: 1
A12: 140 | B12: =VLOOKUP(A12,'Detalhes Links Lojas'!A12:D224,4) -> Vtal | C12: =VLOOKUP(A12,'Detalhes Links Lojas'!A12:L224,12) -> Claro | D12: 1
A13: 142 | B13: =VLOOKUP(A13,'Detalhes Links Lojas'!A13:D225,4) -> Mundivox | C13: =VLOOKUP(A13,'Detalhes Links Lojas'!A13:L225,12) -> Vero | D13: 1
A14: 150 | B14: =VLOOKUP(A14,'Detalhes Links Lojas'!A14:D226,4) -> Claro | C14: =VLOOKUP(A14,'Detalhes Links Lojas'!A14:L226,12) -> Fibrion | D14: 1
A15: 160 | B15: =VLOOKUP(A15,'Detalhes Links Lojas'!A15:D227,4) -> Claro | C15: =VLOOKUP(A15,'Detalhes Links Lojas'!A15:L227,12) -> Vivo | D15: 1
A16: 165 | B16: =VLOOKUP(A16,'Detalhes Links Lojas'!A16:D228,4) -> Mundivox | C16: =VLOOKUP(A16,'Detalhes Links Lojas'!A16:L228,12) -> Vero | D16: 1
A17: 176 | B17: =VLOOKUP(A17,'Detalhes Links Lojas'!A17:D229,4) -> Mundivox | C17: =VLOOKUP(A17,'Detalhes Links Lojas'!A17:L229,12) -> Vero | D17: 1
A18: 178 | B18: =VLOOKUP(A18,'Detalhes Links Lojas'!A18:D230,4) -> Claro | C18: =VLOOKUP(A18,'Detalhes Links Lojas'!A18:L230,12) -> Vivo | D18: 1
A19: 180 | B19: =VLOOKUP(A19,'Detalhes Links Lojas'!A19:D231,4) -> Fibrion | C19: =VLOOKUP(A19,'Detalhes Links Lojas'!A19:L231,12) -> Claro | D19: 1
A20: 196 | B20: =VLOOKUP(A20,'Detalhes Links Lojas'!A20:D232,4) -> Claro | C20: =VLOOKUP(A20,'Detalhes Links Lojas'!A20:L232,12) -> Irapido | D20: 1
A21: 508 | B21: =VLOOKUP(A21,'Detalhes Links Lojas'!A21:D233,4) -> Claro | C21: =VLOOKUP(A21,'Detalhes Links Lojas'!A21:L233,12) -> Vivo | D21: 1
A22: 510 | B22: =VLOOKUP(A22,'Detalhes Links Lojas'!A22:D234,4) -> Claro | C22: =VLOOKUP(A22,'Detalhes Links Lojas'!A22:L234,12) -> Tesa | D22: 1
A23: 514 | B23: =VLOOKUP(A23,'Detalhes Links Lojas'!A23:D237,4) -> Claro | C23: =VLOOKUP(A23,'Detalhes Links Lojas'!A23:L237,12) -> Vivo | D23: 1
A24: 515 | B24: =VLOOKUP(A24,'Detalhes Links Lojas'!A24:D238,4) -> Mundivox | C24: =VLOOKUP(A24,'Detalhes Links Lojas'!A24:L238,12) -> Vero | D24: 1
A25: 517 | B25: =VLOOKUP(A25,'Detalhes Links Lojas'!A25:D239,4) -> Claro | C25: =VLOOKUP(A25,'Detalhes Links Lojas'!A25:L239,12) -> Vtal | D25: 1
A26: 518 | B26: =VLOOKUP(A26,'Detalhes Links Lojas'!A26:D240,4) -> Claro | C26: =VLOOKUP(A26,'Detalhes Links Lojas'!A26:L240,12) -> Vero | D26: 1
A27: 519 | B27: =VLOOKUP(A27,'Detalhes Links Lojas'!A27:D241,4) -> Vtal | C27: =VLOOKUP(A27,'Detalhes Links Lojas'!A27:L241,12) -> Claro | D27: 1
A28: 520 | B28: =VLOOKUP(A28,'Detalhes Links Lojas'!A28:D242,4) -> Claro | C28: =VLOOKUP(A28,'Detalhes Links Lojas'!A28:L242,12) -> Vero | D28: 1
A29: 525 | B29: =VLOOKUP(A29,'Detalhes Links Lojas'!A29:D243,4) -> Claro | C29: =VLOOKUP(A29,'Detalhes Links Lojas'!A29:L243,12) -> Vivo | D29: 1
A30: 526 | B30: =VLOOKUP(A30,'Detalhes Links Lojas'!A30:D244,4) -> Algar | C30: =VLOOKUP(A30,'Detalhes Links Lojas'!A30:L244,12) -> Vero | D30: 1
A31: 527 | B31: =VLOOKUP(A31,'Detalhes Links Lojas'!A31:D245,4) -> Claro | C31: =VLOOKUP(A31,'Detalhes Links Lojas'!A31:L245,12) -> Irapido | D31: 1
A32: 529 | B32: =VLOOKUP(A32,'Detalhes Links Lojas'!A32:D246,4) -> Claro | C32: =VLOOKUP(A32,'Detalhes Links Lojas'!A32:L246,12) -> Vero | D32: 1
A33: 531 | B33: =VLOOKUP(A33,'Detalhes Links Lojas'!A33:D247,4) -> Mundivox | C33: =VLOOKUP(A33,'Detalhes Links Lojas'!A33:L247,12) -> Vivo | D33: 1
A34: 534 | B34: =VLOOKUP(A34,'Detalhes Links Lojas'!A34:D248,4) -> Fibrion | C34: =VLOOKUP(A34,'Detalhes Links Lojas'!A34:L248,12) -> Claro | D34: 1
... A36: 536 | B36: =VLOOKUP(A36,'Detalhes Links Lojas'!A36:D250,4) -> Algar | C36: =VLOOKUP(A36,'Detalhes Links Lojas'!A36:L250,12) -> Claro | D36: 1
A37: 544 | B37: =VLOOKUP(A37,'Detalhes Links Lojas'!A37:D252,4) -> Mundivox | C37: =VLOOKUP(A37,'Detalhes Links Lojas'!A37:L252,12) -> Vero | D37: 1
A38: 546 | B38: =VLOOKUP(A38,'Detalhes Links Lojas'!A38:D253,4) -> Claro | C38: =VLOOKUP(A38,'Detalhes Links Lojas'!A38:L253,12) -> Vero | D38: 1
A39: 547 | B39: =VLOOKUP(A39,'Detalhes Links Lojas'!A39:D254,4) -> Fibrion | C39: =VLOOKUP(A39,'Detalhes Links Lojas'!A39:L254,12) -> Vero | D39: 1
A40: 548 | B40: =VLOOKUP(A40,'Detalhes Links Lojas'!A40:D255,4) -> Claro | C40: =VLOOKUP(A40,'Detalhes Links Lojas'!A40:L255,12) -> Vivo | D40: 1
A41: 549 | B41: =VLOOKUP(A41,'Detalhes Links Lojas'!A41:D256,4) -> Claro | C41: =VLOOKUP(A41,'Detalhes Links Lojas'!A41:L256,12) -> Vero | D41: 1
A42: 550 | B42: =VLOOKUP(A42,'Detalhes Links Lojas'!A42:D257,4) -> Mundivox | C42: =VLOOKUP(A42,'Detalhes Links Lojas'!A42:L257,12) -> Claro | D42: 1
A43: 553 | B43: =VLOOKUP(A43,'Detalhes Links Lojas'!A43:D258,4) -> Algar | C43: =VLOOKUP(A43,'Detalhes Links Lojas'!A43:L258,12) -> Claro | D43: 1
A44: 558 | B44: =VLOOKUP(A44,'Detalhes Links Lojas'!A44:D259,4) -> Claro | C44: =VLOOKUP(A44,'Detalhes Links Lojas'!A44:L259,12) -> Vivo | D44: 1
A45: 559 | B45: =VLOOKUP(A45,'Detalhes Links Lojas'!A45:D260,4) -> Claro | C45: =VLOOKUP(A45,'Detalhes Links Lojas'!A45:L260,12) -> Vero | D45: 1
A46: 560 | B46: =VLOOKUP(A46,'Detalhes Links Lojas'!A46:D261,4) -> Claro | C46: =VLOOKUP(A46,'Detalhes Links Lojas'!A46:L261,12) -> Vtal | D46: 1
A47: 563 | B47: =VLOOKUP(A47,'Detalhes Links Lojas'!A47:D262,4) -> Algar | C47: =VLOOKUP(A47,'Detalhes Links Lojas'!A47:L262,12) -> Vero | D47: 1
A48: 564 | B48: =VLOOKUP(A48,'Detalhes Links Lojas'!A48:D263,4) -> Claro | C48: =VLOOKUP(A48,'Detalhes Links Lojas'!A48:L263,12) -> Vero | D48: 1
... A50: 566 | B50: =VLOOKUP(A50,'Detalhes Links Lojas'!A50:D265,4) -> Claro | C50: =VLOOKUP(A50,'Detalhes Links Lojas'!A50:L265,12) -> Vivo | D50: 1
A51: 571 | B51: =VLOOKUP(A51,'Detalhes Links Lojas'!A51:D267,4) -> Claro | C51: =VLOOKUP(A51,'Detalhes Links Lojas'!A51:L267,12) -> Fibrion | D51: 1
A52: 573 | B52: =VLOOKUP(A52,'Detalhes Links Lojas'!A52:D268,4) -> Claro | C52: =VLOOKUP(A52,'Detalhes Links Lojas'!A52:L268,12) -> Vivo | D52: 1
A53: 575 | B53: =VLOOKUP(A53,'Detalhes Links Lojas'!A53:D269,4) -> Fibrion | C53: =VLOOKUP(A53,'Detalhes Links Lojas'!A53:L269,12) -> Vtal | D53: 1
A54: 576 | B54: =VLOOKUP(A54,'Detalhes Links Lojas'!A54:D270,4) -> Mundivox | C54: =VLOOKUP(A54,'Detalhes Links Lojas'!A54:L270,12) -> Vero | D54: 1
A55: 577 | B55: =VLOOKUP(A55,'Detalhes Links Lojas'!A55:D271,4) -> Claro | C55: =VLOOKUP(A55,'Detalhes Links Lojas'!A55:L271,12) -> Vero | D55: 1
A56: 578 | B56: =VLOOKUP(A56,'Detalhes Links Lojas'!A56:D272,4) -> Claro | C56: =VLOOKUP(A56,'Detalhes Links Lojas'!A56:L272,12) -> Vivo | D56: 1
A57: 579 | B57: =VLOOKUP(A57,'Detalhes Links Lojas'!A57:D273,4) -> Algar | C57: =VLOOKUP(A57,'Detalhes Links Lojas'!A57:L273,12) -> Vero | D57: 1
A58: 580 | B58: =VLOOKUP(A58,'Detalhes Links Lojas'!A58:D274,4) -> Claro | C58: =VLOOKUP(A58,'Detalhes Links Lojas'!A58:L274,12) -> Vivo | D58: 1
A59: 582 | B59: =VLOOKUP(A59,'Detalhes Links Lojas'!A59:D275,4) -> Claro | C59: =VLOOKUP(A59,'Detalhes Links Lojas'!A59:L275,12) -> Vivo | D59: 1
A60: 583 | B60: =VLOOKUP(A60,'Detalhes Links Lojas'!A60:D276,4) -> Algar | C60: =VLOOKUP(A60,'Detalhes Links Lojas'!A60:L276,12) -> Claro | D60: 1
A61: 586 | B61: =VLOOKUP(A61,'Detalhes Links Lojas'!A61:D277,4) -> Mundivox | C61: =VLOOKUP(A61,'Detalhes Links Lojas'!A61:L277,12) -> Vero | D61: 1
A62: 589 | B62: =VLOOKUP(A62,'Detalhes Links Lojas'!A62:D278,4) -> Algar | C62: =VLOOKUP(A62,'Detalhes Links Lojas'!A62:L278,12) -> Vivo | D62: 1
... A64: 594 | B64: =VLOOKUP(A64,'Detalhes Links Lojas'!A64:D280,4) -> Vtal | C64: =VLOOKUP(A64,'Detalhes Links Lojas'!A64:L280,12) -> Claro | D64: 1
A65: 598 | B65: =VLOOKUP(A65,'Detalhes Links Lojas'!A65:D282,4) -> Claro | C65: =VLOOKUP(A65,'Detalhes Links Lojas'!A65:L282,12) -> Vivo | D65: 1
A66: 599 | B66: =VLOOKUP(A66,'Detalhes Links Lojas'!A66:D283,4) -> Claro | C66: =VLOOKUP(A66,'Detalhes Links Lojas'!A66:L283,12) -> Vivo | D66: 1
A67: 600 | B67: =VLOOKUP(A67,'Detalhes Links Lojas'!A67:D284,4) -> Claro | C67: =VLOOKUP(A67,'Detalhes Links Lojas'!A67:L284,12) -> Mundivox | D67: 1
A68: 601 | B68: =VLOOKUP(A68,'Detalhes Links Lojas'!A68:D285,4) -> Mundivox | C68: =VLOOKUP(A68,'Detalhes Links Lojas'!A68:L285,12) -> Claro | D68: 1
A69: 605 | B69: =VLOOKUP(A69,'Detalhes Links Lojas'!A69:D287,4) -> Claro | C69: =VLOOKUP(A69,'Detalhes Links Lojas'!A69:L287,12) -> Vivo | D69: 1
A70: 606 | B70: =VLOOKUP(A70,'Detalhes Links Lojas'!A70:D288,4) -> Claro | C70: =VLOOKUP(A70,'Detalhes Links Lojas'!A70:L288,12) -> Vero | D70: 1
A71: 607 | B71: =VLOOKUP(A71,'Detalhes Links Lojas'!A71:D289,4) -> Claro | C71: =VLOOKUP(A71,'Detalhes Links Lojas'!A71:L289,12) -> Vero | D71: 1
A72: 608 | B72: =VLOOKUP(A72,'Detalhes Links Lojas'!A72:D290,4) -> Claro | C72: =VLOOKUP(A72,'Detalhes Links Lojas'!A72:L290,12) -> Vivo | D72: 1
A73: 610 | B73: =VLOOKUP(A73,'Detalhes Links Lojas'!A73:D291,4) -> Claro | C73: =VLOOKUP(A73,'Detalhes Links Lojas'!A73:L291,12) -> Vivo | D73: 1
A74: 613 | B74: =VLOOKUP(A74,'Detalhes Links Lojas'!A74:D292,4) -> Claro | C74: =VLOOKUP(A74,'Detalhes Links Lojas'!A74:L292,12) -> Vero | D74: 1
A75: 617 | B75: =VLOOKUP(A75,'Detalhes Links Lojas'!A75:D293,4) -> Algar | C75: =VLOOKUP(A75,'Detalhes Links Lojas'!A75:L293,12) -> Claro | D75: 1
A76: 618 | B76: =VLOOKUP(A76,'Detalhes Links Lojas'!A76:D294,4) -> Claro | C76: =VLOOKUP(A76,'Detalhes Links Lojas'!A76:L294,12) -> Vtal | D76: 1
A77: 619 | B77: =VLOOKUP(A77,'Detalhes Links Lojas'!A77:D295,4) -> Claro | C77: =VLOOKUP(A77,'Detalhes Links Lojas'!A77:L295,12) -> Vero | D77: 1
A78: 622 | B78: =VLOOKUP(A78,'Detalhes Links Lojas'!A78:D296,4) -> Wipi | C78: =VLOOKUP(A78,'Detalhes Links Lojas'!A78:L296,12) -> Vero | D78: 1
A79: 623 | B79: =VLOOKUP(A79,'Detalhes Links Lojas'!A79:D297,4) -> Claro | C79: =VLOOKUP(A79,'Detalhes Links Lojas'!A79:L297,12) -> WFT/AST | D79: 1
A80: 624 | B80: =VLOOKUP(A80,'Detalhes Links Lojas'!A80:D298,4) -> Claro | C80: =VLOOKUP(A80,'Detalhes Links Lojas'!A80:L298,12) -> Vero | D80: 1
... A104: 654 | B104: =VLOOKUP(A104,'Detalhes Links Lojas'!A104:D322,4) -> #N/A | C104: =VLOOKUP(A104,'Detalhes Links Lojas'!A104:L322,12) -> #N/A | D104: 1
A105: 656 | B105: =VLOOKUP(A105,'Detalhes Links Lojas'!A104:D323,4) -> Claro | C105: =VLOOKUP(A105,'Detalhes Links Lojas'!A104:L323,12) -> Vero | D105: 1
A106: 659 | B106: =VLOOKUP(A106,'Detalhes Links Lojas'!A105:D325,4) -> Claro | C106: =VLOOKUP(A106,'Detalhes Links Lojas'!A105:L325,12) -> Vivo | D106: 1
A107: 660 | B107: =VLOOKUP(A107,'Detalhes Links Lojas'!A106:D326,4) -> Claro | C107: =VLOOKUP(A107,'Detalhes Links Lojas'!A106:L326,12) -> Vtal | D107: 1
A108: 661 | B108: =VLOOKUP(A108,'Detalhes Links Lojas'!A107:D327,4) -> Claro | C108: =VLOOKUP(A108,'Detalhes Links Lojas'!A107:L327,12) -> Vivo | D108: 1
A109: 662 | B109: =VLOOKUP(A109,'Detalhes Links Lojas'!A108:D328,4) -> Mundivox | C109: =VLOOKUP(A109,'Detalhes Links Lojas'!A108:L328,12) -> Vero | D109: 1
A110: 663 | B110: =VLOOKUP(A110,'Detalhes Links Lojas'!A109:D329,4) -> Claro | C110: =VLOOKUP(A110,'Detalhes Links Lojas'!A109:L329,12) -> Vivo | D110: 1
A111: 664 | B111: =VLOOKUP(A111,'Detalhes Links Lojas'!A110:D330,4) -> Claro | C111: =VLOOKUP(A111,'Detalhes Links Lojas'!A110:L330,12) -> Vivo | D111: 1
A112: 665 | B112: =VLOOKUP(A112,'Detalhes Links Lojas'!A111:D331,4) -> Claro | C112: =VLOOKUP(A112,'Detalhes Links Lojas'!A111:L331,12) -> Vero | D112: 1
A113: 667 | B113: =VLOOKUP(A113,'Detalhes Links Lojas'!A112:D332,4) -> Algar | C113: =VLOOKUP(A113,'Detalhes Links Lojas'!A112:L332,12) -> Vivo | D113: 1
A114: 671 | B114: =VLOOKUP(A114,'Detalhes Links Lojas'!A113:D333,4) -> Vivo | C114: =VLOOKUP(A114,'Detalhes Links Lojas'!A113:L333,12) -> Claro | D114: 1
A115: 672 | B115: =VLOOKUP(A115,'Detalhes Links Lojas'!A114:D334,4) -> Claro | C115: =VLOOKUP(A115,'Detalhes Links Lojas'!A114:L334,12) -> Vero | D115: 1
A116: 674 | B116: =VLOOKUP(A116,'Detalhes Links Lojas'!A115:D335,4) -> Claro | C116: =VLOOKUP(A116,'Detalhes Links Lojas'!A115:L335,12) -> Vero | D116: 1
A117: 676 | B117: =VLOOKUP(A117,'Detalhes Links Lojas'!A116:D337,4) -> Claro | C117: =VLOOKUP(A117,'Detalhes Links Lojas'!A116:L337,12) -> Vivo | D117: 1
A118: 677 | B118: =VLOOKUP(A118,'Detalhes Links Lojas'!A117:D338,4) -> Claro | C118: =VLOOKUP(A118,'Detalhes Links Lojas'!A117:L338,12) -> Vtal | D118: 1
A119: 678 | B119: =VLOOKUP(A119,'Detalhes Links Lojas'!A118:D339,4) -> Claro | C119: =VLOOKUP(A119,'Detalhes Links Lojas'!A118:L339,12) -> Vero | D119: 1
A120: 679 | B120: =VLOOKUP(A120,'Detalhes Links Lojas'!A119:D340,4) -> Fibrion | C120: =VLOOKUP(A120,'Detalhes Links Lojas'!A119:L340,12) -> Vivo | D120: 1
A121: 680 | B121: =VLOOKUP(A121,'Detalhes Links Lojas'!A120:D341,4) -> Claro | C121: =VLOOKUP(A121,'Detalhes Links Lojas'!A120:L341,12) -> Vtal | D121: 1
A122: 681 | B122: =VLOOKUP(A122,'Detalhes Links Lojas'!A121:D342,4) -> Claro | C122: =VLOOKUP(A122,'Detalhes Links Lojas'!A121:L342,12) -> Vivo | D122: 1
A123: 682 | B123: =VLOOKUP(A123,'Detalhes Links Lojas'!A122:D343,4) -> Claro | C123: =VLOOKUP(A123,'Detalhes Links Lojas'!A122:L343,12) -> Vivo | D123: 1
A124: 684 | B124: =VLOOKUP(A124,'Detalhes Links Lojas'!A123:D344,4) -> Claro | C124: =VLOOKUP(A124,'Detalhes Links Lojas'!A123:L344,12) -> Vivo | D124: 1
A125: 685 | B125: =VLOOKUP(A125,'Detalhes Links Lojas'!A124:D345,4) -> Claro | C125: =VLOOKUP(A125,'Detalhes Links Lojas'!A124:L345,12) -> Vivo | D125: 1
A126: 686 | B126: =VLOOKUP(A126,'Detalhes Links Lojas'!A125:D346,4) -> Mundivox | C126: =VLOOKUP(A126,'Detalhes Links Lojas'!A125:L346,12) -> Vero | D126: 1
...

Sheet Ips Link Novos
A1: Ip Links Contratados
A2: Loja | B2: Operadora | C2: Ip | D2: Mascara | E2: Gateway | F2: Data Ativação | G2: Velocidade | H2: Obs
A3: 682 | B3: Claro | C3: 200.246.15.46 | D3: 255255255252 | E3: 200.246.15.45 | F3: 45838 | G3: 20Mb dedicado
A4: 601 | B4: Claro | C4: DHCP | D4: --- | E4: 192.168.0.1 | F4: 45895 | G4: 600Mb ADSL
A5: 600 | B5: Mundivox | C5: 187.103.33.18 | D5: 255255255252 | E5: 187.103.33.17 | F5: 45896 | G5: 100Mb semidedicado | H5: Faixa de IPs: 187.103.33.18 a 187.103.33.18 | I5: Gateway: 187.103.33.17 | J5: Máscara de Sub-rede: 255.255.255.252 | K5: DNS Primário: 200.196.48.20 | L5: DNS Secundário: 179.191.120.5
A6: 140 | B6: Claro | C6: 200.179.90.106 | D6: 255255255252 | E6: 200.179.90.105 | F6: 45896 | G6: 20Mb dedicado
A7: 662 | B7: Mundivox | C7: DHCP | D7: --- | E7: --- | F7: 45896 | G7: 100Mb semidedicado
A8: 565 | B8: Mundivox | C8: DHCP | D8: --- | E8: --- | F8: 45898 | G8: 100Mb semidedicado
A9: 885 | B9: Mundivox | C9: DHCP | D9: --- | E9: --- | F9: 45898 | G9: 100Mb semidedicado | H9: Faixa de IPs: 177.92.98.246 a 177.92.98.246 | I9: Gateway: 177.92.98.245 | J9: Máscara de Sub-rede: 255.255.255.252 | K9: DNS Primário: 200.196.48.20 | L9: DNS Secundário: 179.191.120.5
A10: 8 5 8 | B10: Mundivox | C10: DHCP | D10: --- | E10: --- | F10: 45901 | G10: 100Mb semidedicado
A11: 601 | B11: Mundivox | C11: DHCP | D11: --- | E11: --- | F11: 45902 | G11: 100Mb semidedicado
A12: 744 | B12: Vivo | C12: DHCP | D12: --- | E12: --- | F12: 45902 | G12: 600Mb ADSL
A13: 43 | B13: Mundivox | C13: DHCP | D13: --- | E13: --- | F13: 45904 | G13: 100Mb semidedicado
A14: 550 | B14: Mundivox | C14: DHCP | D14: --- | E14: --- | F14: 45904 | G14: 100Mb semidedicado
A15: 889 | B15: Mundivox | C15: DHCP | D15: --- | E15: --- | F15: 45904 | G15: 100Mb semidedicado
A16: 586 | B16: Mundivox | C16: DHCP | D16: --- | E16: --- | F16: 45910 | G16: 100Mb semidedicado
A17: 640 | B17: Mundivox | C17: DHCP | D17: --- | E17: --- | F17: 45915 | G17: 100Mb semidedicado
A18: 675 | B18: Algar | C18: 187.32.33.21 | D18: 255255255252 | E18: 187.32.33.22 | F18: 45916 | G18: 20Mb dedicado
A19: 125 | B19: Vivo | C19: DHCP | D19: --- | E19: --- | F19: 45917 | G19: 600Mb ADSL
A20: 877 | B20: Vivo | C20: DHCP | D20: --- | E20: --- | F20: 45919 | G20: 600Mb ADSL
A21: 568 | B21: Algar | C21: 189.38.108.41 | D21: 255255255252 | E21: 189.38.108.42 | F21: 45919 | G21: 20Mb dedicado
A22: 589 | B22: Vivo | C22: DHCP | D22: --- | E22: --- | F22: 45922 | G22: 600Mb ADSL
A23: 770 | B23: Vivo | C23: DHCP | D23: --- | E23: --- | F23: 45922 | G23: 600Mb ADSL
A24: 719 | B24: Vivo | C24: DHCP | D24: --- | E24: --- | F24: 45922 | G24: 600Mb ADSL
A25: 774 | B25: Mundivox | C25: DHCP | D25: --- | E25: --- | F25: 45925 | G25: 100Mb semidedicado
A26: 563 | B26: Algar | C26: 189.112.203.69 | D26: 255255255252 | E26: 189.112.203.70 | F26: 45925 | G26: 20Mb dedicado
A27: 751 | B27: Vivo | C27: DHCP | D27: --- | E27: --- | F27: 45926 | G27: 600Mb ADSL
A28: 929 | B28: Mundivox | C28: DHCP | D28: --- | E28: --- | F28: 45926 | G28: 100Mb semidedicado
A29: 921 | B29: Algar | C29: 187.72.10.73 | D29: 255255255252 | E29: 187.72.10.74 | F29: 45936 | G29: 20Mb dedicado
A30: 867 | B30: Algar | C30: 200233218229 | D30: 255255255252 | E30: 200233218230 | F30: 45937 | G30: 20Mb dedicado
A31: 590 | B31: Mundivox | C31: DHCP | D31: --- | E31: --- | F31: 45938 | G31: 100Mb semidedicado
A32: 848 | B32: Claro | C32: DHCP | D32: --- | E32: --- | F32: 45939 | G32: 300Mb ADSL
A33: 893 | B33: Claro | C33: DHCP | D33: --- | E33: --- | F33: 45939 | G33: 300Mb ADSL
A34: 709 | B34: Claro | C34: 189.2.77.222 | D34: 255255255252 | E34: 189.2.77.221 | F34: 45943 | G34: 20Mb dedicado
A35: 645 | B35: Claro | C35: 200212229250 | D35: 255255255252 | E35: 200212229249 | F35: 45944 | G35: 20Mb dedicado
A36: 576 | B36: Mundivox | C36: DHCP | D36: --- | E36: --- | F36: 45944 | G36: 100Mb semidedicado
A37: 580 | B37: Vivo | C37: DHCP | D37: --- | E37: --- | F37: 45944 | G37: 600Mb ADSL
A38: 943 | B38: Claro | C38: 200213117214 | D38: 255255255252 | E38: 200213117213 | F38: 45945 | G38: 20Mb dedicado
A39: 565 | B39: Claro | C39: DHCP | D39: --- | E39: --- | F39: 45945 | G39: 300Mb ADSL
A40: 598 | B40: Vivo | C40: DHCP | D40: --- | E40: --- | F40: 45946 | G40: 600Mb ADSL
A41: 617 | B41: Claro | C41: DHCP | D41: --- | E41: --- | F41: 45946 | G41: 300Mb ADSL
A42: 687 | B42: Claro | C42: DHCP | D42: --- | E42: --- | F42: 45946 | G42: 300Mb ADSL
A43: 725 | B43: Claro | C43: DHCP | D43: --- | E43: --- | F43: 45947 | G43: 300Mb ADSL
A44: 529 | B44: Claro | C44: 200.248.176.14 | D44: 255255255252 | E44: 200.148.176.13 | F44: 45950 | G44: 20Mb dedicado
A45: 715 | B45: Claro | C45: DHCP | D45: --- | E45: --- | F45: 45950 | G45: 300Mb ADSL
A46: 939 | B46: Mundivox | C46: DHCP | D46: --- | E46: --- | F46: 45950 | G46: 100Mb semidedicado
A47: 924 | B47: Mundivox | C47: DHCP | D47: --- | E47: --- | F47: 45951 | G47: 100Mb semidedicado
A48: 845 | B48: Claro | C48: 200.208.245.70 | D48: 255255255252 | E48: 200.208.245.69 | F48: 45952 | G48: 20Mb dedicado
A49: 643 | B49: Algar | C49: 187.32.218.249 | D49: 255255255252 | E49: 187.32.218.250 | F49: 45952 | G49: 20Mb dedicado
A50: 579 | B50: Algar | C50: 187.32.37.161 | D50: 255255255252 | E50: 187.32.37.162 | F50: 45952 | G50: 20Mb dedicado
A51: 536 | B51: Algar | C51: 200170188221 | D51: 255255255252 | E51: 200170188222 | F51: 45953 | G51: 20Mb dedicado
A52: 908 | B52: Claro | C52: 201.90.81.2 | D52: 255255255240 | E52: 201.90.81.1 | F52: 45954 | G52: 20Mb dedicado
A53: 649 | B53: Claro | C53: 200213247210 | D53: 255255255252 | E53: 200213247209 | F53: 45954 | G53: 20Mb dedicado
A54: 652 | B54: Vivo | C54: DHCP | D54: --- | E54: --- | F54: 45954 | G54: 600Mb ADSL
A55: 531 | B55: Mundivox | C55: DHCP | D55: --- | E55: --- | F55: 45954 | G55: 100Mb semidedicado
A56: 712 | B56: Claro | C56: 200228178182 | D56: 255255255252 | E56: 200228178181 | F56: 45957 | G56: 20Mb dedicado
A57: 667 | B57: Vivo | C57: DHCP | D57: --- | E57: --- | F57: 45957 | G57: 600Mb ADSL
A58: 642 | B58: Vivo | C58: DHCP | D58: --- | E58: --- | F58: 45957 | G58: 600Mb ADSL
A59: 135 | B59: Claro | C59: DHCP | D59: --- | E59: --- | F59: 45958 | G59: 300Mb ADSL
A60: 553 | B60: Claro | C60: DHCP | D60: --- | E60: --- | F60: 45959 | G60: 300Mb ADSL
A61: 888 | B61: Algar | C61: 200233134145 | D61: 255255255252 | E61: 200233134146 | F61: 45959 | G61: 20Mb dedicado
A62: 765 | B62: Claro | C62: 200.213.233.74 | D62: 255255255252 | E62: 200.213.233.73 | F62: 45959 | G62: 20Mb dedicado
A63: 885 | B63: Claro | C63: DHCP | D63: --- | E63: --- | F63: 45959 | G63: 300Mb ADSL
A64: 671 | B64: Claro | C64: DHCP | D64: --- | E64: --- | F64: 45960 | G64: 300Mb ADSL
A65: 726 | B65: Claro | C65: 189.86.32.98 | D65: 255255255252 | E65: 189.86.32.97 | F65: 45961 | G65: 20Mb dedicado
A66: 641 | B66: Claro | C66: 200.208.49.66 | D66: 255255255252 | E66: 200.208.49.65 | F66: 45961 | G66: 20Mb dedicado
A67: 582 | B67: Claro | C67: 189.2.205.98 | D67: 255255255240 | E67: 189.2.205.97 | F67: 45964 | G67: 20Mb dedicado
A68: 650 | B68: Claro | C68: 187.28.127.246 | D68: 255255255252 | E68: 187.28.127.245 | F68: 45964 | G68: 20Mb dedicado
A69: 688 | B69: Claro | C69: 20156221242 | D69: 255255255252 | E69: 20156221241 | F69: 45965 | G69: 20Mb dedicado
A70: 607 | B70: Claro | C70: 200178209194 | D70: 255255255240 | E70: 200178209193 | F70: 45965 | G70: 20Mb dedicado
A71: 913 | B71: Claro | C71: 200243233114 | D71: 255255255240 | E71: 200243233113 | F71: 45965 | G71: 20Mb dedicado
A72: 660 | B72: Claro | C72: 201.45.58.210 | D72: 255255255240 | E72: 201.45.58.209 | F72: 45965 | G72: 20Mb dedicado
A73: 951 | B73: Claro | C73: 189.3.25.194 | D73: 255255255240 | E73: 189.3.25.193 | F73: 45965 | G73: 20Mb dedicado
A74: 176 | B74: Mundivox | C74: DHCP | D74: --- | E74: --- | F74: 45965 | G74: 100Mb semidedicado
A75: 852 | B75: Claro | C75: 20018249114 | D75: 255255255240 | E75: 200.18.249.113 | F75: 45966 | G75: 20Mb dedicado
A76: 664 | B76: Claro | C76: 189.22.21.18 | D76: 255255255240 | E76: 189.22.21.17 | F76: 45966 | G76: 20Mb dedicado
A77: 909 | B77: Claro | C77: 201.65.242.50 | D77: 255255255240 | E77: 201.65.242.49 | F77: 45966 | G77: 20Mb dedicado
A78: 639 | B78: Claro | C78: 200.178.26.82 | D78: 255255255240 | E78: 200.178.26.81 | F78: 45966 | G78: 20Mb dedicado
A79: 564 | B79: Claro | C79: 2015623114 | D79: 255255255240 | E79: 201.56.23.113 | F79: 45966 | G79: 20Mb dedicado
A80: 851 | B80: Claro | C80: 201.56.21.194 | D80: 255255255240 | E80: 201.56.21.193 | F80: 45966 | G80: 20Mb dedicado
A81: 783 | B81: Claro | C81: 189326242 | D81: 255255255240 | E81: 189.3.26.241 | F81: 45967 | G81: 20Mb dedicado
A82: 22 | B82: Claro | C82: 200.182.133.66 | D82: 255255255240 | E82: 200.182.133.65 | F82: 45967 | G82: 20Mb dedicado
A83: 531 | B83: Vivo | C83: DHCP | D83: --- | E83: --- | F83: 45967 | G83: 600Mb ADSL
A84: 525 | B84: Claro | C84: 189399146 | D84: 255255255240 | E84: 189.3.99.145 | F84: 45967 | G84: 20Mb dedicado
A85: 774 | B85: Claro | C85: 189.3.231.50 | D85: 255255255240 | E85: 189.3.231.49 | F85: 45968 | G85: 20Mb dedicado
A86: 526 | B86: Algar | C86: 177.69.90.241 | D86: 255255255252 | E86: 177.69.90.242 | F86: 45968 | G86: 20Mb dedicado
A87: 647 | B87: Claro | C87: 201.56.5.210 | D87: 255255255240 | E87: 201.56.5.210 | F87: 45971 | G87: 20Mb dedicado
A88: 605 | B88: Claro | C88: 189.22.47.114 | D88: 255255255240 | E88: 189.22.47.113 | F88: 45971 | G88: 20Mb dedicado
A89: 618 | B89: Claro | C89: 20173231162 | D89: 255255255240 | E89: 201.73.231.161 | F89: 45971 | G89: 20Mb dedicado
A90: 929 | B90: Vivo | C90: 177.43.125.122 | D90: 255255255248 | E90: 177.43.125.121 | F90: 45971 | G90: 30Mb dedicado
A91: 659 | B91: Claro | C91: 200174178130 | D91: 255255255240 | E91: 200174178129 | F91: 45972 | G91: 20Mb dedicado
A92: 780 | B92: Claro | C92: 201.56.23.98 | D92: 255255255240 | E92: 201.56.23.97 | F92: 45975 | G92: 20Mb dedicado
A93: 745 | B93: Claro | C93: 201.39.162.226 | D93: 255255255248 | E93: 201.39.162.225 | F93: 45975 | G93: 20Mb dedicado
A94: 717 | B94: Claro | C94: 200.183.76.198 | D94: 255255255252 | E94: 200.183.76.197 | F94: 45975 | G94: 20Mb dedicado
A95: 142 | B95: Mundivox | C95: DHCP | D95: --- | E95: --- | F95: 45975 | G95: 100Mb semidedicado
A96: 678 | B96: Claro | C96: 200.214.135.34 | D96: 255255255240 | E96: 200.214.135.33 | F96: 45978 | G96: 20Mb dedicado
A97: 606 | B97: Claro | C97: 189.16.242.130 | D97: 255255255240 | E97: 189.16.242.129 | F97: 45978 | G97: 20Mb dedicado
A98: 578 | B98: Claro | C98: 189.2.122.178 | D98: 255255255240 | E98: 189.2.122.177 | F98: 45979 | G98: 20Mb dedicado
A99: 629 | B99: Claro | C99: 200.208.89.178 | D99: 255255255240 | E99: 200.208.89.177 | F99: 45980 | G99: 20Mb dedicado
A100: 857 | B100: Claro | C100: 200208115242 | D100: 255255255240 | E100: 200208115241 | F100: 45980 | G100: 20Mb dedicado
...

Sheet Detalhes EC-EQX-CDs
A1: Local | B1: Estado | C1: Cidade | D1: Operadora 1 | E1: Data Ativação | F1: Vigencia | G1: Designação | H1: Banda | I1: Tipo | J1: Custo/mês | K1: Operadora 2 | L1: Data Ativação | M1: Vigencia | N1: Designação | O1: Banda | P1: Tipo | Q1: Custo/mês | R1: Infra Extra | S1: Valor | T1: IP Loopback | U1: IP Firewall | V1: Custo Total | W1: S/N Fortigate | X1: Última Atualização | Y1: Obs | Z1: Operadora 3 | AA1: Data Ativação | AB1: Vigencia | AC1: Designação | AD1: Banda | AE1: Tipo | AF1: Custo/mês
A2: CD-807 | B2: GO | C2: Goiânia | D2: Algar | E2: 44617 | F2: Vencido | G2: 8754445/8754447 | H2: 10Mb | I2: Dedicado | J2: 470.62 | K2: Vivo | L2: 46176 | M2: 47272 | N2: 621980221280394 | O2: 20Mb | P2: Dedicado | Q2: 380 | U2: 10.8.108.1 | V2: =SUM(J2+Q2) -> 850.62 | X2: 46161
A3: CD-811 | B3: SC | C3: Blumenau | D3: Algar | E3: 44596 | F3: Vencido | G3: 8756818/8756819 | H3: 20Mb | I3: Dedicado | J3: 1024.5 | K3: Claro | L3: 46218 | M3: 47314 | N3: BNU/IP/01514 | O3: 50Mb | P3: Dedicado | Q3: 962 | V3: =SUM(J3+Q3) -> 1986.5 | X3: 46161
A4: CD-818 | B4: SC | C4: Navegantes | D4: Algar | E4: 44589 | F4: Vencido | G4: 8754444/8754446 | H4: 20Mb | I4: Dedicado | J4: 590.69 | K4: MegaTelecom | L4: 44735 | M4: Vencido | N4: TIT000872 | O4: 20Mb | P4: Dedicado | Q4: 997.79 | V4: =SUM(J4+Q4) -> 1588.48 | X4: 46161
A5: CD-820 | B5: SP | C5: Itaquaquecetuba | D5: Vivo | E5: 45338 | F5: 46434 | G5: 113004643101796 | H5: 200Mb | I5: Dedicado | J5: 1910.03 | K5: Fibrion | L5: 45609 | M5: 46704 | N5: ZZ45726039001 | O5: 100Mb | P5: Dedicado | Q5: 430 | U5: 10.8.120.1 | V5: =SUM(J5+Q5) -> 2340.03 | X5: 46161
A6: EC | B6: SP | C6: São Paulo | D6: Mundivox | E6: 46010 | F6: 47106 | G6: 11020625 | H6: 1Gbps | I6: Dedicado | J6: 2750 | K6: Vivo | L6: 46024 | M6: 47120 | N6: 110003825281299 | O6: 1Gbps | P6: Dedicado | Q6: 3400 | V6: =SUM(J6+Q6+AF6) -> 9064.3 | X6: 46161 | Z6: Claro | AA6: 46112 | AB6: 47208 | AC6: SPO/IP/40295 | AD6: 1Gbps | AE6: Dedicado | AF6: 2914.3
A7: EQX | B7: SP | C7: São Paulo | D7: Vivo | E7: 45568 | F7: 46663 | G7: 110005641701194 | H7: 1Gbps | I7: Dedicado | J7: 4110.16 | X7: 46161
B9: EC | C9: CD-807 | D9: CD-811 | E9: CD-818 | F9: CD-820
A10: Equipamento | B10: São Paulo - SP | C10: Goiânia - GO | D10: Blumenau - SC | E10: Navegantes - SC | F10: Itaquaquecetuba-SP
A11: SWITCH1 | B11: 10.10.22.30 | C11: 10.8.108.4 | D11: 10.8.100.5 | E11: 10.8.107.8 | F11: 10.5.6.36
A12: SWITCH2 | B12: 10.10.22.31 | C12: 10.8.108.5 | D12: 10.8.100.7 | E12: 10.8.107.5 | F12: 10.8.120.10
A13: SWITCH3 | F13: 10.8.120.11
A14: SWITCH4 | F14: 10.8.120.12
A15: SWITCH5 | F15: 10.8.120.30
A16: SWITCH6 | F16: 10.8.120.31
A17: SWITCH7 | F17: 10.8.120.32
A18: SWITCH8 | F18: 10.8.120.34
A19: SWITCH9 | F19: 10.8.120.35
A20: SWITCH10 | F20: 10.8.120.36
A21: SWITCH11 | F21: 10.8.120.37
A22: SWITCH12 | F22: 10.8.120.38
A23: SWITCH13 | F23: 10.8.120.40
A24: SWITCH14 | F24: 10.8.120.42
... A33: SWITCH23 | F33: 10.8.120.62

Sheet Detalhes Links Lojas
A1: Loja | B1: Estado | C1: Cidade | D1: Operadora 1 | E1: Contrato | F1: Data Ativação | G1: Vigencia | H1: Designação | I1: Banda | J1: Tipo | K1: Custo/mês | L1: Operadora 2 | M1: Contrato | N1: Data Ativação | O1: Vigencia | P1: Designação | Q1: Banda | R1: Tipo | S1: Custo/mês | T1: Modem 4G - Operadora - N° - Dados | U1: Modem 4G | V1: Operadora | W1: Número | X1: Pacote | Y1: Valor | Z1: Infra Extra | AA1: Valor | AB1: IP Loopback | AC1: IP Loja | AD1: IPs novos Lojas 129 | AE1: Custo Total de Links | AF1: S/N Fortigate | AG1: Última Atualização | AH1: Obs | AJ1: Legenda | AL1: Informação 100% atualizada
A2: 22 | B2: RS | C2: Porto Alegre | D2: Claro | E2: 2990930/2025 | F2: 45967 | G2: 47063 | H2: PAE/IP/20114 | I2: 20Mb | J2: Dedicado | K2: 433.98 | L2: Vero | M2: 2194177 | N2: 45595 | O2: 46690 | P2: 2194177 | Q2: 300Mb | R2: ADSL | S2: 298.9 | U2: --- | V2: --- | W2: --- | Z2: --- | AB2: 10.100.10.18 | AC2: 10.8.64.0/24 | AD2: --- | AE2: =SUM(K2+S2+Y2+AA2) -> 732.88 | AF2: FGT40FTK2109APML | AG2: 45967 | AL2: Falta alguma informação
A3: 43 | B3: SP | C3: São Caetano do Sul | D3: Mundivox | E3: 1894042673/25 | F3: 45904 | G3: 47000 | H3: 11008906 | I3: 100Mb | J3: Semidedicado | K3: 385 | L3: Vero | M3: 2194590 | N3: 45572 | O3: 46302 | P3: 2194590 | Q3: 300MB | R3: ADSL | S3: 298.9 | U3: --- | V3: --- | W3: --- | Z3: --- | AB3: 10.100.10.19 | AC3: 129.43.0.0/16 | AD3: 10.8.43.0/24 | AE3: =SUM(K3+S3+Y3+AA3) -> 683.9 | AF3: FGT40FTK2109A26A | AG3: 45904 | AL3: Informação antiga, sendo atualizada
A4: 80 | B4: PB | C4: Campina Grande | D4: Claro | E4: 2990930/2025 | F4: 46083 | G4: 47179 | H4: CGE/IP/01396 | I4: 20Mb | J4: Dedicado | K4: 461.8 | L4: Vivo | M4: 4116228/2025 | N4: 46002 | O4: 46732 | P4: CGE-817KBYYNOT-013 | Q4: 600Mb | R4: ADSL | S4: 94.99 | T4: 4G-LAN3-VIVO-11995086262 - 30Gb | U4: 4G-LAN3 | V4: VIVO | W4: (11)9 9508-6262 | X4: 30Gb | Y4: 104.05 | Z4: --- | AB4: 10.100.10.20 | AC4: 10.3.7.0/24 | AE4: =SUM(K4+S4+Y4+AA4) -> 660.84 | AF4: FGT40FTK21061990 | AG4: 46083
A5: 87 | B5: PI | C5: Teresina | D5: Claro | E5: 2990930/2025 | F5: 46043 | G5: 47139 | H5: TSA/IP/06690 | I5: 20Mb | J5: Dedicado | K5: 464.78 | L5: Vivo | M5: 899925644320 | N5: 45778 | O5: 46508 | P5: TSA-817GX9NCMF-013 | Q5: 700Mb | R5: ADSL | S5: 144.09 | U5: --- | V5: --- | W5: --- | Z5: --- | AB5: 10.100.10.21 | AC5: 10.3.8.0/24 | AD5: --- | AE5: =SUM(K5+S5+Y5+AA5) -> 608.87 | AF5: FGT40FTK21055522 | AG5: 46043
A6: 120 | B6: MA | C6: São Luis | D6: Vtal | E6: 23348 | F6: 46120 | G6: 46851 | H6: MASLS1000004067 | I6: 20Mb | J6: Dedicado | K6: 357.62 | L6: Fibrion | M6: ZZ45726013004 | N6: 45426 | O6: 46521 | P6: LOJA 120 - São Luis - MA | Q6: 15Mb | R6: ADSL | S6: 390 | T6: 4G-LAN3-CLARO-11993921432-30GB | U6: 4G-LAN3 | V6: CLARO | W6: (11) 99392-1432 | X6: 30Gb | AB6: 10.100.10.6 | AC6: 10.3.12.0/24 | AE6: =SUM(K6+S6+Y6+AA6) -> 747.62 | AF6: FGT40FTK21015404 | AG6: 46220
A7: 125 | B7: SE | C7: Aracajú | D7: Claro | E7: 2990930/2025 | F7: 45994 | G7: 47090 | H7: AJU/IP/08189 | I7: 20Mb | J7: Dedicado | K7: 450.25 | L7: Vivo | M7: 3249939 | N7: 45917 | O7: 46647 | P7: AJU-817JD8OCP9-013 | Q7: 600Mb | R7: ADSL | S7: 94.99 | U7: --- | V7: --- | W7: --- | Z7: --- | AB7: 10.100.10.13 | AC7: 10.3.13.0/24 | AD7: --- | AE7: =SUM(K7+S7+Y7+AA7) -> 545.24 | AF7: FGT40FTK2109A6UB | AG7: 45994
A8: 130 | B8: SC | C8: Florianópolis | D8: Claro | E8: 2990930/2025 | F8: 45996 | G8: 47092 | H8: FNS/IP/02758 | I8: 20Mb | J8: Dedicado | K8: 433.98 | L8: Vivo | M8: 22153440 | N8: 46181 | O8: 47277 | P8: 470000221281490 | Q8: 20Mb | R8: Dedicado | S8: 380 | U8: --- | V8: --- | W8: --- | Z8: --- | AB8: 10.100.10.14 | AC8: 129.130.0.0/16 | AD8: 10.8.130.0/24 | AE8: =SUM(K8+S8+Y8+AA8) -> 813.98 | AF8: FGT40FTK2109BRC2 | AG8: 46181
A9: 133 | B9: SP | C9: São Paulo | D9: Claro | E9: 2990930/2025 | F9: 45951 | G9: 47047 | H9: SPO/IP/96194 | I9: 20Mb | J9: Dedicado | K9: 439.27 | L9: SP18 | M9: 1199 | N9: 42745 | O9: Vencido | P9: INTERLAGOS | Q9: 10MB | R9: Dedicado | S9: 607.14 | U9: --- | V9: --- | W9: --- | Z9: --- | AB9: 10.100.10.15 | AC9: 10.7.16.0/24 | AE9: =SUM(K9+S9+Y9+AA9) -> 1046.41 | AF9: FGT40FTK21019934 | AG9: 45814
A10: 135 | B10: SC | C10: Joinville | D10: Algar | E10: 23352741/2025 | F10: 46087 | G10: 47183 | H10: 10079907 | I10: 20Mb | J10: Dedicado | K10: 360 | L10: Claro | M10: 2990848/2025 | N10: 45958 | O10: 47054 | P10: JVE/IP/02608 | Q10: 300Mb | R10: ADSL | S10: 187.56 | U10: --- | V10: --- | W10: --- | Z10: --- | AB10: 10.100.10.16 | AC10: 10.8.10.0/24 | AE10: =SUM(K10+S10+Y10+AA10) -> 547.56 | AF10: FGT40FTK22069539 | AG10: 46087
A11: 136 | B11: SP | C11: São Bernardo do Campo | D11: Mundivox | E11: 1894042673/25 | F11: 46027 | G11: 47123 | H11: 11019441 | I11: 100Mb | J11: Semidedicado | K11: 385 | L11: Vero | M11: 2194246 | N11: 45345 | O11: Vencido | P11: 2194246 | Q11: 300MB | R11: ADSL | S11: 298.9 | U11: --- | V11: --- | W11: --- | Z11: --- | AB11: 10.100.10.24 | AC11: 129.136.0.0/16 | AD11: 10.8.136.0/24 | AE11: =SUM(K11+S11+Y11+AA11) -> 683.9 | AF11: FGT40FTK2109A0DP | AG11: 46027
A12: 140 | B12: PE | C12: Petrolina | D12: Vtal | E12: 23348 | F12: 46093 | G12: 46824 | H12: PEPTA1000000702 | I12: 20Mb | J12: Dedicado | K12: 357.24 | L12: Claro | M12: VES-2-VAR-2853534-2025 | N12: 45896 | O12: 46626 | P12: PTA/IP/01059 | Q12: 20Mb | R12: Dedicado | S12: 453.09 | Z12: --- | AB12: 10.100.10.9 | AC12: 10.3.15.0/24 | AE12: =SUM(K12+S12+Y12+AA12) -> 810.33 | AF12: FGT40FTK21052450 | AG12: 46093
A13: 142 | B13: RJ | C13: Rio de Janeiro | D13: Mundivox | E13: 1894042673/25 | F13: 45975 | G13: 47071 | H13: 98376 | I13: 100Mb | J13: Semidedicado | K13: 385 | L13: Vero | M13: 2194719 | N13: 45595 | O13: 46690 | P13: 2194719 | Q13: 300Mb | R13: ADSL | S13: 298.9 | T13: 4G-USB-VERO-11951857351-30Gb | U13: 4G-USB | V13: VERO | W13: (11) 95185-7351 | X13: 30Gb | Z13: --- | AB13: 10.100.10.26 | AC13: 10.3.16.0/24 | AD13: --- | AE13: =SUM(K13+S13+Y13+AA13) -> 683.9 | AF13: FGT40FTK2109A2NP | AG13: 45975
A14: 150 | B14: DF | C14: Brasília | D14: Claro | E14: 2990930/2025 | F14: 45996 | G14: 47092 | H14: BSA/IP/25593 | I14: 20Mb | J14: Dedicado | K14: 450.25 | L14: Fibrion | M14: /2026 | N14: 46224 | O14: 46955 | P14: ZZ45726037004A | Q14: 50Mb | R14: Dedicado | S14: 410 | U14: --- | V14: --- | W14: --- | Z14: --- | AB14: 10.100.10.28 | AC14: 10.8.67.0/24 | AE14: =SUM(K14+S14+Y14+AA14) -> 860.25 | AF14: FGT40FTK2109AP42 | AG14: 46224
A15: 160 | B15: PI | C15: Teresina | D15: Claro | E15: 2990930/2025 | F15: 46031 | G15: 47127 | H15: TSA/IP/06654 | I15: 20Mb | J15: Dedicado | K15: 464.78 | L15: Vivo | M15: 22153440 | N15: 46206 | O15: 47302 | P15: 860000221276990 | Q15: 20Mb | R15: Dedicado | S15: 380 | U15: --- | V15: --- | W15: --- | Z15: --- | AB15: 10.100.10.22 | AC15: 10.3.20.0/24 | AE15: =SUM(K15+S15+Y15+AA15) -> 844.78 | AF15: FGT40FTK21064157 | AG15: 46231
A16: 165 | B16: SP | C16: Santo André | D16: Mundivox | E16: 1894042673/25 | F16: 46027 | G16: 47123 | H16: 11019436 | I16: 100Mb | J16: Semidedicado | K16: 385 | L16: Vero | M16: 2194707 | N16: 45595 | O16: 46690 | P16: 2194707 | Q16: 300Mb | R16: ADSL | S16: 298.9 | U16: --- | V16: --- | W16: --- | Z16: --- | AB16: 10.100.10.23 | AC16: 10.7.165.0/24 | AD16: --- | AE16: =SUM(K16+S16+Y16+AA16) -> 683.9 | AF16: FGT40FTK2109A0E2 | AG16: 46027
A17: 176 | B17: SP | C17: Guarulhos | D17: Mundivox | E17: 1894042673/25 | F17: 45965 | G17: 47061 | H17: 11019443 | I17: 100Mb | J17: Semidedicado | K17: 385 | L17: Vero | M17: 2194263 | N17: 45595 | O17: 46690 | P17: 2194263 | Q17: 300Mb | R17: ADSL | S17: 298.9 | U17: --- | V17: --- | W17: --- | Z17: --- | AB17: 10.100.10.25 | AC17: 129.176.0.0/16 | AD17: 10.8.176.0/24 | AE17: =SUM(K17+S17+Y17+AA17) -> 683.9 | AF17: FGT40FTK22068681 | AG17: 45965
A18: 178 | B18: GO | C18: Goiânia | D18: Claro | E18: 2990930/2025 | F18: 45993 | G18: 47089 | H18: ACG/IP/01186 | I18: 20Mb | J18: Dedicado | K18: 444.7 | L18: Vivo | M18: 2341178 | N18: 44425 | O18: Vencido | P18: 621980147058797 | Q18: 10MB | R18: Dedicado | S18: 497.86 | U18: --- | V18: --- | W18: --- | Z18: --- | AB18: 10.100.10.10 | AC18: 129.178.0.0/16 | AD18: 10.8.178.0/24 | AE18: =SUM(K18+S18+Y18+AA18) -> 942.56 | AF18: FGT40FTK22099US0 | AG18: 45797
A19: 180 | B19: SP | C19: Praia Grande | D19: Fibrion | E19: /2026 | F19: 46230 | G19: 46961 | H19: AF798013 FAS125A | I19: 50Mb | J19: Dedicado | K19: 410 | L19: Claro | M19: 2990848/2025 | N19: 45951 | O19: 47047 | P19: PGE/IP/00250 | Q19: 600Mb | R19: ADSL | S19: 227.82 | U19: --- | V19: --- | W19: --- | Z19: --- | AB19: 10.100.10.31 | AC19: 10.7.180.0/24 | AE19: =SUM(K19+S19+Y19+AA19) -> 637.82 | AF19: FGT40FTK21020072 | AG19: 46230
A20: 196 | B20: PB | C20: João Pessoa | D20: Claro | E20: 2990930/2025 | F20: 46007 | G20: 47103 | H20: JPA/IP/06759 | I20: 20Mb | J20: Dedicado | K20: 461.8 | L20: Irapido | M20: /2026 | N20: 46090 | O20: 46821 | P20: 196JoaoPessoa | Q20: 300Mb | R20: ADSL | S20: 400 | T20: 4G-USB-VERO-11935367628-30Gb | U20: 4G-USB | V20: VERO | W20: (11)93536-7628 | X20: 30Gb | Y20: 0 | Z20: --- | AB20: 10.100.10.32 | AC20: 10.3.27.0/24 | AE20: =SUM(K20+S20+Y20+AA20) -> 861.8 | AF20: FGT40FTK2109A26R | AG20: 46090
A21: 508 | B21: DF | C21: Brasília | D21: Claro | E21: 2990930/2025 | F21: 46007 | G21: 47103 | H21: BSA/IP/25646 | I21: 20Mb | J21: Dedicado | K21: 450.25 | L21: Vivo | M21: 22153440 | N21: 46176 | O21: 47272 | P21: 610000221280590 | Q21: 20Mb | R21: Dedicado | S21: 380 | U21: --- | V21: --- | W21: --- | Z21: --- | AB21: 10.100.10.33 | AC21: 10.8.18.0/24 | AE21: =SUM(K21+S21+Y21+AA21) -> 830.25 | AF21: FGT40FTK2109A2VF | AG21: 46181
A22: 510 | B22: SP | C22: São Paulo | D22: Claro | E22: 2990930/2025 | F22: 45951 | G22: 47047 | H22: SPO/IP/95878 | I22: 20MB | J22: Dedicado | K22: 439.27 | L22: Tesa | M22: 201603422 | O22: vencido | P22: LOJA 510 - PORTA DE DADOS 3 | Q22: 20MB | R22: Dedicado | S22: 758.82 | U22: --- | V22: --- | W22: --- | Z22: --- | AB22: 10.100.10.5 | AC22: 10.7.32.0/24 | AE22: =SUM(K22+S22+Y22+AA22) -> 1198.09 | AF22: FGT40FTK22067149 | AG22: 45951
A23: 514 | B23: AP | C23: Macapá | D23: Claro | E23: 2990930/2025 | F23: 46001 | G23: 47097 | H23: MPA/IP/01147 | I23: 20Mb | J23: Dedicado | K23: 507.33 | L23: Vivo | M23: 2341178 | N23: 45778 | O23: 46874 | P23: MPA-817GY6VGBV-013 | Q23: 700Mb | R23: ADSL | S23: 133.79 | T23: 4G-USB-VERO-11935367619-30Gb | U23: 4G-USB | V23: VERO | W23: (11)93536-7619 | X23: 30Gb | Z23: --- | AB23: 10.100.10.35 | AC23: 10.3.30.0/24 | AD23: --- | AE23: =SUM(K23+S23+Y23+AA23) -> 641.12 | AF23: FGT40FTK22075179 | AG23: 46001
A24: 515 | B24: SP | C24: São Paulo | D24: Mundivox | E24: 1894042673/25 | F24: 45904 | G24: 47000 | H24: 11008911 | I24: 100Mb | J24: Semidedicado | K24: 385 | L24: Vero | M24: 2194222 | N24: 45572 | O24: 46302 | P24: 2194222 | Q24: 300MB | R24: ADSL | S24: 298.9 | Z24: --- | AB24: 10.100.10.36 | AC24: 10.7.34.0/24 | AD24: --- | AE24: =SUM(K24+S24+Y24+AA24) -> 683.9 | AF24: FGT40FTK21021823 | AG24: 45904
A25: 517 | B25: AC | C25: Rio Branco | D25: Claro | E25: 2990930/2025 | F25: 46000 | G25: 47096 | H25: RBO/IP/01554 | I25: 20Mb | J25: Dedicado | K25: 444.7 | L25: Vtal | M25: 23348 | N25: 46072 | O25: 46802 | P25: ACRBO1000001730 | Q25: 20Mb | R25: Dedicado | S25: 350.62 | U25: --- | V25: --- | W25: --- | X25: Gb | Z25: --- | AB25: 10.100.10.11 | AC25: 129.213.0.0/16 | AD25: 10.5.17.0/24 | AE25: =SUM(K25+S25+Y25+AA25) -> 795.32 | AF25: FGT40FTK22075919 | AG25: 46072
A26: 518 | B26: SP | C26: Diadema | D26: Claro | E26: 2990930/2025 | F26: 45951 | G26: 47047 | H26: DDA/IP/02269 | I26: 20MB | J26: Dedicado | K26: 439.27 | L26: Vero | M26: 2194210 | N26: 45595 | O26: 46325 | P26: 2194210 | Q26: 300Mb | R26: ADSL | S26: 298.9 | U26: --- | V26: --- | W26: --- | Z26: --- | AB26: 10.100.10.12 | AC26: 10.7.118.0/24 | AD26: --- | AE26: =SUM(K26+S26+Y26+AA26) -> 738.17 | AF26: FGT40FTK21062013 | AG26: 45951
A27: 519 | B27: RO | C27: Porto Velho | D27: Vtal | E27: 23348 | F27: 46100 | G27: 46831 | H27: ROPVO1000002769 | I27: 20Mb | J27: Dedicado | K27: 352.8 | L27: Claro | M27: 2990848/2025 | N27: 45951 | O27: 47047 | P27: PVO/IP/01686 | Q27: 600Mb | R27: ADSL | S27: 226.44 | U27: --- | V27: --- | W27: --- | Z27: --- | AB27: 10.100.10.39 | AC27: 129.215.0.0/16 | AD27: 10.4.19.0/24 | AE27: =SUM(K27+S27+Y27+AA27) -> 579.24 | AF27: FGT40FTK2109A9GE | AG27: 46100
A28: 520 | B28: SP | C28: Mauá | D28: Claro | E28: 2990930/2025 | F28: 45994 | G28: 47090 | H28: MAU/IP/02231 | I28: 20Mb | J28: Dedicado | K28: 439.27 | L28: Vero | M28: 2194258 | N28: 45595 | O28: 46690 | P28: 2194258 | Q28: 300Mb | R28: ADSL | S28: 298.9 | U28: --- | V28: --- | W28: --- | Z28: --- | AB28: 10.100.10.37 | AC28: 129.216.0.0/16 | AD28: 10.6.20.0/24 | AE28: =SUM(K28+S28+Y28+AA28) -> 738.17 | AF28: FGT40FTK2109A0AS | AG28: 45994
A29: 525 | B29: SE | C29: Aracajú | D29: Claro | E29: 2990930/2025 | F29: 45967 | G29: 47063 | H29: AJU/IP/08194 | I29: 20Mb | J29: Dedicado | K29: 450.25 | L29: Vivo | M29: 4116228/2025 | N29: 46100 | O29: 47196 | P29: 790000211865299 | Q29: 20Mb | R29: Dedicado | S29: 380 | T29: 4G-USB- VERO-11935367311-30Gb | U29: 4G-USB | V29: VERO | W29: 11935367311 | X29: 30Gb | Z29: --- | AB29: 10.100.10.40 | AC29: 10.3.32.0/24 | AE29: =SUM(K29+S29+Y29+AA29) -> 830.25 | AF29: FGT40FTK2109A6YL | AG29: 46100
A30: 526 | B30: RS | C30: Canoas | D30: Algar | E30: 23352741/2025 | F30: 45968 | G30: 47064 | H30: 10079710 | I30: 20Mb | J30: Dedicado | K30: 360 | L30: Vero | M30: 2194215 | N30: 45572 | O30: 46302 | P30: 2194215 | Q30: 300MB | R30: ADSL | S30: 298.9 | U30: --- | V30: --- | W30: --- | Z30: --- | AB30: 10.100.10.41 | AC30: 10.8.23.0/24 | AD30: --- | AE30: =SUM(K30+S30+Y30+AA30) -> 658.9 | AF30: FGT40FTK21010497 | AG30: 45968
A31: 527 | B31: CE | C31: Fortaleza | D31: Claro | E31: 2990930/2025 | F31: 45999 | G31: 47095 | H31: FLA/IP/10878 | I31: 20Mb | J31: Dedicado | K31: 450.25 | L31: Irapido | M31: /2026 | N31: 46098 | O31: 46829 | P31: 527Fortaleza | Q31: 600Mb | R31: ADSL | S31: 250 | T31: 4G-USB-CLARO-11913426333-30Gb | U31: 4G-USB | V31: CLARO | W31: (11)91342-6333 | X31: 10Gb | Z31: --- | AB31: 10.100.10.42 | AC31: 10.3.33.0/24 | AE31: =SUM(K31+S31+Y31+AA31) -> 700.25 | AF31: FGT40FTK22071691 | AG31: 46098
A32: 529 | B32: RS | C32: São Leopoldo | D32: Claro | E32: 2990930/2025 | F32: 45950 | G32: 47046 | H32: SLE/IP/01230 | I32: 20Mb | J32: Dedicado | K32: 433.98 | L32: Vero | M32: 2194692 | N32: 45572 | O32: 46302 | P32: 2194692 | Q32: 300Mb | R32: ADSL | S32: 304.02 | U32: --- | V32: --- | W32: --- | Z32: --- | AB32: 10.100.10.43 | AC32: 129.225.0.0/16 | AD32: 10.5.29.0/24 | AE32: =SUM(K32+S32+Y32+AA32) -> 738 | AF32: FGT40FTK20006514 | AG32: 45951
A33: 531 | B33: MG | C33: Belo Horizonte | D33: Mundivox | E33: 1894042673/25 | F33: 45954 | G33: 47050 | H33: 31003593 | I33: 100Mb | J33: Semidedicado | K33: 385 | L33: Vivo | M33: 3249939 | N33: 45967 | O33: 46697 | P33: BHE-817JQEA8OT-013 | Q33: 600Mb | R33: ADSL | S33: 94.9 | U33: --- | V33: --- | W33: --- | Z33: --- | AB33: 10.100.10.251 | AC33: 10.3.36.0/24 | AE33: =SUM(K33+S33+Y33+AA33) -> 479.9 | AF33: FGT40FTK21061463 | AG33: 45967
A34: 534 | B34: SP | C34: Jundiaí | D34: Fibrion | E34: AI055003 FAS004A | F34: 46029 | G34: 47125 | H34: AI055003 FAS004A | I34: 100Mb | J34: Dedicado | K34: 430 | L34: Claro | M34: 2990930/2026 | N34: 46206 | O34: 47302 | P34: JAI/IP/02770 | Q34: 20Mb | R34: Dedicado | S34: 403.13 | U34: --- | V34: --- | W34: --- | Z34: --- | AB34: 10.100.10.44 | AC34: 129.230.0.0/16 | AD34: 10.5.34.0/24 | AE34: =SUM(K34+S34+Y34+AA34) -> 833.13 | AF34: FGT40FTK2109AQJJ | AG34: 46224
A35: 535 | B35: PR | C35: São José dos Pinhais | D35: Claro | E35: 2990930/2025 | F35: 45999 | G35: 47095 | H35: SJP/IP/01447 | I35: 20Mb | J35: Dedicado | K35: 447.46 | L35: Vivo | M35: 2194188 | N35: 45778 | O35: 46508 | P35: SJP817HG2IQL5-013 | Q35: 600Mb | R35: ADSL | S35: 129.99 | U35: --- | V35: --- | W35: --- | Z35: --- | AB35: 10.100.10.45 | AC35: 129.231.0.0/16 | AD35: 10.5.35.0/24 | AE35: =SUM(K35+S35+Y35+AA35) -> 577.45 | AF35: FGT40FTK21063262 | AG35: 45999
A36: 536 | B36: MG | C36: Belo Horizonte | D36: Algar | E36: 23352741/2025 | F36: 45953 | G36: 47049 | H36: 10079638 | I36: 20Mb | J36: Dedicado | K36: 360 | L36: Claro | M36: 2990848/2025 | N36: 45951 | O36: 47047 | P36: BHE/IP/18535 | Q36: 600Mb | R36: ADSL | S36: 227.82 | Z36: --- | AB36: 10.100.10.46 | AC36: 10.3.37.0/24 | AD36: --- | AE36: =SUM(K36+S36+Y36+AA36) -> 587.82 | AF36: FGT40FTK21015937 | AG36: 45951
A37: 544 | B37: SP | C37: São Paulo | D37: Mundivox | E37: 1894042673/25 | F37: 45980 | G37: 47076 | H37: 11019435 | I37: 100Mb | J37: Semidedicado | K37: 385 | L37: Vero | M37: 2194219 | N37: 45595 | O37: 46325 | P37: 2194219 | Q37: 300Mb | R37: ADSL | S37: 298.9 | U37: --- | V37: --- | W37: --- | Z37: --- | AB37: 10.100.10.48 | AC37: 129.240.0.0/16 | AD37: 10.5.44.0/24 | AE37: =SUM(K37+S37+Y37+AA37) -> 683.9 | AF37: FGT40FTK21058963 | AG37: 45805
A38: 546 | B38: SP | C38: São Bernardo do Campo | D38: Claro | E38: 2990930/2025 | F38: 45951 | G38: 47047 | H38: SBO/IP/06617 | I38: 20MB | J38: Dedicado | K38: 439.27 | L38: Vero | M38: 2194159 | N38: 45595 | O38: 46325 | P38: 2194159 | Q38: 300Mb | R38: ADSL | S38: 298.9 | T38: 4G-USB-VERO-11935052445-30GB | U38: 4G-USB | V38: VERO | W38: 11935052445 | X38: 30Gb | Y38: 0 | Z38: --- | AB38: 10.100.10.49 | AC38: 10.7.44.0/24 | AD38: --- | AE38: =SUM(K38+S38+Y38+AA38) -> 738.17 | AF38: FGT40FTK21020738 | AG38: 45951
A39: 547 | B39: SP | C39: Santos | D39: Fibrion | E39: ZZ45726037001A | F39: 46041 | G39: 46771 | H39: ZZ45726037001A | I39: 100Mb | J39: Dedicado | K39: 430 | L39: Vero | M39: 2194275 | N39: 45572 | O39: 46302 | P39: 2194275 | Q39: 300MB | R39: ADSL | S39: 298.9 | U39: --- | V39: --- | W39: --- | Z39: --- | AB39: 10.100.10.50 | AC39: 10.7.45.0/24 | AD39: --- | AE39: =SUM(K39+S39+Y39+AA39) -> 728.9 | AF39: FGT40FTK21059064 | AG39: 46042
A40: 548 | B40: PR | C40: Curitiba | D40: Claro | E40: 2990930/2025 | F40: 45996 | G40: 47092 | H40: CTA/IP/20429 | I40: 20Mb | J40: Dedicado | K40: 447.46 | L40: Vivo | M40: 2194188 | N40: 45778 | O40: 46508 | P40: CTA-817HG1NHZ1-013 | Q40: 600Mb | R40: ADSL | S40: 129.99 | Z40: --- | AB40: 10.100.10.51 | AC40: 129.76.0.0/16 | AD40: 10.5.48.0/24 | AE40: =SUM(K40+S40+Y40+AA40) -> 577.45 | AF40: FGT40FTK22068723 | AG40: 46062
A41: 549 | B41: SP | C41: Ribeirão Preto | D41: Claro | E41: 2990930/2025 | F41: 45951 | G41: 47047 | H41: RPO/IP/10333 | I41: 20MB | J41: Dedicado | K41: 439.27 | L41: Vero | M41: 2194163 | N41: 46142 | O41: 46873 | P41: 2194163 | Q41: 100Mb | R41: Dedicado | S41: 280 | U41: --- | V41: --- | W41: --- | Z41: --- | AB41: 10.100.10.52 | AC41: 10.7.149.0/24 | AD41: --- | AE41: =SUM(K41+S41+Y41+AA41) -> 719.27 | AF41: FGT40FTK21030190 | AG41: 45951
A42: 550 | B42: SP | C42: Guarulhos | D42: Mundivox | E42: 1894042673/25 | F42: 45904 | G42: 47000 | H42: 11008908 | I42: 100Mb | J42: Semidedicado | K42: 385 | L42: Claro | M42: 2990848/2025 | N42: 45951 | O42: 47047 | P42: GRS/IP/03825 | Q42: 600mb | R42: ADSL | S42: 227.82 | U42: --- | V42: --- | W42: --- | Z42: --- | AB42: 10.100.10.53 | AC42: 10.7.150.0/24 | AD42: --- | AE42: =SUM(K42+S42+Y42+AA42) -> 612.82 | AF42: FGT40FTK21015267 | AG42: 45951
A43: 553 | B43: RN | C43: Natal | D43: Algar | E43: 498254216 | F43: 45226 | G43: 46322 | H43: 9307692 | I43: 100MB | J43: Dedicado | K43: 442.53 | L43: Claro | M43: 2990848/2025 | N43: 45959 | O43: 47055 | P43: NTL/IP/07477 | Q43: 300Mb | R43: ADSL | S43: 194.6 | U43: --- | V43: --- | W43: --- | Z43: --- | AB43: 10.100.10.54 | AC43: 10.3.42.0/24 | AD43: --- | AE43: =SUM(K43+S43+Y43+AA43) -> 637.13 | AF43: FGT40FTK22068125 | AG43: 46156 | AH43: FIrewall trocado nessa data - FGT40FTK25033571 novo
A44: 558 | B44: AM | C44: Manaus | D44: Claro | E44: 2990930/2025 | F44: 45996 | G44: 47092 | H44: MNS/IP/06488 | I44: 20Mb | J44: Dedicado | K44: 450.25 | L44: Vivo | M44: 899925650790 | N44: 45778 | O44: 46508 | P44: MNS-817GWN21FB-013 | Q44: 700Mb | R44: ADSL | S44: 144.09 | U44: --- | V44: --- | W44: --- | Z44: --- | AB44: 10.100.10.55 | AC44: 10.3.46.0/24 | AD44: ---- | AE44: =SUM(K44+S44+Y44+AA44) -> 594.34 | AF44: FGT40FTK22068180 | AG44: 45996
A45: 559 | B45: SP | C45: Osasco | D45: Claro | E45: 2990930/2025 | F45: 45951 | G45: 47047 | H45: OCO/IP/04810 | I45: 20MB | J45: Dedicado | K45: 439.27 | L45: Vero | M45: 2194776 | N45: 45595 | O45: 46690 | P45: 2194776 | Q45: 300Mb | R45: ADSL | S45: 298.9 | T45: 4G-LAN3-VERO-11 935036255-30GB | U45: 4G-LAN3 | V45: VERO | W45: (11) 935036255 | X45: 30Gb | Z45: --- | AB45: 10.100.10.56 | AC45: 10.7.159.0/24 | AD45: --- | AE45: =SUM(K45+S45+Y45+AA45) -> 738.17 | AF45: FGT40FTK2109A8VB | AG45: 46241 | AH45: instalado 4g devido link vero fora por cabo rompido
A46: 560 | B46: PA | C46: Belém | D46: Claro | E46: 2990930/2025 | F46: 46029 | G46: 47125 | H46: BLM/IP/09398 | I46: 20Mb | J46: Dedicado | K46: 444.7 | L46: Vtal | M46: 23348 | N46: 46120 | O46: 46851 | P46: PABLM1000004792 | Q46: 20Mb | R46: Dedicado | S46: 350.62 | U46: --- | V46: --- | W46: --- | Z46: --- | AB46: 10.100.10.57 | AC46: 10.3.47.0/24 | AD46: --- | AE46: =SUM(K46+S46+Y46+AA46) -> 795.32 | AF46: FGT40FTK22099MHN | AG46: 46120
A47: 563 | B47: SP | C47: São Paulo | D47: Algar | E47: 23352741/2025 | F47: 45925 | G47: 47021 | H47: 10079708 | I47: 20Mb | J47: Dedicado | K47: 360 | L47: Vero | M47: 2194268 | N47: 45572 | O47: 46302 | P47: 2194268 | Q47: 300MB | R47: ADSL | S47: 298.9 | U47: --- | V47: --- | W47: --- | Z47: --- | AB47: 10.100.10.58 | AC47: 10.7.50.0/24 | AD47: --- | AE47: =SUM(K47+S47+Y47+AA47) -> 658.9 | AF47: FGT40FTK21061688 | AG47: 45925
A48: 564 | B48: SP | C48: São Paulo | D48: Claro | E48: 2990930/2025 | F48: 45966 | G48: 47062 | H48: SPO/IP/96403 | I48: 20Mb | J48: Dedicado | K48: 439.27 | L48: Vero | M48: 2194227 | N48: 45595 | O48: 46690 | P48: 2194227 | Q48: 300Mb | R48: ADSL | S48: 298.9 | U48: --- | V48: --- | W48: --- | Z48: --- | AB48: 10.100.10.59 | AC48: 129.92.0.0/16 | AD48: 10.5.64.0/24 | AE48: =SUM(K48+S48+Y48+AA48) -> 738.17 | AF48: FGT40FTK22067557 | AG48: 45966
A49: 565 | B49: PE | C49: Jaboatão dos Guararapes | D49: Mundivox | E49: 1894042673/25 | F49: 45897 | G49: 46993 | H49: 81000176 | I49: 100Mb | J49: Semidedicado | K49: 385 | L49: Claro | M49: 2990848/2025 | N49: 45945 | O49: 47041 | P49: JBO/IP/03176 | Q49: 300Mb | R49: ADSL | S49: 195.82 | Z49: --- | AB49: 10.100.10.60 | AC49: 10.3.50.0/24 | AD49: --- | AE49: =SUM(K49+S49+Y49+AA49) -> 580.82 | AF49: FGT40FTK21049234 | AG49: 45945
A50: 566 | B50: AL | C50: Maceió | D50: Claro | E50: 2990930/2025 | F50: 46009 | G50: 47105 | H50: MCO/IP/10344 | I50: 20Mb | J50: Dedicado | K50: 450.25 | L50: Vivo | M50: 22153440 | N50: 46203 | O50: 47299 | P50: 820000221277890 | Q50: 20Mb | R50: Dedicado | S50: 380 | U50: --- | V50: --- | W50: --- | Z50: --- | AB50: 10.100.10.61 | AC50: 10.3.51.0/24 | AD50: --- | AE50: =SUM(K50+S50+Y50+AA50) -> 830.25 | AF50: FGT40FTK22068276 | AG50: 46203
A51: 571 | B51: RS | C51: Cachoeirinha | D51: Claro | E51: 2990930/2026 | F51: 46232 | G51: 47328 | H51: CHN/IP/00770 | I51: 20Mb | J51: Dedicado | K51: 398.05 | L51: Fibrion | M51: ZZ45726037002 | N51: 45533 | O51: 46628 | P51: LOJA 571 - Shopping do Vale - RS | Q51: 100MB | R51: Dedicado | S51: 430 | T51: 4G-USB-VVIVO-11995059068-10Gb | U51: 4G-USB | V51: VIVO | W51: (11)99505-9068 | X51: 10Gb | Z51: --- | AB51: 10.100.10.62 | AC51: 129.137.0.0/16 | AD51: 10.5.71.0/24 | AE51: =SUM(K51+S51+Y51+AA51) -> 828.05 | AF51: FGT40FTK20013140 | AG51: 46206
A52: 573 | B52: SP | C52: Santo André | D52: Claro | E52: 2990930/2025 | F52: 46045 | G52: 47141 | H52: SNE/IP/03896 | I52: 20Mb | J52: Dedicado | K52: 439.27 | L52: Vivo | M52: 2341178 | N52: 44421 | O52: Vencido | P52: 116334990013698 | Q52: 10MB | R52: Dedicado | S52: 497 | U52: --- | V52: --- | W52: --- | Z52: --- | AB52: 10.100.10.63 | AC52: 129.74.0.0/16 | AD52: 10.5.73.0/24 | AE52: =SUM(K52+S52+Y52+AA52) -> 936.27 | AF52: FGT40FTK2109A245 | AG52: 46045
A53: 575 | B53: RJ | C53: São Gonçalo | D53: Fibrion | E53: ZZ45726037003 | F53: 45512 | G53: 46607 | H53: LOJA 575 - Alcantara - RJ | I53: 100Mb | J53: Dedicado | K53: 430 | L53: Vtal | M53: 23348 | N53: 46059 | O53: 46789 | P53: RJSGO1000000525 | Q53: 400Mb | R53: ADSL | S53: 304.57 | U53: --- | V53: --- | W53: --- | Z53: --- | AB53: 10.100.10.64 | AC53: 10.3.55.0/24 | AD53: --- | AE53: =SUM(K53+S53+Y53+AA53) -> 734.57 | AF53: FGT40FTK2109A2ME | AG53: 46059
A54: 576 | B54: SP | C54: Campinas | D54: Mundivox | E54: 1894042673/25 | F54: 45944 | G54: 47040 | H54: 11019440 | I54: 100Mb | J54: Semidedicado | K54: 385 | L54: Vero | M54: 2194174 | N54: 45595 | O54: 46325 | P54: 2194174 | Q54: 300Mb | R54: ADSL | S54: 298.9 | U54: --- | V54: --- | W54: --- | Z54: --- | AB54: 10.100.10.65 | AC54: 10.7.56.0/24 | AD54: --- | AE54: =SUM(K54+S54+Y54+AA54) -> 683.9 | AF54: FGT40FTK21012311 | AG54: 45944
A55: 577 | B55: SP | C55: Mogi das Cruzes | D55: Claro | E55: 2990930/2025 | F55: 45995 | G55: 47091 | H55: MCZ/IP/01667 | I55: 20Mb | J55: Dedicado | K55: 439.27 | L55: Vero | M55: 2194188 | N55: 45595 | O55: 46690 | P55: 2194188 | Q55: 300Mb | R55: ADSL | S55: 298.9 | U55: --- | V55: --- | W55: --- | Z55: --- | AB55: 10.100.10.66 | AC55: 129.33.0.0/16 | AD55: 10.5.77.0/24 | AE55: =SUM(K55+S55+Y55+AA55) -> 738.17 | AF55: FGT40FTK2109A0D9 | AG55: 45995 | AH55: Vero, reajuste 05/2025
A56: 578 | B56: SC | C56: Tubarão | D56: Claro | E56: 2990930/2025 | F56: 45982 | G56: 47078 | H56: TRO/IP/00448 | I56: 20Mb | J56: Dedicado | K56: 433.98 | L56: Vivo | M56: 22153440 | N56: 46192 | O56: 47288 | P56: 471990221273694 | Q56: 20Mb | R56: Dedicado | S56: 380 | U56: --- | V56: --- | W56: --- | Z56: --- | AB56: 10.100.10.67 | AC56: 10.8.30.0/24 | AD56: --- | AE56: =SUM(K56+S56+Y56+AA56) -> 813.98 | AF56: FGT40FTK21005799 | AG56: 46192
A57: 579 | B57: SP | C57: São Paulo | D57: Algar | E57: 23352741/2025 | F57: 45952 | G57: 47048 | H57: 10079713 | I57: 20Mb | J57: Dedicado | K57: 360 | L57: Vero | M57: 2194207 | N57: 45595 | O57: 46690 | P57: 2194207 | Q57: 300Mb | R57: ADSL | S57: 298.9 | T57: 4G-LAN3-CLARO-11988247327-30Gb | U57: 4G-LAN3 | V57: CLARO | W57: (11)98824-7327 | X57: 30Gb | Z57: --- | AB57: 10.100.10.68 | AC57: 10.7.179.0/24 | AD57: --- | AE57: =SUM(K57+S57+Y57+AA57) -> 658.9 | AF57: FGT40FTK2109A2MX | AG57: 46241 | AH57: instalado 4g devido falha nos dois links
A58: 580 | B58: SP | C58: Piracicaba | D58: Claro | E58: 2990930/2025 | F58: 45982 | G58: 47078 | H58: PAA/IP/03834 | I58: 20Mb | J58: Dedicado | K58: 439.27 | L58: Vivo | M58: 3249939 | N58: 45944 | O58: 46674 | P58: PAA-817JDDTYE3-013 | Q58: 600Mb | R58: ADSL | S58: 94.99 | U58: --- | V58: --- | W58: --- | Z58: --- | AB58: 10.100.10.69 | AC58: 129.145.0.0/16 | AD58: 10.5.80.0/24 | AE58: =SUM(K58+S58+Y58+AA58) -> 534.26 | AF58: FGT40FTK21028599 | AG58: 45982
A59: 582 | B59: RS | C59: Porto Alegre | D59: Claro | E59: 2990930/2025 | F59: 45964 | G59: 47060 | H59: PAE/IP/20133 | I59: 20Mb | J59: Dedicado | K59: 433.98 | L59: Vivo | M59: 2194188 | N59: 45778 | O59: 46508 | P59: PAE-817HE8TQM7-013 | Q59: 700MB | R59: ADSL | S59: 144.9 | U59: --- | V59: --- | W59: --- | Z59: --- | AB59: 10.100.10.70 | AC59: 10.8.31.0/24 | AD59: --- | AE59: =SUM(K59+S59+Y59+AA59) -> 578.88 | AF59: FGT40FTK21025762 | AG59: 45964
A60: 583 | B60: MG | C60: Belo Horizonte | D60: Algar | E60: 23352741/2025 | F60: 46058 | G60: 47154 | H60: 10079639 | I60: 20Mb | J60: Dedicado | K60: 360 | L60: Claro | M60: 2990848/2025 | N60: 45951 | O60: 47047 | P60: BHE/IP/18635 | Q60: 600MB | R60: ADSL | S60: 227.82 | T60: 4G-USB-VERO-11935367622-30Gb | U60: 4G-USB | V60: VERO | W60: (11) 93536-7622 | X60: 30Gb | Z60: --- | AB60: 10.100.10.71 | AC60: 10.3.56.0/24 | AD60: --- | AE60: =SUM(K60+S60+Y60+AA60) -> 587.82 | AF60: FGT40FTK21018667 | AG60: 46168 | AH60: modem instalado na loja nessa data devido queda
A61: 586 | B61: SP | C61: São Paulo | D61: Mundivox | E61: 1894042673/25 | F61: 45910 | G61: 47006 | H61: 11009059 | I61: 100Mb | J61: Semidedicado | K61: 436.91 | L61: Vero | M61: 2194245 | N61: 45572 | O61: 46667 | P61: 2194245 | Q61: 300MB | R61: ADSL | S61: 320.14 | U61: --- | V61: --- | W61: --- | Z61: --- | AB61: 10.100.10.73 | AC61: 129.114.0.0/16 | AD61: 10.5.86.0/24 | AE61: =SUM(K61+S61+Y61+AA61) -> 757.05 | AF61: FGT40FTK21014665 | AG61: 45910
A62: 589 | B62: AL | C62: Maceió | D62: Algar | E62: - SPO-2019-1026 | F62: 45226 | G62: 46322 | H62: 9307714 | I62: 100Mb | J62: Dedicado | K62: 524.04 | L62: Vivo | M62: 3249939 | N62: 45922 | O62: 46652 | P62: MCO-817JDFHI2B-013 | Q62: 600Mb | R62: ADSL | S62: 94.99 | U62: --- | V62: --- | W62: --- | Z62: --- | AB62: 10.100.10.17 | AC62: 10.3.58.0/24 | AD62: --- | AE62: =SUM(K62+S62+Y62+AA62) -> 619.03 | AF62: FGT40FTK22067302 | AG62: 45922
A63: 590 | B63: MG | C63: Contagem | D63: Claro | E63: 2990930/2026 | F63: 46213 | G63: 47309 | H63: CEM/IP/01832 | I63: 20Mb | J63: Dedicado | K63: 403.13 | L63: Mundivox | M63: 1894042673/25 | N63: 45938 | O63: 47034 | P63: 31003592 | Q63: 100Mb | R63: Semidedicado | S63: 385 | U63: --- | V63: --- | W63: --- | Z63: --- | AB63: 10.100.10.75 | AC63: 10.3.59.0/24 | AD63: --- | AE63: =SUM(K63+S63+Y63+AA63) -> 788.13 | AF63: FGT40FTK21016063 | AG63: 46224
A64: 594 | B64: SC | C64: Florianópolis | D64: Vtal | E64: 23348 | F64: 46111 | G64: 46842 | H64: SCFNS1000004555 | I64: 20Mb | J64: Dedicado | K64: 342.18 | L64: Claro | M64: 2990848/2025 | N64: 45951 | O64: 47047 | P64: FNS/IP/02139 | Q64: 600MB | R64: ADSL | S64: 224.97 | U64: --- | V64: --- | W64: --- | Z64: --- | AB64: 10.100.10.76 | AC64: 10.8.34.0/24 | AD64: --- | AE64: =SUM(K64+S64+Y64+AA64) -> 567.15 | AF64: FGT40FTK22099CKB | AG64: 46111
A65: 598 | B65: MS | C65: Dourados | D65: Claro | E65: 2990848/2025 | F65: 45951 | G65: 47047 | H65: DOS/IP/01439 | I65: 600Mb | J65: ADSL | K65: 225.08 | L65: Vivo | M65: 3249939 | N65: 45946 | O65: 46676 | P65: DOS-817JDEPDAB-013 | Q65: 600Mb | R65: ADSL | S65: 94.9 | U65: --- | V65: --- | W65: --- | Z65: --- | AB65: 10.100.10.78 | AC65: 129.108.0.0/16 | AD65: 10.5.98.0/24 | AE65: =SUM(K65+S65+Y65+AA65) -> 319.98 | AF65: FGT40FTK20013280 | AG65: 45946
A66: 599 | B66: PR | C66: Ponta Grossa | D66: Claro | E66: 2990930/2025 | F66: 45999 | G66: 47095 | H66: PGO/IP/00877 | I66: 20Mb | J66: Dedicado | K66: 447.46 | L66: Vivo | M66: 3249939 | N66: 45988 | O66: 46718 | P66: PGO-817K1FNCR7-013 | Q66: 600Mb | R66: ADSL | S66: 94.99 | U66: --- | V66: --- | W66: --- | Z66: --- | AB66: 10.100.10.79 | AC66: 129.116.0.0/16 | AD66: 10.5.99.0/24 | AE66: =SUM(K66+S66+Y66+AA66) -> 542.45 | AF66: FGT40FTK2109A2AE | AG66: 45999
A67: 600 | B67: BA | C67: Salvador | D67: Claro | E67: 2990930/2026 | F67: 46211 | G67: 47307 | H67: SDR/IP/22841 | I67: 20Mb | J67: Dedicado | K67: 416.41 | L67: Mundivox | M67: 1894042673/25 | N67: 45896 | O67: 46992 | P67: 71000355 | Q67: 100Mb | R67: Semidedicado | S67: 385 | Z67: --- | AB67: 10.100.10.80 | AC67: 10.3.63.0/24 | AD67: --- | AE67: =SUM(K67+S67+Y67+AA67) -> 801.41 | AF67: FGT40FTK22082057 | AG67: 46224
A68: 601 | B68: PE | C68: Recife | D68: Mundivox | E68: 1894042673/25 | F68: 45902 | G68: 46998 | H68: 81000012 | I68: 100Mb | J68: Semidedicado | K68: 385 | L68: Claro | M68: VES-2-VAR-2853534-2025 | N68: 45895 | O68: 46625 | P68: RCE/IP/21699 | Q68: 600Mb | R68: ADSL | S68: 234.99 | T68: 4G-USB-VERO-11935055343-30Gb | U68: 4G-USB | V68: VERO | W68: (11)93505-5343 | X68: 30Gb | Y68: 0 | Z68: --- | AB68: 10.100.10.81 | AC68: 10.3.64.0/24 | AE68: =SUM(K68+S68+Y68+AA68) -> 619.99 | AF68: FGT40FTK21052531 | AG68: 46191 | AH68: modem 4g que era da loja 885 encerrada - Erika regional pegou emprestado com autorização do jeferson
A69: 605 | B69: PR | C69: Maringá | D69: Claro | E69: 2990930/2025 | F69: 45971 | G69: 47067 | H69: MGA/IP/01552 | I69: 20Mb | J69: Dedicado | K69: 447.46 | L69: Vivo | M69: 22153440 | N69: 46192 | O69: 47288 | P69: 413890221288599 | Q69: 20Mb | R69: Dedicado | S69: 380 | U69: --- | V69: --- | W69: --- | Z69: --- | AB69: 10.100.10.84 | AC69: 129.103.0.0/16 | AD69: 10.6.5.0/24 | AE69: =SUM(K69+S69+Y69+AA69) -> 827.46 | AF69: FGT40FTK2109AL2F | AG69: 46192
A70: 606 | B70: MG | C70: Ipatinga | D70: Claro | E70: 2990930/2025 | F70: 45978 | G70: 47074 | H70: IIG/IP/01637 | I70: 20Mb | J70: Dedicado | K70: 439.27 | L70: Vero | M70: /2026 | N70: 46136 | O70: 46867 | P70: 2780740 | Q70: 800Mb | R70: ADSL | S70: 280 | U70: --- | V70: --- | W70: --- | Z70: --- | AB70: 10.100.10.85 | AC70: 10.3.67.0/24 | AD70: --- | AE70: =SUM(K70+S70+Y70+AA70) -> 719.27 | AF70: FGT40FTK22099Q44 | AG70: 46136
A71: 607 | B71: SP | C71: Limeira | D71: Claro | E71: 2990930/2025 | F71: 45965 | G71: 47061 | H71: LRA/IP/03872 | I71: 20Mb | J71: Dedicado | K71: 439.27 | L71: Vero | M71: 2194255 | N71: 45572 | O71: 46302 | P71: 2194255 | Q71: 300MB | R71: ADSL | S71: 298.9 | U71: --- | V71: --- | W71: --- | Z71: --- | AB71: 10.100.10.86 | AC71: 129.17.0.0/16 | AD71: 10.6.7.0/24 | AE71: =SUM(K71+S71+Y71+AA71) -> 738.17 | AF71: FGT40FTK22068540 | AG71: 45965
A72: 608 | B72: SP | C72: Taubaté | D72: Claro | E72: 2990930/2025 | F72: 46007 | G72: 47103 | H72: TTE/IP/01540 | I72: 20Mb | J72: Dedicado | K72: 439.27 | L72: Vivo | M72: 22153440 | N72: 46174 | O72: 47270 | P72: 116613632083590 | Q72: 20MB | R72: Dedicado | S72: 380 | U72: --- | V72: --- | W72: --- | Z72: --- | AB72: 10.100.10.87 | AC72: 129.20.0.0/16 | AD72: 10.6.8.0/24 | AE72: =SUM(K72+S72+Y72+AA72) -> 819.27 | AF72: FGT40FTK2109A949 | AG72: 46174
A73: 610 | B73: PB | C73: Campina Grande | D73: Claro | E73: 2990930/2025 | F73: 46008 | G73: 47104 | H73: CGE/IP/01110 | I73: 20Mb | J73: Dedicado | K73: 461.8 | L73: Vivo | M73: 22153440 | N73: 46181 | O73: 47277 | P73: 830400221284992 | Q73: 20Mb | R73: Dedicado | S73: 380 | U73: --- | V73: --- | W73: --- | Z73: --- | AB73: 10.100.10.88 | AC73: 10.3.68.0/24 | AD73: --- | AE73: =SUM(K73+S73+Y73+AA73) -> 841.8 | AF73: FGT40FTK2109A3MH | AG73: 46181
A74: 613 | B74: SP | C74: São Paulo | D74: Claro | E74: 2990930/2025 | F74: 45982 | G74: 47078 | H74: SPO/IP/96904 | I74: 20Mb | J74: Dedicado | K74: 439.27 | L74: Vero | M74: 2194235 | N74: 45596 | O74: 46690 | P74: 2194235 | Q74: 300Mb | R74: ADSL | S74: 298.9 | U74: --- | V74: --- | W74: --- | Z74: --- | AB74: 10.100.10.89 | AC74: 129.81.0.0/16 | AD74: 10.6.13.0/24 | AE74: =SUM(K74+S74+Y74+AA74) -> 738.17 | AF74: FGT40FTK22066659 | AG74: 45982
A75: 617 | B75: GO | C75: Goiânia | D75: Algar | E75: - SPO-2019-1026 | F75: 45226 | G75: 46322 | H75: 9307724 | I75: 100Mb | J75: Dedicado | K75: 507.1 | L75: Claro | M75: 2990848/2025 | N75: 45946 | O75: 47042 | P75: GNA/IP/07167 | Q75: 300Mb | R75: ADSL | S75: 192.2 | U75: --- | V75: --- | W75: --- | Z75: --- | AB75: 10.100.10.90 | AC75: 129.105.0.0/16 | AD75: 10.6.17.0/24 | AE75: =SUM(K75+S75+Y75+AA75) -> 699.3 | AF75: FGT40FTK2109A2FG | AG75: 45946
A76: 618 | B76: BA | C76: Itabuna | D76: Claro | E76: 2990930/2025 | F76: 45971 | G76: 47067 | H76: ITB/IP/02780 | I76: 20Mb | J76: Dedicado | K76: 453.09 | L76: Vtal | M76: 23348 | N76: 46121 | O76: 46852 | P76: BAITB1000001051 | Q76: 20Mb | R76: Dedicado | S76: 357.24 | T76: 4G-USB-VERO-11935032530-30Gb | U76: 4G-USB | V76: VERO | W76: (11)93503-2530 | X76: 30Gb | Y76: 0 | Z76: --- | AB76: 10.100.10.91 | AC76: 10.3.69.0/24 | AD76: --- | AE76: =SUM(K76+S76+Y76+AA76) -> 810.33 | AF76: FGT40FTK2109A5EY | AG76: 46121
A77: 619 | B77: SP | C77: Guarulhos | D77: Claro | E77: 2990930/2025 | F77: 46000 | G77: 47096 | H77: GRS/IP/07395 | I77: 20Mb | J77: Dedicado | K77: 439.27 | L77: Vero | M77: 2194778 | N77: 45595 | O77: 46325 | P77: 2194778 | Q77: 300Mb | R77: ADSL | S77: 298.9 | U77: --- | V77: --- | W77: --- | Z77: --- | AB77: 10.100.10.92 | AC77: 129.40.0.0/16 | AD77: 10.6.19.0/24 | AE77: =SUM(K77+S77+Y77+AA77) -> 738.17 | AF77: FGT40FTK22067066 | AG77: 46001
A78: 622 | B78: SP | C78: São Paulo | D78: Wipi | E78: Termo 01 | F78: 46009 | G78: 46739 | H78: 9055_Dados | I78: 20Mb | J78: Dedicado | K78: 710 | L78: Vero | M78: 2194283 | N78: 45596 | O78: 46326 | P78: 2194283 | Q78: 300Mb | R78: ADSL | S78: 320.14 | U78: --- | V78: --- | W78: --- | Z78: --- | AB78: 10.100.10.93 | AC78: 10.7.222.0/24 | AD78: --- | AE78: =SUM(K78+S78+Y78+AA78) -> 1030.14 | AF78: FGT40FTK2109A2M8 | AG78: 46009
A79: 623 | B79: PE | C79: Caruaru | D79: Claro | E79: 2990930/2026 | F79: 46211 | G79: 47307 | H79: CRU/IP/03057 | I79: 20Mb | J79: Dedicado | K79: 416.41 | L79: WFT/AST | N79: 45523 | O79: 46618 | P79: Link - 623 | Q79: 200MB | R79: Semidedicado | S79: 200 | U79: --- | V79: --- | W79: --- | Z79: --- | AB79: 10.100.10.94 | AC79: 10.3.70.0/24 | AD79: --- | AE79: =SUM(K79+S79+Y79+AA79) -> 616.41 | AF79: FGT40FTK21054246 | AG79: 46224
A80: 624 | B80: SP | C80: São José dos Campos | D80: Claro | E80: 2990930/2025 | F80: 45995 | G80: 47091 | H80: SJC/IP/03632 | I80: 20Mb | J80: Dedicado | K80: 439.27 | L80: Vero | M80: 2194715 | N80: 45595 | O80: 46690 | P80: 2194715 | Q80: 300Mb | R80: ADSL | S80: 298.9 | U80: --- | V80: --- | W80: --- | Z80: --- | AB80: 10.100.10.95 | AC80: 10.7.70.0/24 | AD80: --- | AE80: =SUM(K80+S80+Y80+AA80) -> 738.17 | AF80: FGT40FTK2109A961 | AG80: 45995
A81: 625 | B81: MS | C81: Campo Grande | D81: Claro | E81: 2990930/2025 | F81: 45951 | G81: 47047 | H81: CPE/IP/04724 | I81: 20MB | J81: Dedicado | K81: 433.98 | L81: Vero | M81: 2194594 | N81: 45572 | O81: 46302 | P81: 2194594 | Q81: 300MB | R81: ADSL | S81: 298.9 | U81: --- | V81: --- | W81: --- | Z81: --- | AB81: 10.100.10.96 | AC81: 129.49.0.0/16 | AD81: 10.6.25.0/24 | AE81: =SUM(K81+S81+Y81+AA81) -> 732.88 | AF81: FGT40FTK21010061 | AG81: 45951
A82: 626 | B82: SP | C82: São Paulo | D82: Claro | E82: 2990930/2025 | F82: 45980 | G82: 47076 | H82: SPO/IP/97179 | I82: 20Mb | J82: Dedicado | K82: 439.27 | L82: Vero | M82: 2194252 | N82: 45595 | O82: 46690 | P82: 2194252 | Q82: 300Mb | R82: ADSL | S82: 298.9 | U82: --- | V82: --- | W82: --- | Z82: --- | AB82: 10.100.10.246 | AC82: 10.7.226.0/24 | AD82: --- | AE82: =SUM(K82+S82+Y82+AA82) -> 738.17 | AF82: FGT40FTK2109AAYB | AG82: 45980
A83: 627 | B83: RN | C83: Natal | D83: Claro | E83: 2990930/2025 | F83: 45996 | G83: 47092 | H83: NTL/IP/06588 | I83: 20Mb | J83: Dedicado | K83: 450.25 | L83: Vivo | M83: 3249939 | N83: 46064 | O83: 47160 | P83: 840000211865996 | Q83: 20Mb | R83: Dedicado | S83: 380 | T83: 4G-LAN3-VIVO-11942025033-30gb | U83: 4G-LAN3 | V83: VIVO | W83: (11) 94202-5033 | X83: 30Gb | Z83: --- | AB83: 10.100.10.97 | AC83: 10.3.71.0/24 | AD83: --- | AE83: =SUM(K83+S83+Y83+AA83) -> 830.25 | AF83: FGT40FTK2109A6G0 | AG83: 46064
A84: 629 | B84: SP | C84: São José do Rio Preto | D84: Claro | E84: 2990930/2025 | F84: 45980 | G84: 47076 | H84: SRR/IP/05055 | I84: 20Mb | J84: Dedicado | K84: 439.27 | L84: Fibrion | M84: AF798013 FAS139 | N84: 45143 | O84: 46239 | P84: LOJA 629 - Plaza Avenida Shop, - SP | Q84: 6MB | R84: Dedicado | S84: 759.98 | T84: 4G-USB-VERO-11935055957-30Gb | U84: 4G-USB | V84: VERO | W84: (11) 93505-5957 | X84: 30Gb | Z84: --- | AB84: 10.100.10.98 | AC84: 129.85.0.0/16 | AD84: 10.6.29.0/24 | AE84: =SUM(K84+S84+Y84+AA84) -> 1199.25 | AF84: FGT40FTK22066690 | AG84: 45980
A85: 631 | B85: SP | C85: Osasco | D85: Claro | E85: 2990930/2025 | F85: 45999 | G85: 47095 | H85: OCO/IP/04865 | I85: 20Mb | J85: Dedicado | K85: 439.27 | L85: Vero | M85: 2194700 | N85: 45572 | O85: 46302 | P85: 2194700 | Q85: 300MB | R85: ADSL | S85: 320.14 | U85: --- | V85: --- | W85: --- | Z85: --- | AB85: 10.100.10.7 | AC85: 10.7.231.0/24 | AD85: --- | AE85: =SUM(K85+S85+Y85+AA85) -> 759.41 | AF85: FGT40FTK21018318 | AG85: 45999
A86: 632 | B86: PR | C86: Curitiba | D86: Claro | E86: 2990930/2025 | F86: 45992 | G86: 47088 | H86: CTA/IP/20466 | I86: 20MB | J86: Dedicado | K86: 447.46 | L86: Vivo | M86: 22153440 | N86: 46198 | O86: 47294 | P86: 410000221274495 | Q86: 20Mb | R86: Dedicado | S86: 380 | U86: --- | V86: --- | W86: --- | Z86: --- | AB86: 10.100.10.99 | AC86: 129.62.0.0/16 | AD86: 10.6.32.0/24 | AE86: =SUM(K86+S86+Y86+AA86) -> 827.46 | AF86: FGT40FTK21005881 | AG86: 46198
A87: 633 | B87: RS | C87: Porto Alegre | D87: Claro | E87: 2990930/2025 | F87: 46009 | G87: 47105 | H87: PAE/IP/20106 | I87: 20Mb | J87: Dedicado | K87: 433.98 | L87: Oi | M87: 1859883/2014 | N87: 43837 | O87: Vencido | P87: PAE 0847606 | Q87: 10MB | R87: Dedicado | S87: 934.14 | T87: 4G-USB-VERO-11935364020-30Gb | U87: 4G-USB | V87: VERO | W87: (11)93536-4020 | X87: 30Gb | Z87: --- | AB87: 10.100.10.100 | AC87: 129.109.0.0/16 | AD87: 10.6.33.0/24 | AE87: =SUM(K87+S87+Y87+AA87) -> 1368.12 | AF87: FGT40FTK21004879 | AG87: 46009
A88: 635 | B88: MG | C88: Belo Horizonte | D88: Algar | E88: 23352741/2025 | F88: 46059 | G88: 47155 | H88: 10161792 | I88: 20Mb | J88: Dedicado | K88: 360 | L88: Claro | M88: 2990848/2025 | N88: 45951 | O88: 47047 | P88: BHE/IP/18636 | Q88: 600Mb | R88: ADSL | S88: 227.82 | U88: --- | V88: --- | W88: --- | Z88: --- | AB88: 10.100.10.101 | AC88: 10.3.74.0/24 | AD88: --- | AE88: =SUM(K88+S88+Y88+AA88) -> 587.82 | AF88: FGT40FTK21020336 | AG88: 46059
A89: 636 | B89: SP | C89: Marília | D89: Claro | E89: 2990930/2025 | F89: 46001 | G89: 47097 | H89: MIA/IP/02460 | I89: 20Mb | J89: Dedicado | K89: 439.27 | L89: Fibrion | M89: AF798013 FAS137 | N89: 45166 | O89: 46262 | P89: LOJA 636 - Marília Shop, - SP | Q89: 6MB | R89: Dedicado | S89: 759.98 | U89: --- | V89: --- | W89: --- | Z89: --- | AB89: 10.100.10.102 | AC89: 129.67.0.0/16 | AD89: 10.6.36.0/24 | AE89: =SUM(K89+S89+Y89+AA89) -> 1199.25 | AF89: FGT40FTK2109A3VX | AG89: 46001
A90: 639 | B90: SP | C90: Cubatão | D90: Claro | E90: 2990930/2025 | F90: 45966 | G90: 47062 | H90: CAO/IP/01386 | I90: 20Mb | J90: Dedicado | K90: 439.27 | L90: Vivo | M90: 3249939 | N90: 45994 | O90: 46724 | P90: CAO-817K0Y3URB-013 | Q90: 600Mb | R90: ADSL | S90: 94.99 | U90: --- | V90: --- | W90: --- | Z90: --- | AB90: 10.100.10.103 | AC90: 10.7.239.0/24 | AD90: ---- | AE90: =SUM(K90+S90+Y90+AA90) -> 534.26 | AF90: FGT40FTK22080332 | AG90: 45994
A91: 640 | B91: SP | C91: São Paulo | D91: Mundivox | E91: 1894042673/25 | F91: 45915 | G91: 47011 | H91: 11008904 | I91: 100Mb | J91: Semidedicado | K91: 385 | L91: Vero | M91: 2194603 | N91: 45572 | O91: 46302 | P91: 2194603 | Q91: 300MB | R91: ADSL | S91: 298.9 | U91: --- | V91: --- | W91: --- | Z91: --- | AB91: 10.100.10.104 | AC91: 129.118.0.0/16 | AD91: 10.6.40.0/24 | AE91: =SUM(K91+S91+Y91+AA91) -> 683.9 | AF91: FGT40FTK21017488 | AG91: 45915 | AH91: links atualizado nessa data
A92: 641 | B92: SP | C92: Ferraz de Vasconcelos | D92: Claro | E92: 2990930/2025 | F92: 45961 | G92: 47057 | H92: FAV/IP/01283 | I92: 20Mb | J92: Dedicado | K92: 439.27 | L92: Vero | M92: 1792583 | N92: 45180 | O92: 46276 | P92: 1792583 | Q92: 300MB | R92: ADSL | S92: 299.9 | Z92: --- | AB92: 10.100.10.4 | AC92: 129.121.0.0/16 | AD92: 10.6.41.0/24 | AE92: =SUM(K92+S92+Y92+AA92) -> 739.17 | AF92: FGT40FTK2209A0JL | AG92: 45961
A93: 642 | B93: SP | C93: Guaratinguetá | D93: Claro | E93: 2990930/2025 | F93: 46007 | G93: 47103 | H93: GTA/IP/00439 | I93: 20Mb | J93: Dedicado | K93: 439.27 | L93: Vivo | M93: 3249939 | N93: 45957 | O93: 46687 | P93: GTA-817JDZJJ4L-013 | Q93: 600Mb | R93: ADSL | S93: 94.9 | U93: --- | V93: --- | W93: --- | Z93: --- | AB93: 10.100.10.105 | AC93: 129.122.0.0/16 | AD93: 10.6.42.0/24 | AE93: =SUM(K93+S93+Y93+AA93) -> 534.17 | AF93: FGT40FTK2109A9D2 | AG93: 46007
A94: 643 | B94: PB | C94: João Pessoa | D94: Algar | E94: 23352741/2025 | F94: 45952 | G94: 47048 | H94: 10079714 | I94: 20Mb | J94: Dedicado | K94: 360 | L94: Claro | M94: 2990930/2026 | N94: 46195 | O94: 47291 | P94: JPA/IP/07596 | Q94: 20Mb | R94: Dedicado | S94: 424.82 | T94: 4G-USB-VIVO-11950502054-30Gb | U94: 4G-USB | V94: VIVO | W94: (11) 95050-2054 | X94: 10Gb | Z94: --- | AB94: 10.100.10.106 | AC94: 10.3.75.0/24 | AE94: =SUM(K94+S94+Y94+AA94) -> 784.82 | AF94: FGT40FTK21059191 | AG94: 46195
A95: 645 | B95: SP | C95: Jacareí | D95: Claro | E95: 2990930/2025 | F95: 45944 | G95: 47040 | H95: JCI/IP/01038 | I95: 20Mb | J95: Dedicado | K95: 439.27 | L95: Vero | M95: 2194596 | N95: 45572 | O95: 46302 | P95: 2194596 | Q95: 300MB | R95: ADSL | S95: 298.9 | U95: --- | V95: --- | W95: --- | Z95: --- | AB95: 10.100.10.107 | AC95: 129.149.0.0/16 | AD95: 10.6.45.0/24 | AE95: =SUM(K95+S95+Y95+AA95) -> 738.17 | AF95: FGT40FTK21014295 | AG95: 45944
A96: 646 | B96: BA | C96: Salvador | D96: Claro | E96: 2990930/2025 | F96: 46069 | G96: 47165 | H96: SDR/IP/31403 | I96: 20MB | J96: Dedicado | K96: 453.09 | L96: ITS Brasil | M96: /2026 | N96: 46113 | O96: 46478 | P96: LJ646SHBAHIA | Q96: 400Mb | R96: ADSL | S96: 319.9 | T96: 4G-LAN3-VERO-11935055342-30Gb | U96: 4G-LAN3 | V96: VERO | W96: (11)93505-5342 | X96: 30Gb | Z96: --- | AB96: 10.100.10.108 | AC96: 10.3.77.0/24 | AD96: --- | AE96: =SUM(K96+S96+Y96+AA96) -> 772.99 | AF96: FGT40FTK2109A40P | AG96: 46113
A97: 647 | B97: SP | C97: Guarujá | D97: Claro | E97: 2990930/2025 | F97: 45971 | G97: 47067 | H97: GJA/IP/02131 | I97: 20Mb | J97: Dedicado | K97: 439.27 | L97: Vivo | M97: 2341178 | N97: 45267 | O97: 46729 | P97: GJA-8179JSR3LD-013 | Q97: 500MB | R97: ADSL | S97: 326.33 | U97: --- | V97: --- | W97: --- | Z97: --- | AB97: 10.100.10.109 | AC97: 129.155.0.0/16 | AD97: 10.6.47.0/24 | AE97: =SUM(K97+S97+Y97+AA97) -> 765.6 | AF97: FGT40FTK22081904 | AG97: 45971
A98: 648 | B98: SP | C98: Taboão da Serra | D98: Embratel | E98: VES-2-VAR-00089-2010 | F98: 44765 | G98: Vencido | H98: TBS/IP/01508 | I98: 6MB | J98: Dedicado | K98: 439.27 | L98: Vero | M98: 2194213 | N98: 46077 | O98: 46807 | P98: 2194213 | Q98: 800Mb | R98: ADSL | S98: 280 | U98: --- | V98: --- | W98: --- | Z98: --- | AB98: 10.100.10.110 | AC98: 129.158.0.0/16 | AD98: 10.6.48.0/24 | AE98: =SUM(K98+S98+Y98+AA98) -> 719.27 | AF98: FGT40FTK2109AFQV | AG98: 46077
A99: 649 | B99: PR | C99: Curitiba | D99: Claro | E99: 2990930/2025 | F99: 45954 | G99: 47050 | H99: CTA/IP/23665 | I99: 20Mb | J99: Dedicado | K99: 447.46 | L99: Fibrion | M99: AI055003 FAS038 | N99: 45738 | O99: 46834 | P99: LOJA 649 - Palladium Shop, Center - PR | Q99: 30Mb | R99: ADSL | S99: 446.42 | T99: 4G-LAN3-CLARO-11988247332-20Gb | U99: 4G-LAN3 | V99: CLARO | W99: (11) 98824-7332 | X99: 30Gb | Z99: Golden Jumper | AA99: 200 | AB99: 10.100.10.111 | AC99: 129.161.0.0/16 | AD99: 10.6.49.0/24 | AE99: =SUM(K99+S99+Y99+AA99) -> 1093.88 | AF99: FGT40FTK21059823 | AG99: 45957 | AH99: Goldem Jumper pago para o shopping
A100: 650 | B100: PA | C100: Belém | D100: Claro | E100: 2990930/2025 | F100: 45964 | G100: 47060 | H100: BLM/IP/09410 | I100: 20Mb | J100: Dedicado | K100: 444.7 | L100: Vtal | M100: 23348 | N100: 46122 | O100: 46853 | P100: PABLM1000004793 | Q100: 20Mb | R100: Dedicado | S100: 350.62 | T100: 4G-USB-VIVO-11942876965-20Gb | U100: 4G-USB | V100: VIVO | W100: (11)94287-6965 | X100: 20Gb | Y100: 104.05 | Z100: --- | AB100: 10.100.10.112 | AC100: 10.3.91.0/24 | AD100: --- | AE100: =SUM(K100+S100+Y100+AA100) -> 899.37 | AF100: FGT40FTK22099VM2 | AG100: 46122 | AH100: Loja base com kit (switch, antena e firewall)
...

Sheet Resumo_Links
A1: Operadoras | B1: Qtde de links | C1: Lojas | D1: EC-CDs-Datacenter | E1: Gerente | F1: Contato | G1: Contato | H1: Suporte | I1: Escalonamento depois de 6 Horas
A2: Embratel | B2: =SUM(C2:D2) -> 4 | C2: =COUNTIF('Detalhes Links Lojas'!D2:D216,"Embratel") + COUNTIF('Detalhes Links Lojas'!L2:L216,"Embratel") -> 4 | D2: =COUNTIF('Detalhes EC-EQX-CDs'!$A$2:AF7,"Embratel") -> 0 | E2: Roberto/Aurelio | F2: (11) 96600-9086 / 11 99183-6240 | G2: 11 96600-9086 / 11 99183-6240 | H2: Caspo (11) 99365-7505 | I2: Evandro 11 2121-2721 | K2: Jose Eduardo 11 9 9259-6352
A3: Claro | B3: =SUM(C3:D3) -> 176 | C3: =COUNTIF('Detalhes Links Lojas'!D3:D217,"Claro") + COUNTIF('Detalhes Links Lojas'!L3:L217,"Claro") -> 174 | D3: =COUNTIF('Detalhes EC-EQX-CDs'!$A$2:AF8,"Claro") -> 2 | E3: Roberto/Aurelio | G3: 11 96600-9086 / 11 99183-6240 | H3: Caspo (11) 99365-7505 | I3: Evandro 11 2121-2721 | K3: Jose Eduardo 11 9 9259-6352
A4: Vivo | B4: =SUM(C4:D4) -> 80 | C4: =COUNTIF('Detalhes Links Lojas'!D2:D216,"Vivo") + COUNTIF('Detalhes Links Lojas'!L2:L216,"Vivo") -> 76 | D4: =COUNTIF('Detalhes EC-EQX-CDs'!$A$2:AF9,"Vivo") -> 4 | E4: Jorge/Julien | F4: (11) 99956-2671 / (51) 98405-7640 | G4: 11 94288-6345 / 8405-7640 | H4: Bhering (11)97504-1171 | I4: Ricardo (11) 99909-5181 /Douglas 1199551-6968
A5: Fibrion | B5: =SUM(C5:D5) -> 29 | C5: =COUNTIF('Detalhes Links Lojas'!D2:D216,"Fibrion") + COUNTIF('Detalhes Links Lojas'!L2:L216,"Fibrion") -> 28 | D5: =COUNTIF('Detalhes EC-EQX-CDs'!$A$2:AF10,"Fibrion") -> 1 | E5: Patricia/Cristina Midori | F5: (11) 99869-0974 / (11) 94730-4945 | G5: 11 94730-4945 / 11 94737-6219 | H5: 11 4934-7000 | I5: Angelica 11 96397-1965 / Humberto 11 94028-8104
A6: Vero | B6: =SUM(C6:D6) -> 66 | C6: =COUNTIF('Detalhes Links Lojas'!D1:D216,"Vero") + COUNTIF('Detalhes Links Lojas'!L2:L216,"Vero") -> 66 | D6: =COUNTIF('Detalhes EC-EQX-CDs'!$A$2:AF11,"Vero") -> 0 | E6: Fernando Ciscar | F6: (11) 94546-3623 | G6: 11935038242 | H6: 11 3500-1152/ 11 5043-5856 | I6: 1195185-9620/ 1193585-3415
A7: Mundivox | B7: =SUM(C7:D7) -> 25 | C7: =COUNTIF('Detalhes Links Lojas'!D2:D216,"Mundivox") + COUNTIF('Detalhes Links Lojas'!L2:L216,"Mundivox") -> 24 | D7: =COUNTIF('Detalhes EC-EQX-CDs'!$A$2:AF12,"Mundivox") -> 1 | E7: Cesar Padovese | F7: (11) 97572-1422 | G7: 11 95034-2020 | H7: Maria Clara 21 96822-5988 | I7: Jonio 21 9 7377-1427
A8: Oi | B8: =SUM(C8:D8) -> 3 | C8: =COUNTIF('Detalhes Links Lojas'!D2:D216,"Oi") + COUNTIF('Detalhes Links Lojas'!L2:L216,"Oi") -> 3 | D8: =COUNTIF('Detalhes EC-EQX-CDs'!$A$2:AF13,"Oi") -> 0 | E8: Juliana/Cesar | F8: (11) 98914 4855 | G8: 11 96721-0488 / 11 98914-4855 | H8: Jackson 21 96958-2554 | I8: Washington 2196958-2526
A9: Algar | B9: =SUM(C9:D9) -> 24 | C9: =COUNTIF('Detalhes Links Lojas'!D2:D216,"Algar") + COUNTIF('Detalhes Links Lojas'!L2:L216,"Algar") -> 21 | D9: =COUNTIF('Detalhes EC-EQX-CDs'!$A$2:AF14,"Algar") -> 3 | E9: Daniel Lassalva/ Arthur | F9: 11 98500-7777 | G9: 11 98500-7777/ 11 96000-8867 | H9: 349889-2822
A10: SEA Telecom | B10: =SUM(C10:D10) -> 1 | C10: =COUNTIF('Detalhes Links Lojas'!D4:D219,"SEA Telecom") + COUNTIF('Detalhes Links Lojas'!L4:L219,"SEA Telecom") -> 1 | D10: =COUNTIF('Detalhes EC-EQX-CDs'!$A$2:AF15,"Sea Telecom") -> 0 | G10: 91 2992-0230 | H10: 91 2992-0230
A11: SP18 | B11: =SUM(C11:D11) -> 2 | C11: =COUNTIF('Detalhes Links Lojas'!D5:D220,"SP18") + COUNTIF('Detalhes Links Lojas'!L5:L220,"SP18") -> 2 | D11: =COUNTIF('Detalhes EC-EQX-CDs'!$A$2:AF16,"SP18") -> 0 | E11: Oliver | G11: 11 32100018 - 11 995282246
A12: Tesa | B12: =SUM(C12:D12) -> 2 | C12: =COUNTIF('Detalhes Links Lojas'!D6:D221,"Tesa") + COUNTIF('Detalhes Links Lojas'!L6:L221,"Tesa") -> 2 | D12: =COUNTIF('Detalhes EC-EQX-CDs'!$A$2:AF17,"Tesa") -> 0 | E12: Marcos Souza | F12: (11) 94766-4053 | G12: 8000383838 | H12: 114302-0001
A13: Wipi | B13: =SUM(C13:D13) -> 1 | C13: =COUNTIF('Detalhes Links Lojas'!D2:D216,"Wipi") + COUNTIF('Detalhes Links Lojas'!L2:L216,"Wipi") -> 1 | D13: =COUNTIF('Detalhes EC-EQX-CDs'!$A$2:AF18,"Wipi") -> 0 | G13: 8000710000
A14: Megatelecom | B14: =SUM(C14:D14) -> 1 | C14: =COUNTIF('Detalhes Links Lojas'!D2:D216,"Megatelecom") + COUNTIF('Detalhes Links Lojas'!L2:L216,"Megatelecom") -> 0 | D14: =COUNTIF('Detalhes EC-EQX-CDs'!$A$2:AF19,"Megatelecom") -> 1 | G14: 11 2110-1000 | H14: 11 2110-1000
A15: WFT / AST | B15: =SUM(C15:D15) -> 1 | C15: =COUNTIF('Detalhes Links Lojas'!D2:D216,"WFT/AST") + COUNTIF('Detalhes Links Lojas'!L2:L216,"WFT/AST") -> 1 | D15: =COUNTIF('Detalhes EC-EQX-CDs'!$A$2:AF20,"WFT/AST") -> 0 | E15: Wedja Florêncio | F15: (81) 9 8970-2098 | G15: 81 8970-2098 | H15: 81 9761-4249
A16: Vtal | B16: =SUM(C16:D16) -> 21 | C16: =COUNTIF('Detalhes Links Lojas'!D2:D216,"Vtal") + COUNTIF('Detalhes Links Lojas'!L2:L216,"Vtal") -> 21 | D16: =COUNTIF('Detalhes EC-EQX-CDs'!$A$2:AF21,"Vtal") -> 0 | E16: Allan | G16: 11 99869-0974 | H16: 08001255060 (opção 2) | I16: Wilson Kael 41 99292-9050
A17: Irapido | B17: =SUM(C17:D17) -> 3 | C17: =COUNTIF('Detalhes Links Lojas'!D2:D216,"Irapido") + COUNTIF('Detalhes Links Lojas'!L2:L216,"Irapido") -> 3 | D17: =COUNTIF('Detalhes EC-EQX-CDs'!$A$2:AF22,"ITS Brasil") -> 0 | E17: Vinicius | G17: 91 8123-6353 | H17: 91 8123-6353 - Vinicius
A18: ITS Brasil | B18: =SUM(C18:D18) -> 1 | C18: =COUNTIF('Detalhes Links Lojas'!D3:D217,"ITS Brasil") + COUNTIF('Detalhes Links Lojas'!L3:L217,"ITS Brasil") -> 1 | D18: =COUNTIF('Detalhes EC-EQX-CDs'!$A$2:AF23,"Irapido") -> 0 | E18: Amanda Santos | G18: 71 3402-0856 | H18: 71 3402-0800 - 71 2104-2244 | I18: https://itsbrasil.sz.chat/webchat/v2/?cid=61c0dd992ad99100111fc632&host=https://itsbrasil.sz.chat
A19: Total | B19: =SUM(B2:B17) -> 439 | C19: =SUM(C2:C17) -> 427 | D19: =SUM(D2:D17) -> 12
